Workbook

Sheet Stage 1
A1: Stage 1 · Project Familiarisation & Initiation — desglose por entregable y empresa (AUD)
A2: Importe = horas × tarifa de venta (pestaña Datos). Reparto por empresa según el tipo de cada entregable (pestaña Escenarios).
B4: Reducción de precio del Stage 1 | C4: =Resumen!$C$5 -> 0 | D4: =Resumen!$C$6 -> IDOM | E4: Se cambian en el panel de control de la pestaña Resumen (porcentaje y quién la absorbe).
A6: Oferta original | F6: Reparto | J6: =Escenarios!I$10&" · "&Escenarios!I$11 -> Escenario 1 · Original | P6: =Escenarios!J$10&" · "&Escenarios!J$11 -> Escenario 2 · Sin las 4 tareas de Plan Safe | V6: =Escenarios!K$10&" · "&Escenarios!K$11 -> Escenario 3 · Sin tareas Plan Safe ni SSC | AB6: =Escenarios!L$10&" · "&Escenarios!L$11 -> Escenario 4 · Sin SSC, tareas Plan Safe al 50 %
A7: Código | B7: Entregable | C7: Tipo | D7: Horas base | E7: Importe base | F7: % IDOM | G7: % Plan Safe | H7: % Synertec | I7: % INVAP | J7: Horas | K7: IDOM | L7: Plan Safe | M7: Synertec | N7: INVAP | O7: Total | P7: Horas | Q7: IDOM | R7: Plan Safe | S7: Synertec | T7: INVAP | U7: Total | V7: Horas | W7: IDOM | X7: Plan Safe | Y7: Synertec | Z7: INVAP | AA7: Total | AB7: Horas | AC7: IDOM | AD7: Plan Safe | AE7: Synertec | AF7: INVAP | AG7: Total
A8: S1 | B8: Safety Assurance Plan / Safety Integration Plan | C8: =INDEX(Escenarios!$D$12:$D$36,MATCH($A8,Escenarios!$A$12:$A$36,0)) -> Compartido | D8: =SUMIFS(Datos!$H$5:$H$291,Datos!$E$5:$E$291,$A8,Datos!$F$5:$F$291,"S1") -> 625 | E8: =SUMIFS(Datos!$J$5:$J$291,Datos!$E$5:$E$291,$A8,Datos!$F$5:$F$291,"S1") -> 148179.67 | F8: =INDEX(Escenarios!$E$12:$E$36,MATCH($A8,Escenarios!$A$12:$A$36,0)) -> 0.9 | G8: =INDEX(Escenarios!$F$12:$F$36,MATCH($A8,Escenarios!$A$12:$A$36,0)) -> 0.1 | H8: =INDEX(Escenarios!$G$12:$G$36,MATCH($A8,Escenarios!$A$12:$A$36,0)) -> 0 | I8: =INDEX(Escenarios!$H$12:$H$36,MATCH($A8,Escenarios!$A$12:$A$36,0)) -> 0 | J8: =IF(INDEX(Escenarios!$I$12:$I$36,MATCH($A8,Escenarios!$A$12:$A$36,0))>0,$D8,0) -> 625 | K8: =$E8*INDEX(Escenarios!$I$12:$I$36,MATCH($A8,Escenarios!$A$12:$A$36,0))*F8 -> 133361.71 | L8: =$E8*INDEX(Escenarios!$I$12:$I$36,MATCH($A8,Escenarios!$A$12:$A$36,0))*G8 -> 14817.968 | M8: =$E8*INDEX(Escenarios!$I$12:$I$36,MATCH($A8,Escenarios!$A$12:$A$36,0))*H8 -> 0 | N8: =$E8*INDEX(Escenarios!$I$12:$I$36,MATCH($A8,Escenarios!$A$12:$A$36,0))*I8 -> 0 | O8: =SUM(K8:N8) -> 148179.67 | P8: =IF(INDEX(Escenarios!$J$12:$J$36,MATCH($A8,Escenarios!$A$12:$A$36,0))>0,$D8,0) -> 625 | Q8: =$E8*INDEX(Escenarios!$J$12:$J$36,MATCH($A8,Escenarios!$A$12:$A$36,0))*F8 -> 133361.71 | R8: =$E8*INDEX(Escenarios!$J$12:$J$36,MATCH($A8,Escenarios!$A$12:$A$36,0))*G8 -> 14817.968 | S8: =$E8*INDEX(Escenarios!$J$12:$J$36,MATCH($A8,Escenarios!$A$12:$A$36,0))*H8 -> 0 | T8: =$E8*INDEX(Escenarios!$J$12:$J$36,MATCH($A8,Escenarios!$A$12:$A$36,0))*I8 -> 0 | U8: =SUM(Q8:T8) -> 148179.67 | V8: =IF(INDEX(Escenarios!$K$12:$K$36,MATCH($A8,Escenarios!$A$12:$A$36,0))>0,$D8,0) -> 625 | W8: =$E8*INDEX(Escenarios!$K$12:$K$36,MATCH($A8,Escenarios!$A$12:$A$36,0))*F8 -> 133361.71 | X8: =$E8*INDEX(Escenarios!$K$12:$K$36,MATCH($A8,Escenarios!$A$12:$A$36,0))*G8 -> 14817.968 | Y8: =$E8*INDEX(Escenarios!$K$12:$K$36,MATCH($A8,Escenarios!$A$12:$A$36,0))*H8 -> 0 | Z8: =$E8*INDEX(Escenarios!$K$12:$K$36,MATCH($A8,Escenarios!$A$12:$A$36,0))*I8 -> 0 | AA8: =SUM(W8:Z8) -> 148179.67 | AB8: =IF(INDEX(Escenarios!$L$12:$L$36,MATCH($A8,Escenarios!$A$12:$A$36,0))>0,$D8,0) -> 625 | AC8: =$E8*INDEX(Escenarios!$L$12:$L$36,MATCH($A8,Escenarios!$A$12:$A$36,0))*F8 -> 133361.71 | AD8: =$E8*INDEX(Escenarios!$L$12:$L$36,MATCH($A8,Escenarios!$A$12:$A$36,0))*G8 -> 14817.968 | AE8: =$E8*INDEX(Escenarios!$L$12:$L$36,MATCH($A8,Escenarios!$A$12:$A$36,0))*H8 -> 0 | AF8: =$E8*INDEX(Escenarios!$L$12:$L$36,MATCH($A8,Escenarios!$A$12:$A$36,0))*I8 -> 0 | AG8: =SUM(AC8:AF8) -> 148179.67
A9: Pre | B9: Conceptual Design Verification | C9: =INDEX(Escenarios!$D$12:$D$36,MATCH($A9,Escenarios!$A$12:$A$36,0)) -> INVAP | D9: =SUMIFS(Datos!$H$5:$H$291,Datos!$E$5:$E$291,$A9,Datos!$F$5:$F$291,"S1") -> 345 | E9: =SUMIFS(Datos!$J$5:$J$291,Datos!$E$5:$E$291,$A9,Datos!$F$5:$F$291,"S1") -> 78836.1 | F9: =INDEX(Escenarios!$E$12:$E$36,MATCH($A9,Escenarios!$A$12:$A$36,0)) -> 0 | G9: =INDEX(Escenarios!$F$12:$F$36,MATCH($A9,Escenarios!$A$12:$A$36,0)) -> 0 | H9: =INDEX(Escenarios!$G$12:$G$36,MATCH($A9,Escenarios!$A$12:$A$36,0)) -> 0 | I9: =INDEX(Escenarios!$H$12:$H$36,MATCH($A9,Escenarios!$A$12:$A$36,0)) -> 1 | J9: =IF(INDEX(Escenarios!$I$12:$I$36,MATCH($A9,Escenarios!$A$12:$A$36,0))>0,$D9,0) -> 345 | K9: =$E9*INDEX(Escenarios!$I$12:$I$36,MATCH($A9,Escenarios!$A$12:$A$36,0))*F9 -> 0 | L9: =$E9*INDEX(Escenarios!$I$12:$I$36,MATCH($A9,Escenarios!$A$12:$A$36,0))*G9 -> 0 | M9: =$E9*INDEX(Escenarios!$I$12:$I$36,MATCH($A9,Escenarios!$A$12:$A$36,0))*H9 -> 0 | N9: =$E9*INDEX(Escenarios!$I$12:$I$36,MATCH($A9,Escenarios!$A$12:$A$36,0))*I9 -> 78836.1 | O9: =SUM(K9:N9) -> 78836.1 | P9: =IF(INDEX(Escenarios!$J$12:$J$36,MATCH($A9,Escenarios!$A$12:$A$36,0))>0,$D9,0) -> 345 | Q9: =$E9*INDEX(Escenarios!$J$12:$J$36,MATCH($A9,Escenarios!$A$12:$A$36,0))*F9 -> 0 | R9: =$E9*INDEX(Escenarios!$J$12:$J$36,MATCH($A9,Escenarios!$A$12:$A$36,0))*G9 -> 0 | S9: =$E9*INDEX(Escenarios!$J$12:$J$36,MATCH($A9,Escenarios!$A$12:$A$36,0))*H9 -> 0 | T9: =$E9*INDEX(Escenarios!$J$12:$J$36,MATCH($A9,Escenarios!$A$12:$A$36,0))*I9 -> 78836.1 | U9: =SUM(Q9:T9) -> 78836.1 | V9: =IF(INDEX(Escenarios!$K$12:$K$36,MATCH($A9,Escenarios!$A$12:$A$36,0))>0,$D9,0) -> 345 | W9: =$E9*INDEX(Escenarios!$K$12:$K$36,MATCH($A9,Escenarios!$A$12:$A$36,0))*F9 -> 0 | X9: =$E9*INDEX(Escenarios!$K$12:$K$36,MATCH($A9,Escenarios!$A$12:$A$36,0))*G9 -> 0 | Y9: =$E9*INDEX(Escenarios!$K$12:$K$36,MATCH($A9,Escenarios!$A$12:$A$36,0))*H9 -> 0 | Z9: =$E9*INDEX(Escenarios!$K$12:$K$36,MATCH($A9,Escenarios!$A$12:$A$36,0))*I9 -> 78836.1 | AA9: =SUM(W9:Z9) -> 78836.1 | AB9: =IF(INDEX(Escenarios!$L$12:$L$36,MATCH($A9,Escenarios!$A$12:$A$36,0))>0,$D9,0) -> 345 | AC9: =$E9*INDEX(Escenarios!$L$12:$L$36,MATCH($A9,Escenarios!$A$12:$A$36,0))*F9 -> 0 | AD9: =$E9*INDEX(Escenarios!$L$12:$L$36,MATCH($A9,Escenarios!$A$12:$A$36,0))*G9 -> 0 | AE9: =$E9*INDEX(Escenarios!$L$12:$L$36,MATCH($A9,Escenarios!$A$12:$A$36,0))*H9 -> 0 | AF9: =$E9*INDEX(Escenarios!$L$12:$L$36,MATCH($A9,Escenarios!$A$12:$A$36,0))*I9 -> 78836.1 | AG9: =SUM(AC9:AF9) -> 78836.1
A10: S2 | B10: Human Factors Assurance Plan / Human Factors Integration Plan (HFIP) | C10: =INDEX(Escenarios!$D$12:$D$36,MATCH($A10,Escenarios!$A$12:$A$36,0)) -> Plan Safe | D10: =SUMIFS(Datos!$H$5:$H$291,Datos!$E$5:$E$291,$A10,Datos!$F$5:$F$291,"S1") -> 270 | E10: =SUMIFS(Datos!$J$5:$J$291,Datos!$E$5:$E$291,$A10,Datos!$F$5:$F$291,"S1") -> 62875.575 | F10: =INDEX(Escenarios!$E$12:$E$36,MATCH($A10,Escenarios!$A$12:$A$36,0)) -> 0 | G10: =INDEX(Escenarios!$F$12:$F$36,MATCH($A10,Escenarios!$A$12:$A$36,0)) -> 1 | H10: =INDEX(Escenarios!$G$12:$G$36,MATCH($A10,Escenarios!$A$12:$A$36,0)) -> 0 | I10: =INDEX(Escenarios!$H$12:$H$36,MATCH($A10,Escenarios!$A$12:$A$36,0)) -> 0 | J10: =IF(INDEX(Escenarios!$I$12:$I$36,MATCH($A10,Escenarios!$A$12:$A$36,0))>0,$D10,0) -> 270 | K10: =$E10*INDEX(Escenarios!$I$12:$I$36,MATCH($A10,Escenarios!$A$12:$A$36,0))*F10 -> 0 | L10: =$E10*INDEX(Escenarios!$I$12:$I$36,MATCH($A10,Escenarios!$A$12:$A$36,0))*G10 -> 62875.575 | M10: =$E10*INDEX(Escenarios!$I$12:$I$36,MATCH($A10,Escenarios!$A$12:$A$36,0))*H10 -> 0 | N10: =$E10*INDEX(Escenarios!$I$12:$I$36,MATCH($A10,Escenarios!$A$12:$A$36,0))*I10 -> 0 | O10: =SUM(K10:N10) -> 62875.575 | P10: =IF(INDEX(Escenarios!$J$12:$J$36,MATCH($A10,Escenarios!$A$12:$A$36,0))>0,$D10,0) -> 0 | Q10: =$E10*INDEX(Escenarios!$J$12:$J$36,MATCH($A10,Escenarios!$A$12:$A$36,0))*F10 -> 0 | R10: =$E10*INDEX(Escenarios!$J$12:$J$36,MATCH($A10,Escenarios!$A$12:$A$36,0))*G10 -> 0 | S10: =$E10*INDEX(Escenarios!$J$12:$J$36,MATCH($A10,Escenarios!$A$12:$A$36,0))*H10 -> 0 | T10: =$E10*INDEX(Escenarios!$J$12:$J$36,MATCH($A10,Escenarios!$A$12:$A$36,0))*I10 -> 0 | U10: =SUM(Q10:T10) -> 0 | V10: =IF(INDEX(Escenarios!$K$12:$K$36,MATCH($A10,Escenarios!$A$12:$A$36,0))>0,$D10,0) -> 0 | W10: =$E10*INDEX(Escenarios!$K$12:$K$36,MATCH($A10,Escenarios!$A$12:$A$36,0))*F10 -> 0 | X10: =$E10*INDEX(Escenarios!$K$12:$K$36,MATCH($A10,Escenarios!$A$12:$A$36,0))*G10 -> 0 | Y10: =$E10*INDEX(Escenarios!$K$12:$K$36,MATCH($A10,Escenarios!$A$12:$A$36,0))*H10 -> 0 | Z10: =$E10*INDEX(Escenarios!$K$12:$K$36,MATCH($A10,Escenarios!$A$12:$A$36,0))*I10 -> 0 | AA10: =SUM(W10:Z10) -> 0 | AB10: =IF(INDEX(Escenarios!$L$12:$L$36,MATCH($A10,Escenarios!$A$12:$A$36,0))>0,$D10,0) -> 270 | AC10: =$E10*INDEX(Escenarios!$L$12:$L$36,MATCH($A10,Escenarios!$A$12:$A$36,0))*F10 -> 0 | AD10: =$E10*INDEX(Escenarios!$L$12:$L$36,MATCH($A10,Escenarios!$A$12:$A$36,0))*G10 -> 31437.787 | AE10: =$E10*INDEX(Escenarios!$L$12:$L$36,MATCH($A10,Escenarios!$A$12:$A$36,0))*H10 -> 0 | AF10: =$E10*INDEX(Escenarios!$L$12:$L$36,MATCH($A10,Escenarios!$A$12:$A$36,0))*I10 -> 0 | AG10: =SUM(AC10:AF10) -> 31437.787
A11: S3 | B11: Human Factors Hazards Identification and Control Plan (HFHICP) | C11: =INDEX(Escenarios!$D$12:$D$36,MATCH($A11,Escenarios!$A$12:$A$36,0)) -> Plan Safe | D11: =SUMIFS(Datos!$H$5:$H$291,Datos!$E$5:$E$291,$A11,Datos!$F$5:$F$291,"S1") -> 195 | E11: =SUMIFS(Datos!$J$5:$J$291,Datos!$E$5:$E$291,$A11,Datos!$F$5:$F$291,"S1") -> 45191.475 | F11: =INDEX(Escenarios!$E$12:$E$36,MATCH($A11,Escenarios!$A$12:$A$36,0)) -> 0 | G11: =INDEX(Escenarios!$F$12:$F$36,MATCH($A11,Escenarios!$A$12:$A$36,0)) -> 1 | H11: =INDEX(Escenarios!$G$12:$G$36,MATCH($A11,Escenarios!$A$12:$A$36,0)) -> 0 | I11: =INDEX(Escenarios!$H$12:$H$36,MATCH($A11,Escenarios!$A$12:$A$36,0)) -> 0 | J11: =IF(INDEX(Escenarios!$I$12:$I$36,MATCH($A11,Escenarios!$A$12:$A$36,0))>0,$D11,0) -> 195 | K11: =$E11*INDEX(Escenarios!$I$12:$I$36,MATCH($A11,Escenarios!$A$12:$A$36,0))*F11 -> 0 | L11: =$E11*INDEX(Escenarios!$I$12:$I$36,MATCH($A11,Escenarios!$A$12:$A$36,0))*G11 -> 45191.475 | M11: =$E11*INDEX(Escenarios!$I$12:$I$36,MATCH($A11,Escenarios!$A$12:$A$36,0))*H11 -> 0 | N11: =$E11*INDEX(Escenarios!$I$12:$I$36,MATCH($A11,Escenarios!$A$12:$A$36,0))*I11 -> 0 | O11: =SUM(K11:N11) -> 45191.475 | P11: =IF(INDEX(Escenarios!$J$12:$J$36,MATCH($A11,Escenarios!$A$12:$A$36,0))>0,$D11,0) -> 0 | Q11: =$E11*INDEX(Escenarios!$J$12:$J$36,MATCH($A11,Escenarios!$A$12:$A$36,0))*F11 -> 0 | R11: =$E11*INDEX(Escenarios!$J$12:$J$36,MATCH($A11,Escenarios!$A$12:$A$36,0))*G11 -> 0 | S11: =$E11*INDEX(Escenarios!$J$12:$J$36,MATCH($A11,Escenarios!$A$12:$A$36,0))*H11 -> 0 | T11: =$E11*INDEX(Escenarios!$J$12:$J$36,MATCH($A11,Escenarios!$A$12:$A$36,0))*I11 -> 0 | U11: =SUM(Q11:T11) -> 0 | V11: =IF(INDEX(Escenarios!$K$12:$K$36,MATCH($A11,Escenarios!$A$12:$A$36,0))>0,$D11,0) -> 0 | W11: =$E11*INDEX(Escenarios!$K$12:$K$36,MATCH($A11,Escenarios!$A$12:$A$36,0))*F11 -> 0 | X11: =$E11*INDEX(Escenarios!$K$12:$K$36,MATCH($A11,Escenarios!$A$12:$A$36,0))*G11 -> 0 | Y11: =$E11*INDEX(Escenarios!$K$12:$K$36,MATCH($A11,Escenarios!$A$12:$A$36,0))*H11 -> 0 | Z11: =$E11*INDEX(Escenarios!$K$12:$K$36,MATCH($A11,Escenarios!$A$12:$A$36,0))*I11 -> 0 | AA11: =SUM(W11:Z11) -> 0 | AB11: =IF(INDEX(Escenarios!$L$12:$L$36,MATCH($A11,Escenarios!$A$12:$A$36,0))>0,$D11,0) -> 195 | AC11: =$E11*INDEX(Escenarios!$L$12:$L$36,MATCH($A11,Escenarios!$A$12:$A$36,0))*F11 -> 0 | AD11: =$E11*INDEX(Escenarios!$L$12:$L$36,MATCH($A11,Escenarios!$A$12:$A$36,0))*G11 -> 22595.737 | AE11: =$E11*INDEX(Escenarios!$L$12:$L$36,MATCH($A11,Escenarios!$A$12:$A$36,0))*H11 -> 0 | AF11: =$E11*INDEX(Escenarios!$L$12:$L$36,MATCH($A11,Escenarios!$A$12:$A$36,0))*I11 -> 0 | AG11: =SUM(AC11:AF11) -> 22595.737
B12: Subtotal Stage 1 (entregables) | D12: =SUM(D8:D11) -> 1435 | E12: =SUM(E8:E11) -> 335082.83 | J12: =SUM(J8:J11) -> 1435 | K12: =SUM(K8:K11) -> 133361.71 | L12: =SUM(L8:L11) -> 122885.02 | M12: =SUM(M8:M11) -> 0 | N12: =SUM(N8:N11) -> 78836.1 | O12: =SUM(O8:O11) -> 335082.83 | P12: =SUM(P8:P11) -> 970 | Q12: =SUM(Q8:Q11) -> 133361.71 | ... AG12: =SUM(AG8:AG11) -> 281049.3
B13: ="Reducción de precio del Stage 1 ("&TEXT(Resumen!$C$5,"0.0%")&", absorbe "&Resumen!$C$6&")" -> Reducción de precio del Stage 1 (0.0%, absorbe IDOM) | K13: =-Resumen!$C$5*IF(Resumen!$C$6="IDOM",O12,K12) -> 0 | L13: =-Resumen!$C$5*IF(Resumen!$C$6="IDOM",0,L12) -> 0 | M13: =-Resumen!$C$5*IF(Resumen!$C$6="IDOM",0,M12) -> 0 | N13: =-Resumen!$C$5*IF(Resumen!$C$6="IDOM",0,N12) -> 0 | O13: =SUM(K13:N13) -> 0 | Q13: =-Resumen!$C$5*IF(Resumen!$C$6="IDOM",U12,Q12) -> 0 | R13: =-Resumen!$C$5*IF(Resumen!$C$6="IDOM",0,R12) -> 0 | S13: =-Resumen!$C$5*IF(Resumen!$C$6="IDOM",0,S12) -> 0 | T13: =-Resumen!$C$5*IF(Resumen!$C$6="IDOM",0,T12) -> 0 | U13: =SUM(Q13:T13) -> 0 | W13: =-Resumen!$C$5*IF(Resumen!$C$6="IDOM",AA12,W12) -> 0 | X13: =-Resumen!$C$5*IF(Resumen!$C$6="IDOM",0,X12) -> 0 | Y13: =-Resumen!$C$5*IF(Resumen!$C$6="IDOM",0,Y12) -> 0 | Z13: =-Resumen!$C$5*IF(Resumen!$C$6="IDOM",0,Z12) -> 0 | AA13: =SUM(W13:Z13) -> 0 | AC13: =-Resumen!$C$5*IF(Resumen!$C$6="IDOM",AG12,AC12) -> 0 | AD13: =-Resumen!$C$5*IF(Resumen!$C$6="IDOM",0,AD12) -> 0 | AE13: =-Resumen!$C$5*IF(Resumen!$C$6="IDOM",0,AE12) -> 0 | AF13: =-Resumen!$C$5*IF(Resumen!$C$6="IDOM",0,AF12) -> 0 | AG13: =SUM(AC13:AF13) -> 0
B14: TOTAL STAGE 1 | D14: =D12 -> 1435 | E14: =E12 -> 335082.83 | J14: =J12 -> 1435 | K14: =K12+K13 -> 133361.71 | L14: =L12+L13 -> 122885.02 | M14: =M12+M13 -> 0 | N14: =N12+N13 -> 78836.1 | O14: =O12+O13 -> 335082.83 | P14: =P12 -> 970 | Q14: =Q12+Q13 -> 133361.71 | R14: =R12+R13 -> 14817.968 | S14: =S12+S13 -> 0 | T14: =T12+T13 -> 78836.1 | U14: =U12+U13 -> 227015.77 | V14: =V12 -> 970 | W14: =W12+W13 -> 133361.71 | X14: =X12+X13 -> 14817.968 | Y14: =Y12+Y13 -> 0 | Z14: =Z12+Z13 -> 78836.1 | AA14: =AA12+AA13 -> 227015.77 | AB14: =AB12 -> 1435 | AC14: =AC12+AC13 -> 133361.71 | AD14: =AD12+AD13 -> 68851.492 | AE14: =AE12+AE13 -> 0 | AF14: =AF12+AF13 -> 78836.1 | AG14: =AG12+AG13 -> 281049.3
B16: Referencia: oferta original por empresa (sin escenarios ni ajustes) | E16: =SUM(F16:I16) -> 335082.83 | F16: =SUMPRODUCT($E$8:$E$11,F$8:F$11) -> 133361.71 | G16: =SUMPRODUCT($E$8:$E$11,G$8:G$11) -> 122885.02 | H16: =SUMPRODUCT($E$8:$E$11,H$8:H$11) -> 0 | I16: =SUMPRODUCT($E$8:$E$11,I$8:I$11) -> 78836.1

Sheet Stage 2
A1: Stage 2 · Concept Design — desglose por entregable y empresa (AUD)
A2: Importe = horas × tarifa de venta (pestaña Datos). Reparto por empresa según el tipo de cada entregable (pestaña Escenarios).
B4: Descontar el retrabajo | C4: No | D4: =Escenarios!$B$8 -> 0.35 | E4: Sí = se quita la reserva de retrabajo del precio de IDOM en el Stage 2 (recargo de D4 sobre sus tareas, editable en Escenarios).
A6: Oferta original | F6: Reparto | J6: =Escenarios!I$10&" · "&Escenarios!I$11 -> Escenario 1 · Original | P6: =Escenarios!J$10&" · "&Escenarios!J$11 -> Escenario 2 · Sin las 4 tareas de Plan Safe | V6: =Escenarios!K$10&" · "&Escenarios!K$11 -> Escenario 3 · Sin tareas Plan Safe ni SSC | AB6: =Escenarios!L$10&" · "&Escenarios!L$11 -> Escenario 4 · Sin SSC, tareas Plan Safe al 50 %
A7: Código | B7: Entregable | C7: Tipo | D7: Horas base | E7: Importe base | F7: % IDOM | G7: % Plan Safe | H7: % Synertec | I7: % INVAP | J7: Horas | K7: IDOM | L7: Plan Safe | M7: Synertec | N7: INVAP | O7: Total | P7: Horas | Q7: IDOM | R7: Plan Safe | S7: Synertec | T7: INVAP | U7: Total | V7: Horas | W7: IDOM | X7: Plan Safe | Y7: Synertec | Z7: INVAP | AA7: Total | AB7: Horas | AC7: IDOM | AD7: Plan Safe | AE7: Synertec | AF7: INVAP | AG7: Total
A8: E94 | B8: Radiological Zoning Layout drawing(s) | C8: =INDEX(Escenarios!$D$12:$D$36,MATCH($A8,Escenarios!$A$12:$A$36,0)) -> IDOM | D8: =SUMIFS(Datos!$H$5:$H$291,Datos!$E$5:$E$291,$A8,Datos!$F$5:$F$291,"S2") -> 185 | E8: =SUMIFS(Datos!$J$5:$J$291,Datos!$E$5:$E$291,$A8,Datos!$F$5:$F$291,"S2") -> 35206.5 | F8: =INDEX(Escenarios!$E$12:$E$36,MATCH($A8,Escenarios!$A$12:$A$36,0)) -> 1 | G8: =INDEX(Escenarios!$F$12:$F$36,MATCH($A8,Escenarios!$A$12:$A$36,0)) -> 0 | H8: =INDEX(Escenarios!$G$12:$G$36,MATCH($A8,Escenarios!$A$12:$A$36,0)) -> 0 | I8: =INDEX(Escenarios!$H$12:$H$36,MATCH($A8,Escenarios!$A$12:$A$36,0)) -> 0 | J8: =IF(INDEX(Escenarios!$I$12:$I$36,MATCH($A8,Escenarios!$A$12:$A$36,0))>0,$D8,0) -> 185 | K8: =$E8*INDEX(Escenarios!$I$12:$I$36,MATCH($A8,Escenarios!$A$12:$A$36,0))*F8 -> 35206.5 | L8: =$E8*INDEX(Escenarios!$I$12:$I$36,MATCH($A8,Escenarios!$A$12:$A$36,0))*G8 -> 0 | M8: =$E8*INDEX(Escenarios!$I$12:$I$36,MATCH($A8,Escenarios!$A$12:$A$36,0))*H8 -> 0 | N8: =$E8*INDEX(Escenarios!$I$12:$I$36,MATCH($A8,Escenarios!$A$12:$A$36,0))*I8 -> 0 | O8: =SUM(K8:N8) -> 35206.5 | P8: =IF(INDEX(Escenarios!$J$12:$J$36,MATCH($A8,Escenarios!$A$12:$A$36,0))>0,$D8,0) -> 185 | Q8: =$E8*INDEX(Escenarios!$J$12:$J$36,MATCH($A8,Escenarios!$A$12:$A$36,0))*F8 -> 35206.5 | R8: =$E8*INDEX(Escenarios!$J$12:$J$36,MATCH($A8,Escenarios!$A$12:$A$36,0))*G8 -> 0 | S8: =$E8*INDEX(Escenarios!$J$12:$J$36,MATCH($A8,Escenarios!$A$12:$A$36,0))*H8 -> 0 | T8: =$E8*INDEX(Escenarios!$J$12:$J$36,MATCH($A8,Escenarios!$A$12:$A$36,0))*I8 -> 0 | U8: =SUM(Q8:T8) -> 35206.5 | V8: =IF(INDEX(Escenarios!$K$12:$K$36,MATCH($A8,Escenarios!$A$12:$A$36,0))>0,$D8,0) -> 185 | W8: =$E8*INDEX(Escenarios!$K$12:$K$36,MATCH($A8,Escenarios!$A$12:$A$36,0))*F8 -> 35206.5 | X8: =$E8*INDEX(Escenarios!$K$12:$K$36,MATCH($A8,Escenarios!$A$12:$A$36,0))*G8 -> 0 | Y8: =$E8*INDEX(Escenarios!$K$12:$K$36,MATCH($A8,Escenarios!$A$12:$A$36,0))*H8 -> 0 | Z8: =$E8*INDEX(Escenarios!$K$12:$K$36,MATCH($A8,Escenarios!$A$12:$A$36,0))*I8 -> 0 | AA8: =SUM(W8:Z8) -> 35206.5 | AB8: =IF(INDEX(Escenarios!$L$12:$L$36,MATCH($A8,Escenarios!$A$12:$A$36,0))>0,$D8,0) -> 185 | AC8: =$E8*INDEX(Escenarios!$L$12:$L$36,MATCH($A8,Escenarios!$A$12:$A$36,0))*F8 -> 35206.5 | AD8: =$E8*INDEX(Escenarios!$L$12:$L$36,MATCH($A8,Escenarios!$A$12:$A$36,0))*G8 -> 0 | AE8: =$E8*INDEX(Escenarios!$L$12:$L$36,MATCH($A8,Escenarios!$A$12:$A$36,0))*H8 -> 0 | AF8: =$E8*INDEX(Escenarios!$L$12:$L$36,MATCH($A8,Escenarios!$A$12:$A$36,0))*I8 -> 0 | AG8: =SUM(AC8:AF8) -> 35206.5
A9: S1 | B9: Safety Assurance Plan / Safety Integration Plan | C9: =INDEX(Escenarios!$D$12:$D$36,MATCH($A9,Escenarios!$A$12:$A$36,0)) -> Compartido | D9: =SUMIFS(Datos!$H$5:$H$291,Datos!$E$5:$E$291,$A9,Datos!$F$5:$F$291,"S2") -> 1200 | E9: =SUMIFS(Datos!$J$5:$J$291,Datos!$E$5:$E$291,$A9,Datos!$F$5:$F$291,"S2") -> 284239.2 | F9: =INDEX(Escenarios!$E$12:$E$36,MATCH($A9,Escenarios!$A$12:$A$36,0)) -> 0.9 | G9: =INDEX(Escenarios!$F$12:$F$36,MATCH($A9,Escenarios!$A$12:$A$36,0)) -> 0.1 | H9: =INDEX(Escenarios!$G$12:$G$36,MATCH($A9,Escenarios!$A$12:$A$36,0)) -> 0 | I9: =INDEX(Escenarios!$H$12:$H$36,MATCH($A9,Escenarios!$A$12:$A$36,0)) -> 0 | J9: =IF(INDEX(Escenarios!$I$12:$I$36,MATCH($A9,Escenarios!$A$12:$A$36,0))>0,$D9,0) -> 1200 | K9: =$E9*INDEX(Escenarios!$I$12:$I$36,MATCH($A9,Escenarios!$A$12:$A$36,0))*F9 -> 255815.28 | L9: =$E9*INDEX(Escenarios!$I$12:$I$36,MATCH($A9,Escenarios!$A$12:$A$36,0))*G9 -> 28423.92 | M9: =$E9*INDEX(Escenarios!$I$12:$I$36,MATCH($A9,Escenarios!$A$12:$A$36,0))*H9 -> 0 | N9: =$E9*INDEX(Escenarios!$I$12:$I$36,MATCH($A9,Escenarios!$A$12:$A$36,0))*I9 -> 0 | O9: =SUM(K9:N9) -> 284239.2 | P9: =IF(INDEX(Escenarios!$J$12:$J$36,MATCH($A9,Escenarios!$A$12:$A$36,0))>0,$D9,0) -> 1200 | Q9: =$E9*INDEX(Escenarios!$J$12:$J$36,MATCH($A9,Escenarios!$A$12:$A$36,0))*F9 -> 255815.28 | R9: =$E9*INDEX(Escenarios!$J$12:$J$36,MATCH($A9,Escenarios!$A$12:$A$36,0))*G9 -> 28423.92 | S9: =$E9*INDEX(Escenarios!$J$12:$J$36,MATCH($A9,Escenarios!$A$12:$A$36,0))*H9 -> 0 | T9: =$E9*INDEX(Escenarios!$J$12:$J$36,MATCH($A9,Escenarios!$A$12:$A$36,0))*I9 -> 0 | U9: =SUM(Q9:T9) -> 284239.2 | V9: =IF(INDEX(Escenarios!$K$12:$K$36,MATCH($A9,Escenarios!$A$12:$A$36,0))>0,$D9,0) -> 1200 | W9: =$E9*INDEX(Escenarios!$K$12:$K$36,MATCH($A9,Escenarios!$A$12:$A$36,0))*F9 -> 255815.28 | X9: =$E9*INDEX(Escenarios!$K$12:$K$36,MATCH($A9,Escenarios!$A$12:$A$36,0))*G9 -> 28423.92 | Y9: =$E9*INDEX(Escenarios!$K$12:$K$36,MATCH($A9,Escenarios!$A$12:$A$36,0))*H9 -> 0 | Z9: =$E9*INDEX(Escenarios!$K$12:$K$36,MATCH($A9,Escenarios!$A$12:$A$36,0))*I9 -> 0 | AA9: =SUM(W9:Z9) -> 284239.2 | AB9: =IF(INDEX(Escenarios!$L$12:$L$36,MATCH($A9,Escenarios!$A$12:$A$36,0))>0,$D9,0) -> 1200 | AC9: =$E9*INDEX(Escenarios!$L$12:$L$36,MATCH($A9,Escenarios!$A$12:$A$36,0))*F9 -> 255815.28 | AD9: =$E9*INDEX(Escenarios!$L$12:$L$36,MATCH($A9,Escenarios!$A$12:$A$36,0))*G9 -> 28423.92 | AE9: =$E9*INDEX(Escenarios!$L$12:$L$36,MATCH($A9,Escenarios!$A$12:$A$36,0))*H9 -> 0 | AF9: =$E9*INDEX(Escenarios!$L$12:$L$36,MATCH($A9,Escenarios!$A$12:$A$36,0))*I9 -> 0 | AG9: =SUM(AC9:AF9) -> 284239.2
A10: S17 | B10: ALARP (Optioneering) Study | C10: =INDEX(Escenarios!$D$12:$D$36,MATCH($A10,Escenarios!$A$12:$A$36,0)) -> Compartido | D10: =SUMIFS(Datos!$H$5:$H$291,Datos!$E$5:$E$291,$A10,Datos!$F$5:$F$291,"S2") -> 385 | E10: =SUMIFS(Datos!$J$5:$J$291,Datos!$E$5:$E$291,$A10,Datos!$F$5:$F$291,"S2") -> 90335.175 | F10: =INDEX(Escenarios!$E$12:$E$36,MATCH($A10,Escenarios!$A$12:$A$36,0)) -> 0.9 | G10: =INDEX(Escenarios!$F$12:$F$36,MATCH($A10,Escenarios!$A$12:$A$36,0)) -> 0.1 | H10: =INDEX(Escenarios!$G$12:$G$36,MATCH($A10,Escenarios!$A$12:$A$36,0)) -> 0 | I10: =INDEX(Escenarios!$H$12:$H$36,MATCH($A10,Escenarios!$A$12:$A$36,0)) -> 0 | J10: =IF(INDEX(Escenarios!$I$12:$I$36,MATCH($A10,Escenarios!$A$12:$A$36,0))>0,$D10,0) -> 385 | K10: =$E10*INDEX(Escenarios!$I$12:$I$36,MATCH($A10,Escenarios!$A$12:$A$36,0))*F10 -> 81301.658 | L10: =$E10*INDEX(Escenarios!$I$12:$I$36,MATCH($A10,Escenarios!$A$12:$A$36,0))*G10 -> 9033.5175 | M10: =$E10*INDEX(Escenarios!$I$12:$I$36,MATCH($A10,Escenarios!$A$12:$A$36,0))*H10 -> 0 | N10: =$E10*INDEX(Escenarios!$I$12:$I$36,MATCH($A10,Escenarios!$A$12:$A$36,0))*I10 -> 0 | O10: =SUM(K10:N10) -> 90335.175 | P10: =IF(INDEX(Escenarios!$J$12:$J$36,MATCH($A10,Escenarios!$A$12:$A$36,0))>0,$D10,0) -> 385 | Q10: =$E10*INDEX(Escenarios!$J$12:$J$36,MATCH($A10,Escenarios!$A$12:$A$36,0))*F10 -> 81301.658 | R10: =$E10*INDEX(Escenarios!$J$12:$J$36,MATCH($A10,Escenarios!$A$12:$A$36,0))*G10 -> 9033.5175 | S10: =$E10*INDEX(Escenarios!$J$12:$J$36,MATCH($A10,Escenarios!$A$12:$A$36,0))*H10 -> 0 | T10: =$E10*INDEX(Escenarios!$J$12:$J$36,MATCH($A10,Escenarios!$A$12:$A$36,0))*I10 -> 0 | U10: =SUM(Q10:T10) -> 90335.175 | V10: =IF(INDEX(Escenarios!$K$12:$K$36,MATCH($A10,Escenarios!$A$12:$A$36,0))>0,$D10,0) -> 385 | W10: =$E10*INDEX(Escenarios!$K$12:$K$36,MATCH($A10,Escenarios!$A$12:$A$36,0))*F10 -> 81301.658 | X10: =$E10*INDEX(Escenarios!$K$12:$K$36,MATCH($A10,Escenarios!$A$12:$A$36,0))*G10 -> 9033.5175 | Y10: =$E10*INDEX(Escenarios!$K$12:$K$36,MATCH($A10,Escenarios!$A$12:$A$36,0))*H10 -> 0 | Z10: =$E10*INDEX(Escenarios!$K$12:$K$36,MATCH($A10,Escenarios!$A$12:$A$36,0))*I10 -> 0 | AA10: =SUM(W10:Z10) -> 90335.175 | AB10: =IF(INDEX(Escenarios!$L$12:$L$36,MATCH($A10,Escenarios!$A$12:$A$36,0))>0,$D10,0) -> 385 | AC10: =$E10*INDEX(Escenarios!$L$12:$L$36,MATCH($A10,Escenarios!$A$12:$A$36,0))*F10 -> 81301.658 | AD10: =$E10*INDEX(Escenarios!$L$12:$L$36,MATCH($A10,Escenarios!$A$12:$A$36,0))*G10 -> 9033.5175 | AE10: =$E10*INDEX(Escenarios!$L$12:$L$36,MATCH($A10,Escenarios!$A$12:$A$36,0))*H10 -> 0 | AF10: =$E10*INDEX(Escenarios!$L$12:$L$36,MATCH($A10,Escenarios!$A$12:$A$36,0))*I10 -> 0 | AG10: =SUM(AC10:AF10) -> 90335.175
A11: S24 | B11: Radiological Classification of Areas (RCA) | C11: =INDEX(Escenarios!$D$12:$D$36,MATCH($A11,Escenarios!$A$12:$A$36,0)) -> IDOM | D11: =SUMIFS(Datos!$H$5:$H$291,Datos!$E$5:$E$291,$A11,Datos!$F$5:$F$291,"S2") -> 280 | E11: =SUMIFS(Datos!$J$5:$J$291,Datos!$E$5:$E$291,$A11,Datos!$F$5:$F$291,"S2") -> 64455.825 | F11: =INDEX(Escenarios!$E$12:$E$36,MATCH($A11,Escenarios!$A$12:$A$36,0)) -> 1 | G11: =INDEX(Escenarios!$F$12:$F$36,MATCH($A11,Escenarios!$A$12:$A$36,0)) -> 0 | H11: =INDEX(Escenarios!$G$12:$G$36,MATCH($A11,Escenarios!$A$12:$A$36,0)) -> 0 | I11: =INDEX(Escenarios!$H$12:$H$36,MATCH($A11,Escenarios!$A$12:$A$36,0)) -> 0 | J11: =IF(INDEX(Escenarios!$I$12:$I$36,MATCH($A11,Escenarios!$A$12:$A$36,0))>0,$D11,0) -> 280 | K11: =$E11*INDEX(Escenarios!$I$12:$I$36,MATCH($A11,Escenarios!$A$12:$A$36,0))*F11 -> 64455.825 | L11: =$E11*INDEX(Escenarios!$I$12:$I$36,MATCH($A11,Escenarios!$A$12:$A$36,0))*G11 -> 0 | M11: =$E11*INDEX(Escenarios!$I$12:$I$36,MATCH($A11,Escenarios!$A$12:$A$36,0))*H11 -> 0 | N11: =$E11*INDEX(Escenarios!$I$12:$I$36,MATCH($A11,Escenarios!$A$12:$A$36,0))*I11 -> 0 | O11: =SUM(K11:N11) -> 64455.825 | P11: =IF(INDEX(Escenarios!$J$12:$J$36,MATCH($A11,Escenarios!$A$12:$A$36,0))>0,$D11,0) -> 280 | Q11: =$E11*INDEX(Escenarios!$J$12:$J$36,MATCH($A11,Escenarios!$A$12:$A$36,0))*F11 -> 64455.825 | R11: =$E11*INDEX(Escenarios!$J$12:$J$36,MATCH($A11,Escenarios!$A$12:$A$36,0))*G11 -> 0 | S11: =$E11*INDEX(Escenarios!$J$12:$J$36,MATCH($A11,Escenarios!$A$12:$A$36,0))*H11 -> 0 | T11: =$E11*INDEX(Escenarios!$J$12:$J$36,MATCH($A11,Escenarios!$A$12:$A$36,0))*I11 -> 0 | U11: =SUM(Q11:T11) -> 64455.825 | V11: =IF(INDEX(Escenarios!$K$12:$K$36,MATCH($A11,Escenarios!$A$12:$A$36,0))>0,$D11,0) -> 280 | W11: =$E11*INDEX(Escenarios!$K$12:$K$36,MATCH($A11,Escenarios!$A$12:$A$36,0))*F11 -> 64455.825 | X11: =$E11*INDEX(Escenarios!$K$12:$K$36,MATCH($A11,Escenarios!$A$12:$A$36,0))*G11 -> 0 | Y11: =$E11*INDEX(Escenarios!$K$12:$K$36,MATCH($A11,Escenarios!$A$12:$A$36,0))*H11 -> 0 | Z11: =$E11*INDEX(Escenarios!$K$12:$K$36,MATCH($A11,Escenarios!$A$12:$A$36,0))*I11 -> 0 | AA11: =SUM(W11:Z11) -> 64455.825 | AB11: =IF(INDEX(Escenarios!$L$12:$L$36,MATCH($A11,Escenarios!$A$12:$A$36,0))>0,$D11,0) -> 280 | AC11: =$E11*INDEX(Escenarios!$L$12:$L$36,MATCH($A11,Escenarios!$A$12:$A$36,0))*F11 -> 64455.825 | AD11: =$E11*INDEX(Escenarios!$L$12:$L$36,MATCH($A11,Escenarios!$A$12:$A$36,0))*G11 -> 0 | AE11: =$E11*INDEX(Escenarios!$L$12:$L$36,MATCH($A11,Escenarios!$A$12:$A$36,0))*H11 -> 0 | AF11: =$E11*INDEX(Escenarios!$L$12:$L$36,MATCH($A11,Escenarios!$A$12:$A$36,0))*I11 -> 0 | AG11: =SUM(AC11:AF11) -> 64455.825
A12: S26 | B12: Structures Systems and Components (SSC) Categorisation Report | C12: =INDEX(Escenarios!$D$12:$D$36,MATCH($A12,Escenarios!$A$12:$A$36,0)) -> IDOM | D12: =SUMIFS(Datos!$H$5:$H$291,Datos!$E$5:$E$291,$A12,Datos!$F$5:$F$291,"S2") -> 270 | E12: =SUMIFS(Datos!$J$5:$J$291,Datos!$E$5:$E$291,$A12,Datos!$F$5:$F$291,"S2") -> 62552.175 | F12: =INDEX(Escenarios!$E$12:$E$36,MATCH($A12,Escenarios!$A$12:$A$36,0)) -> 1 | G12: =INDEX(Escenarios!$F$12:$F$36,MATCH($A12,Escenarios!$A$12:$A$36,0)) -> 0 | H12: =INDEX(Escenarios!$G$12:$G$36,MATCH($A12,Escenarios!$A$12:$A$36,0)) -> 0 | I12: =INDEX(Escenarios!$H$12:$H$36,MATCH($A12,Escenarios!$A$12:$A$36,0)) -> 0 | J12: =IF(INDEX(Escenarios!$I$12:$I$36,MATCH($A12,Escenarios!$A$12:$A$36,0))>0,$D12,0) -> 270 | K12: =$E12*INDEX(Escenarios!$I$12:$I$36,MATCH($A12,Escenarios!$A$12:$A$36,0))*F12 -> 62552.175 | L12: =$E12*INDEX(Escenarios!$I$12:$I$36,MATCH($A12,Escenarios!$A$12:$A$36,0))*G12 -> 0 | M12: =$E12*INDEX(Escenarios!$I$12:$I$36,MATCH($A12,Escenarios!$A$12:$A$36,0))*H12 -> 0 | N12: =$E12*INDEX(Escenarios!$I$12:$I$36,MATCH($A12,Escenarios!$A$12:$A$36,0))*I12 -> 0 | O12: =SUM(K12:N12) -> 62552.175 | P12: =IF(INDEX(Escenarios!$J$12:$J$36,MATCH($A12,Escenarios!$A$12:$A$36,0))>0,$D12,0) -> 270 | Q12: =$E12*INDEX(Escenarios!$J$12:$J$36,MATCH($A12,Escenarios!$A$12:$A$36,0))*F12 -> 62552.175 | R12: =$E12*INDEX(Escenarios!$J$12:$J$36,MATCH($A12,Escenarios!$A$12:$A$36,0))*G12 -> 0 | S12: =$E12*INDEX(Escenarios!$J$12:$J$36,MATCH($A12,Escenarios!$A$12:$A$36,0))*H12 -> 0 | T12: =$E12*INDEX(Escenarios!$J$12:$J$36,MATCH($A12,Escenarios!$A$12:$A$36,0))*I12 -> 0 | U12: =SUM(Q12:T12) -> 62552.175 | V12: =IF(INDEX(Escenarios!$K$12:$K$36,MATCH($A12,Escenarios!$A$12:$A$36,0))>0,$D12,0) -> 0 | W12: =$E12*INDEX(Escenarios!$K$12:$K$36,MATCH($A12,Escenarios!$A$12:$A$36,0))*F12 -> 0 | X12: =$E12*INDEX(Escenarios!$K$12:$K$36,MATCH($A12,Escenarios!$A$12:$A$36,0))*G12 -> 0 | Y12: =$E12*INDEX(Escenarios!$K$12:$K$36,MATCH($A12,Escenarios!$A$12:$A$36,0))*H12 -> 0 | Z12: =$E12*INDEX(Escenarios!$K$12:$K$36,MATCH($A12,Escenarios!$A$12:$A$36,0))*I12 -> 0 | AA12: =SUM(W12:Z12) -> 0 | AB12: =IF(INDEX(Escenarios!$L$12:$L$36,MATCH($A12,Escenarios!$A$12:$A$36,0))>0,$D12,0) -> 0 | AC12: =$E12*INDEX(Escenarios!$L$12:$L$36,MATCH($A12,Escenarios!$A$12:$A$36,0))*F12 -> 0 | AD12: =$E12*INDEX(Escenarios!$L$12:$L$36,MATCH($A12,Escenarios!$A$12:$A$36,0))*G12 -> 0 | AE12: =$E12*INDEX(Escenarios!$L$12:$L$36,MATCH($A12,Escenarios!$A$12:$A$36,0))*H12 -> 0 | AF12: =$E12*INDEX(Escenarios!$L$12:$L$36,MATCH($A12,Escenarios!$A$12:$A$36,0))*I12 -> 0 | AG12: =SUM(AC12:AF12) -> 0
A13: S27 | B13: Structures Systems and Components (SSC) Register | C13: =INDEX(Escenarios!$D$12:$D$36,MATCH($A13,Escenarios!$A$12:$A$36,0)) -> IDOM | D13: =SUMIFS(Datos!$H$5:$H$291,Datos!$E$5:$E$291,$A13,Datos!$F$5:$F$291,"S2") -> 165 | E13: =SUMIFS(Datos!$J$5:$J$291,Datos!$E$5:$E$291,$A13,Datos!$F$5:$F$291,"S2") -> 37183.65 | F13: =INDEX(Escenarios!$E$12:$E$36,MATCH($A13,Escenarios!$A$12:$A$36,0)) -> 1 | G13: =INDEX(Escenarios!$F$12:$F$36,MATCH($A13,Escenarios!$A$12:$A$36,0)) -> 0 | H13: =INDEX(Escenarios!$G$12:$G$36,MATCH($A13,Escenarios!$A$12:$A$36,0)) -> 0 | I13: =INDEX(Escenarios!$H$12:$H$36,MATCH($A13,Escenarios!$A$12:$A$36,0)) -> 0 | J13: =IF(INDEX(Escenarios!$I$12:$I$36,MATCH($A13,Escenarios!$A$12:$A$36,0))>0,$D13,0) -> 165 | K13: =$E13*INDEX(Escenarios!$I$12:$I$36,MATCH($A13,Escenarios!$A$12:$A$36,0))*F13 -> 37183.65 | L13: =$E13*INDEX(Escenarios!$I$12:$I$36,MATCH($A13,Escenarios!$A$12:$A$36,0))*G13 -> 0 | M13: =$E13*INDEX(Escenarios!$I$12:$I$36,MATCH($A13,Escenarios!$A$12:$A$36,0))*H13 -> 0 | N13: =$E13*INDEX(Escenarios!$I$12:$I$36,MATCH($A13,Escenarios!$A$12:$A$36,0))*I13 -> 0 | O13: =SUM(K13:N13) -> 37183.65 | P13: =IF(INDEX(Escenarios!$J$12:$J$36,MATCH($A13,Escenarios!$A$12:$A$36,0))>0,$D13,0) -> 165 | Q13: =$E13*INDEX(Escenarios!$J$12:$J$36,MATCH($A13,Escenarios!$A$12:$A$36,0))*F13 -> 37183.65 | R13: =$E13*INDEX(Escenarios!$J$12:$J$36,MATCH($A13,Escenarios!$A$12:$A$36,0))*G13 -> 0 | S13: =$E13*INDEX(Escenarios!$J$12:$J$36,MATCH($A13,Escenarios!$A$12:$A$36,0))*H13 -> 0 | T13: =$E13*INDEX(Escenarios!$J$12:$J$36,MATCH($A13,Escenarios!$A$12:$A$36,0))*I13 -> 0 | U13: =SUM(Q13:T13) -> 37183.65 | V13: =IF(INDEX(Escenarios!$K$12:$K$36,MATCH($A13,Escenarios!$A$12:$A$36,0))>0,$D13,0) -> 0 | W13: =$E13*INDEX(Escenarios!$K$12:$K$36,MATCH($A13,Escenarios!$A$12:$A$36,0))*F13 -> 0 | X13: =$E13*INDEX(Escenarios!$K$12:$K$36,MATCH($A13,Escenarios!$A$12:$A$36,0))*G13 -> 0 | Y13: =$E13*INDEX(Escenarios!$K$12:$K$36,MATCH($A13,Escenarios!$A$12:$A$36,0))*H13 -> 0 | Z13: =$E13*INDEX(Escenarios!$K$12:$K$36,MATCH($A13,Escenarios!$A$12:$A$36,0))*I13 -> 0 | AA13: =SUM(W13:Z13) -> 0 | AB13: =IF(INDEX(Escenarios!$L$12:$L$36,MATCH($A13,Escenarios!$A$12:$A$36,0))>0,$D13,0) -> 0 | AC13: =$E13*INDEX(Escenarios!$L$12:$L$36,MATCH($A13,Escenarios!$A$12:$A$36,0))*F13 -> 0 | AD13: =$E13*INDEX(Escenarios!$L$12:$L$36,MATCH($A13,Escenarios!$A$12:$A$36,0))*G13 -> 0 | AE13: =$E13*INDEX(Escenarios!$L$12:$L$36,MATCH($A13,Escenarios!$A$12:$A$36,0))*H13 -> 0 | AF13: =$E13*INDEX(Escenarios!$L$12:$L$36,MATCH($A13,Escenarios!$A$12:$A$36,0))*I13 -> 0 | AG13: =SUM(AC13:AF13) -> 0
A14: S2 | B14: Human Factors Assurance Plan / Human Factors Integration Plan (HFIP) | C14: =INDEX(Escenarios!$D$12:$D$36,MATCH($A14,Escenarios!$A$12:$A$36,0)) -> Plan Safe | D14: =SUMIFS(Datos!$H$5:$H$291,Datos!$E$5:$E$291,$A14,Datos!$F$5:$F$291,"S2") -> 380 | E14: =SUMIFS(Datos!$J$5:$J$291,Datos!$E$5:$E$291,$A14,Datos!$F$5:$F$291,"S2") -> 88244.1 | F14: =INDEX(Escenarios!$E$12:$E$36,MATCH($A14,Escenarios!$A$12:$A$36,0)) -> 0 | G14: =INDEX(Escenarios!$F$12:$F$36,MATCH($A14,Escenarios!$A$12:$A$36,0)) -> 1 | H14: =INDEX(Escenarios!$G$12:$G$36,MATCH($A14,Escenarios!$A$12:$A$36,0)) -> 0 | I14: =INDEX(Escenarios!$H$12:$H$36,MATCH($A14,Escenarios!$A$12:$A$36,0)) -> 0 | J14: =IF(INDEX(Escenarios!$I$12:$I$36,MATCH($A14,Escenarios!$A$12:$A$36,0))>0,$D14,0) -> 380 | K14: =$E14*INDEX(Escenarios!$I$12:$I$36,MATCH($A14,Escenarios!$A$12:$A$36,0))*F14 -> 0 | L14: =$E14*INDEX(Escenarios!$I$12:$I$36,MATCH($A14,Escenarios!$A$12:$A$36,0))*G14 -> 88244.1 | M14: =$E14*INDEX(Escenarios!$I$12:$I$36,MATCH($A14,Escenarios!$A$12:$A$36,0))*H14 -> 0 | N14: =$E14*INDEX(Escenarios!$I$12:$I$36,MATCH($A14,Escenarios!$A$12:$A$36,0))*I14 -> 0 | O14: =SUM(K14:N14) -> 88244.1 | P14: =IF(INDEX(Escenarios!$J$12:$J$36,MATCH($A14,Escenarios!$A$12:$A$36,0))>0,$D14,0) -> 0 | Q14: =$E14*INDEX(Escenarios!$J$12:$J$36,MATCH($A14,Escenarios!$A$12:$A$36,0))*F14 -> 0 | R14: =$E14*INDEX(Escenarios!$J$12:$J$36,MATCH($A14,Escenarios!$A$12:$A$36,0))*G14 -> 0 | S14: =$E14*INDEX(Escenarios!$J$12:$J$36,MATCH($A14,Escenarios!$A$12:$A$36,0))*H14 -> 0 | T14: =$E14*INDEX(Escenarios!$J$12:$J$36,MATCH($A14,Escenarios!$A$12:$A$36,0))*I14 -> 0 | U14: =SUM(Q14:T14) -> 0 | V14: =IF(INDEX(Escenarios!$K$12:$K$36,MATCH($A14,Escenarios!$A$12:$A$36,0))>0,$D14,0) -> 0 | W14: =$E14*INDEX(Escenarios!$K$12:$K$36,MATCH($A14,Escenarios!$A$12:$A$36,0))*F14 -> 0 | X14: =$E14*INDEX(Escenarios!$K$12:$K$36,MATCH($A14,Escenarios!$A$12:$A$36,0))*G14 -> 0 | Y14: =$E14*INDEX(Escenarios!$K$12:$K$36,MATCH($A14,Escenarios!$A$12:$A$36,0))*H14 -> 0 | Z14: =$E14*INDEX(Escenarios!$K$12:$K$36,MATCH($A14,Escenarios!$A$12:$A$36,0))*I14 -> 0 | AA14: =SUM(W14:Z14) -> 0 | AB14: =IF(INDEX(Escenarios!$L$12:$L$36,MATCH($A14,Escenarios!$A$12:$A$36,0))>0,$D14,0) -> 380 | AC14: =$E14*INDEX(Escenarios!$L$12:$L$36,MATCH($A14,Escenarios!$A$12:$A$36,0))*F14 -> 0 | AD14: =$E14*INDEX(Escenarios!$L$12:$L$36,MATCH($A14,Escenarios!$A$12:$A$36,0))*G14 -> 44122.05 | AE14: =$E14*INDEX(Escenarios!$L$12:$L$36,MATCH($A14,Escenarios!$A$12:$A$36,0))*H14 -> 0 | AF14: =$E14*INDEX(Escenarios!$L$12:$L$36,MATCH($A14,Escenarios!$A$12:$A$36,0))*I14 -> 0 | AG14: =SUM(AC14:AF14) -> 44122.05
A15: S3 | B15: Human Factors Hazards Identification and Control Plan (HFHICP) | C15: =INDEX(Escenarios!$D$12:$D$36,MATCH($A15,Escenarios!$A$12:$A$36,0)) -> Plan Safe | D15: =SUMIFS(Datos!$H$5:$H$291,Datos!$E$5:$E$291,$A15,Datos!$F$5:$F$291,"S2") -> 305 | E15: =SUMIFS(Datos!$J$5:$J$291,Datos!$E$5:$E$291,$A15,Datos!$F$5:$F$291,"S2") -> 70622.475 | F15: =INDEX(Escenarios!$E$12:$E$36,MATCH($A15,Escenarios!$A$12:$A$36,0)) -> 0 | G15: =INDEX(Escenarios!$F$12:$F$36,MATCH($A15,Escenarios!$A$12:$A$36,0)) -> 1 | H15: =INDEX(Escenarios!$G$12:$G$36,MATCH($A15,Escenarios!$A$12:$A$36,0)) -> 0 | I15: =INDEX(Escenarios!$H$12:$H$36,MATCH($A15,Escenarios!$A$12:$A$36,0)) -> 0 | J15: =IF(INDEX(Escenarios!$I$12:$I$36,MATCH($A15,Escenarios!$A$12:$A$36,0))>0,$D15,0) -> 305 | K15: =$E15*INDEX(Escenarios!$I$12:$I$36,MATCH($A15,Escenarios!$A$12:$A$36,0))*F15 -> 0 | L15: =$E15*INDEX(Escenarios!$I$12:$I$36,MATCH($A15,Escenarios!$A$12:$A$36,0))*G15 -> 70622.475 | M15: =$E15*INDEX(Escenarios!$I$12:$I$36,MATCH($A15,Escenarios!$A$12:$A$36,0))*H15 -> 0 | N15: =$E15*INDEX(Escenarios!$I$12:$I$36,MATCH($A15,Escenarios!$A$12:$A$36,0))*I15 -> 0 | O15: =SUM(K15:N15) -> 70622.475 | P15: =IF(INDEX(Escenarios!$J$12:$J$36,MATCH($A15,Escenarios!$A$12:$A$36,0))>0,$D15,0) -> 0 | Q15: =$E15*INDEX(Escenarios!$J$12:$J$36,MATCH($A15,Escenarios!$A$12:$A$36,0))*F15 -> 0 | R15: =$E15*INDEX(Escenarios!$J$12:$J$36,MATCH($A15,Escenarios!$A$12:$A$36,0))*G15 -> 0 | S15: =$E15*INDEX(Escenarios!$J$12:$J$36,MATCH($A15,Escenarios!$A$12:$A$36,0))*H15 -> 0 | T15: =$E15*INDEX(Escenarios!$J$12:$J$36,MATCH($A15,Escenarios!$A$12:$A$36,0))*I15 -> 0 | U15: =SUM(Q15:T15) -> 0 | V15: =IF(INDEX(Escenarios!$K$12:$K$36,MATCH($A15,Escenarios!$A$12:$A$36,0))>0,$D15,0) -> 0 | W15: =$E15*INDEX(Escenarios!$K$12:$K$36,MATCH($A15,Escenarios!$A$12:$A$36,0))*F15 -> 0 | X15: =$E15*INDEX(Escenarios!$K$12:$K$36,MATCH($A15,Escenarios!$A$12:$A$36,0))*G15 -> 0 | Y15: =$E15*INDEX(Escenarios!$K$12:$K$36,MATCH($A15,Escenarios!$A$12:$A$36,0))*H15 -> 0 | Z15: =$E15*INDEX(Escenarios!$K$12:$K$36,MATCH($A15,Escenarios!$A$12:$A$36,0))*I15 -> 0 | AA15: =SUM(W15:Z15) -> 0 | AB15: =IF(INDEX(Escenarios!$L$12:$L$36,MATCH($A15,Escenarios!$A$12:$A$36,0))>0,$D15,0) -> 305 | AC15: =$E15*INDEX(Escenarios!$L$12:$L$36,MATCH($A15,Escenarios!$A$12:$A$36,0))*F15 -> 0 | AD15: =$E15*INDEX(Escenarios!$L$12:$L$36,MATCH($A15,Escenarios!$A$12:$A$36,0))*G15 -> 35311.238 | AE15: =$E15*INDEX(Escenarios!$L$12:$L$36,MATCH($A15,Escenarios!$A$12:$A$36,0))*H15 -> 0 | AF15: =$E15*INDEX(Escenarios!$L$12:$L$36,MATCH($A15,Escenarios!$A$12:$A$36,0))*I15 -> 0 | AG15: =SUM(AC15:AF15) -> 35311.238
B16: Subtotal Stage 2 (entregables) | D16: =SUM(D8:D15) -> 3170 | E16: =SUM(E8:E15) -> 732839.1 | J16: =SUM(J8:J15) -> 3170 | K16: =SUM(K8:K15) -> 536515.09 | L16: =SUM(L8:L15) -> 196324.01 | M16: =SUM(M8:M15) -> 0 | N16: =SUM(N8:N15) -> 0 | O16: =SUM(O8:O15) -> 732839.1 | P16: =SUM(P8:P15) -> 2485 | Q16: =SUM(Q8:Q15) -> 536515.09 | ... AG16: =SUM(AG8:AG15) -> 553669.99
B17: ="Retrabajo descontado (recargo "&TEXT(Escenarios!$B$8,"0%")&" sobre las tareas de IDOM): "&$C$4 -> Retrabajo descontado (recargo 35% sobre las tareas de IDOM): No | K17: =-IF($C$4="Sí",K16*Escenarios!$B$8/(1+Escenarios!$B$8),0) -> 0 | L17: 0 | M17: 0 | N17: 0 | O17: =SUM(K17:N17) -> 0 | Q17: =-IF($C$4="Sí",Q16*Escenarios!$B$8/(1+Escenarios!$B$8),0) -> 0 | R17: 0 | S17: 0 | T17: 0 | U17: =SUM(Q17:T17) -> 0 | W17: =-IF($C$4="Sí",W16*Escenarios!$B$8/(1+Escenarios!$B$8),0) -> 0 | X17: 0 | Y17: 0 | Z17: 0 | AA17: =SUM(W17:Z17) -> 0 | AC17: =-IF($C$4="Sí",AC16*Escenarios!$B$8/(1+Escenarios!$B$8),0) -> 0 | AD17: 0 | AE17: 0 | AF17: 0 | AG17: =SUM(AC17:AF17) -> 0
B18: TOTAL STAGE 2 | D18: =D16 -> 3170 | E18: =E16 -> 732839.1 | J18: =J16 -> 3170 | K18: =K16+K17 -> 536515.09 | L18: =L16+L17 -> 196324.01 | M18: =M16+M17 -> 0 | N18: =N16+N17 -> 0 | O18: =O16+O17 -> 732839.1 | P18: =P16 -> 2485 | Q18: =Q16+Q17 -> 536515.09 | R18: =R16+R17 -> 37457.438 | S18: =S16+S17 -> 0 | T18: =T16+T17 -> 0 | U18: =U16+U17 -> 573972.53 | V18: =V16 -> 2050 | W18: =W16+W17 -> 436779.26 | X18: =X16+X17 -> 37457.438 | Y18: =Y16+Y17 -> 0 | Z18: =Z16+Z17 -> 0 | AA18: =AA16+AA17 -> 474236.7 | AB18: =AB16 -> 2735 | AC18: =AC16+AC17 -> 436779.26 | AD18: =AD16+AD17 -> 116890.73 | AE18: =AE16+AE17 -> 0 | AF18: =AF16+AF17 -> 0 | AG18: =AG16+AG17 -> 553669.99
B20: Referencia: oferta original por empresa (sin escenarios ni ajustes) | E20: =SUM(F20:I20) -> 732839.1 | F20: =SUMPRODUCT($E$8:$E$15,F$8:F$15) -> 536515.09 | G20: =SUMPRODUCT($E$8:$E$15,G$8:G$15) -> 196324.01 | H20: =SUMPRODUCT($E$8:$E$15,H$8:H$15) -> 0 | I20: =SUMPRODUCT($E$8:$E$15,I$8:I$15) -> 0

Sheet Stage 3
A1: Stage 3 · Preliminary Design — desglose por entregable y empresa (AUD)
A2: Importe = horas × tarifa de venta (pestaña Datos). Reparto por empresa según el tipo de cada entregable (pestaña Escenarios).
A6: Oferta original | F6: Reparto | J6: =Escenarios!I$10&" · "&Escenarios!I$11 -> Escenario 1 · Original | P6: =Escenarios!J$10&" · "&Escenarios!J$11 -> Escenario 2 · Sin las 4 tareas de Plan Safe | V6: =Escenarios!K$10&" · "&Escenarios!K$11 -> Escenario 3 · Sin tareas Plan Safe ni SSC | AB6: =Escenarios!L$10&" · "&Escenarios!L$11 -> Escenario 4 · Sin SSC, tareas Plan Safe al 50 %
A7: Código | B7: Entregable | C7: Tipo | D7: Horas base | E7: Importe base | F7: % IDOM | G7: % Plan Safe | H7: % Synertec | I7: % INVAP | J7: Horas | K7: IDOM | L7: Plan Safe | M7: Synertec | N7: INVAP | O7: Total | P7: Horas | Q7: IDOM | R7: Plan Safe | S7: Synertec | T7: INVAP | U7: Total | V7: Horas | W7: IDOM | X7: Plan Safe | Y7: Synertec | Z7: INVAP | AA7: Total | AB7: Horas | AC7: IDOM | AD7: Plan Safe | AE7: Synertec | AF7: INVAP | AG7: Total
A8: E94 | B8: Radiological Zoning Layout drawing(s) | C8: =INDEX(Escenarios!$D$12:$D$36,MATCH($A8,Escenarios!$A$12:$A$36,0)) -> IDOM | D8: =SUMIFS(Datos!$H$5:$H$291,Datos!$E$5:$E$291,$A8,Datos!$F$5:$F$291,"S3") -> 315 | E8: =SUMIFS(Datos!$J$5:$J$291,Datos!$E$5:$E$291,$A8,Datos!$F$5:$F$291,"S3") -> 58869.825 | F8: =INDEX(Escenarios!$E$12:$E$36,MATCH($A8,Escenarios!$A$12:$A$36,0)) -> 1 | G8: =INDEX(Escenarios!$F$12:$F$36,MATCH($A8,Escenarios!$A$12:$A$36,0)) -> 0 | H8: =INDEX(Escenarios!$G$12:$G$36,MATCH($A8,Escenarios!$A$12:$A$36,0)) -> 0 | I8: =INDEX(Escenarios!$H$12:$H$36,MATCH($A8,Escenarios!$A$12:$A$36,0)) -> 0 | J8: =IF(INDEX(Escenarios!$I$12:$I$36,MATCH($A8,Escenarios!$A$12:$A$36,0))>0,$D8,0) -> 315 | K8: =$E8*INDEX(Escenarios!$I$12:$I$36,MATCH($A8,Escenarios!$A$12:$A$36,0))*F8 -> 58869.825 | L8: =$E8*INDEX(Escenarios!$I$12:$I$36,MATCH($A8,Escenarios!$A$12:$A$36,0))*G8 -> 0 | M8: =$E8*INDEX(Escenarios!$I$12:$I$36,MATCH($A8,Escenarios!$A$12:$A$36,0))*H8 -> 0 | N8: =$E8*INDEX(Escenarios!$I$12:$I$36,MATCH($A8,Escenarios!$A$12:$A$36,0))*I8 -> 0 | O8: =SUM(K8:N8) -> 58869.825 | P8: =IF(INDEX(Escenarios!$J$12:$J$36,MATCH($A8,Escenarios!$A$12:$A$36,0))>0,$D8,0) -> 315 | Q8: =$E8*INDEX(Escenarios!$J$12:$J$36,MATCH($A8,Escenarios!$A$12:$A$36,0))*F8 -> 58869.825 | R8: =$E8*INDEX(Escenarios!$J$12:$J$36,MATCH($A8,Escenarios!$A$12:$A$36,0))*G8 -> 0 | S8: =$E8*INDEX(Escenarios!$J$12:$J$36,MATCH($A8,Escenarios!$A$12:$A$36,0))*H8 -> 0 | T8: =$E8*INDEX(Escenarios!$J$12:$J$36,MATCH($A8,Escenarios!$A$12:$A$36,0))*I8 -> 0 | U8: =SUM(Q8:T8) -> 58869.825 | V8: =IF(INDEX(Escenarios!$K$12:$K$36,MATCH($A8,Escenarios!$A$12:$A$36,0))>0,$D8,0) -> 315 | W8: =$E8*INDEX(Escenarios!$K$12:$K$36,MATCH($A8,Escenarios!$A$12:$A$36,0))*F8 -> 58869.825 | X8: =$E8*INDEX(Escenarios!$K$12:$K$36,MATCH($A8,Escenarios!$A$12:$A$36,0))*G8 -> 0 | Y8: =$E8*INDEX(Escenarios!$K$12:$K$36,MATCH($A8,Escenarios!$A$12:$A$36,0))*H8 -> 0 | Z8: =$E8*INDEX(Escenarios!$K$12:$K$36,MATCH($A8,Escenarios!$A$12:$A$36,0))*I8 -> 0 | AA8: =SUM(W8:Z8) -> 58869.825 | AB8: =IF(INDEX(Escenarios!$L$12:$L$36,MATCH($A8,Escenarios!$A$12:$A$36,0))>0,$D8,0) -> 315 | AC8: =$E8*INDEX(Escenarios!$L$12:$L$36,MATCH($A8,Escenarios!$A$12:$A$36,0))*F8 -> 58869.825 | AD8: =$E8*INDEX(Escenarios!$L$12:$L$36,MATCH($A8,Escenarios!$A$12:$A$36,0))*G8 -> 0 | AE8: =$E8*INDEX(Escenarios!$L$12:$L$36,MATCH($A8,Escenarios!$A$12:$A$36,0))*H8 -> 0 | AF8: =$E8*INDEX(Escenarios!$L$12:$L$36,MATCH($A8,Escenarios!$A$12:$A$36,0))*I8 -> 0 | AG8: =SUM(AC8:AF8) -> 58869.825
A9: S9 | B9: Deterministic Safety Assessment(s) (DSA) / Inherent Risk Assessment(s) | C9: =INDEX(Escenarios!$D$12:$D$36,MATCH($A9,Escenarios!$A$12:$A$36,0)) -> Compartido | D9: =SUMIFS(Datos!$H$5:$H$291,Datos!$E$5:$E$291,$A9,Datos!$F$5:$F$291,"S3") -> 1385 | E9: =SUMIFS(Datos!$J$5:$J$291,Datos!$E$5:$E$291,$A9,Datos!$F$5:$F$291,"S3") -> 323392.65 | F9: =INDEX(Escenarios!$E$12:$E$36,MATCH($A9,Escenarios!$A$12:$A$36,0)) -> 0.9 | G9: =INDEX(Escenarios!$F$12:$F$36,MATCH($A9,Escenarios!$A$12:$A$36,0)) -> 0.1 | H9: =INDEX(Escenarios!$G$12:$G$36,MATCH($A9,Escenarios!$A$12:$A$36,0)) -> 0 | I9: =INDEX(Escenarios!$H$12:$H$36,MATCH($A9,Escenarios!$A$12:$A$36,0)) -> 0 | J9: =IF(INDEX(Escenarios!$I$12:$I$36,MATCH($A9,Escenarios!$A$12:$A$36,0))>0,$D9,0) -> 1385 | K9: =$E9*INDEX(Escenarios!$I$12:$I$36,MATCH($A9,Escenarios!$A$12:$A$36,0))*F9 -> 291053.39 | L9: =$E9*INDEX(Escenarios!$I$12:$I$36,MATCH($A9,Escenarios!$A$12:$A$36,0))*G9 -> 32339.265 | M9: =$E9*INDEX(Escenarios!$I$12:$I$36,MATCH($A9,Escenarios!$A$12:$A$36,0))*H9 -> 0 | N9: =$E9*INDEX(Escenarios!$I$12:$I$36,MATCH($A9,Escenarios!$A$12:$A$36,0))*I9 -> 0 | O9: =SUM(K9:N9) -> 323392.65 | P9: =IF(INDEX(Escenarios!$J$12:$J$36,MATCH($A9,Escenarios!$A$12:$A$36,0))>0,$D9,0) -> 1385 | Q9: =$E9*INDEX(Escenarios!$J$12:$J$36,MATCH($A9,Escenarios!$A$12:$A$36,0))*F9 -> 291053.39 | R9: =$E9*INDEX(Escenarios!$J$12:$J$36,MATCH($A9,Escenarios!$A$12:$A$36,0))*G9 -> 32339.265 | S9: =$E9*INDEX(Escenarios!$J$12:$J$36,MATCH($A9,Escenarios!$A$12:$A$36,0))*H9 -> 0 | T9: =$E9*INDEX(Escenarios!$J$12:$J$36,MATCH($A9,Escenarios!$A$12:$A$36,0))*I9 -> 0 | U9: =SUM(Q9:T9) -> 323392.65 | V9: =IF(INDEX(Escenarios!$K$12:$K$36,MATCH($A9,Escenarios!$A$12:$A$36,0))>0,$D9,0) -> 1385 | W9: =$E9*INDEX(Escenarios!$K$12:$K$36,MATCH($A9,Escenarios!$A$12:$A$36,0))*F9 -> 291053.39 | X9: =$E9*INDEX(Escenarios!$K$12:$K$36,MATCH($A9,Escenarios!$A$12:$A$36,0))*G9 -> 32339.265 | Y9: =$E9*INDEX(Escenarios!$K$12:$K$36,MATCH($A9,Escenarios!$A$12:$A$36,0))*H9 -> 0 | Z9: =$E9*INDEX(Escenarios!$K$12:$K$36,MATCH($A9,Escenarios!$A$12:$A$36,0))*I9 -> 0 | AA9: =SUM(W9:Z9) -> 323392.65 | AB9: =IF(INDEX(Escenarios!$L$12:$L$36,MATCH($A9,Escenarios!$A$12:$A$36,0))>0,$D9,0) -> 1385 | AC9: =$E9*INDEX(Escenarios!$L$12:$L$36,MATCH($A9,Escenarios!$A$12:$A$36,0))*F9 -> 291053.39 | AD9: =$E9*INDEX(Escenarios!$L$12:$L$36,MATCH($A9,Escenarios!$A$12:$A$36,0))*G9 -> 32339.265 | AE9: =$E9*INDEX(Escenarios!$L$12:$L$36,MATCH($A9,Escenarios!$A$12:$A$36,0))*H9 -> 0 | AF9: =$E9*INDEX(Escenarios!$L$12:$L$36,MATCH($A9,Escenarios!$A$12:$A$36,0))*I9 -> 0 | AG9: =SUM(AC9:AF9) -> 323392.65
A10: S17 | B10: ALARP (Optioneering) Study | C10: =INDEX(Escenarios!$D$12:$D$36,MATCH($A10,Escenarios!$A$12:$A$36,0)) -> Compartido | D10: =SUMIFS(Datos!$H$5:$H$291,Datos!$E$5:$E$291,$A10,Datos!$F$5:$F$291,"S3") -> 650 | E10: =SUMIFS(Datos!$J$5:$J$291,Datos!$E$5:$E$291,$A10,Datos!$F$5:$F$291,"S3") -> 151656.23 | F10: =INDEX(Escenarios!$E$12:$E$36,MATCH($A10,Escenarios!$A$12:$A$36,0)) -> 0.9 | G10: =INDEX(Escenarios!$F$12:$F$36,MATCH($A10,Escenarios!$A$12:$A$36,0)) -> 0.1 | H10: =INDEX(Escenarios!$G$12:$G$36,MATCH($A10,Escenarios!$A$12:$A$36,0)) -> 0 | I10: =INDEX(Escenarios!$H$12:$H$36,MATCH($A10,Escenarios!$A$12:$A$36,0)) -> 0 | J10: =IF(INDEX(Escenarios!$I$12:$I$36,MATCH($A10,Escenarios!$A$12:$A$36,0))>0,$D10,0) -> 650 | K10: =$E10*INDEX(Escenarios!$I$12:$I$36,MATCH($A10,Escenarios!$A$12:$A$36,0))*F10 -> 136490.6 | L10: =$E10*INDEX(Escenarios!$I$12:$I$36,MATCH($A10,Escenarios!$A$12:$A$36,0))*G10 -> 15165.622 | M10: =$E10*INDEX(Escenarios!$I$12:$I$36,MATCH($A10,Escenarios!$A$12:$A$36,0))*H10 -> 0 | N10: =$E10*INDEX(Escenarios!$I$12:$I$36,MATCH($A10,Escenarios!$A$12:$A$36,0))*I10 -> 0 | O10: =SUM(K10:N10) -> 151656.23 | P10: =IF(INDEX(Escenarios!$J$12:$J$36,MATCH($A10,Escenarios!$A$12:$A$36,0))>0,$D10,0) -> 650 | Q10: =$E10*INDEX(Escenarios!$J$12:$J$36,MATCH($A10,Escenarios!$A$12:$A$36,0))*F10 -> 136490.6 | R10: =$E10*INDEX(Escenarios!$J$12:$J$36,MATCH($A10,Escenarios!$A$12:$A$36,0))*G10 -> 15165.622 | S10: =$E10*INDEX(Escenarios!$J$12:$J$36,MATCH($A10,Escenarios!$A$12:$A$36,0))*H10 -> 0 | T10: =$E10*INDEX(Escenarios!$J$12:$J$36,MATCH($A10,Escenarios!$A$12:$A$36,0))*I10 -> 0 | U10: =SUM(Q10:T10) -> 151656.23 | V10: =IF(INDEX(Escenarios!$K$12:$K$36,MATCH($A10,Escenarios!$A$12:$A$36,0))>0,$D10,0) -> 650 | W10: =$E10*INDEX(Escenarios!$K$12:$K$36,MATCH($A10,Escenarios!$A$12:$A$36,0))*F10 -> 136490.6 | X10: =$E10*INDEX(Escenarios!$K$12:$K$36,MATCH($A10,Escenarios!$A$12:$A$36,0))*G10 -> 15165.622 | Y10: =$E10*INDEX(Escenarios!$K$12:$K$36,MATCH($A10,Escenarios!$A$12:$A$36,0))*H10 -> 0 | Z10: =$E10*INDEX(Escenarios!$K$12:$K$36,MATCH($A10,Escenarios!$A$12:$A$36,0))*I10 -> 0 | AA10: =SUM(W10:Z10) -> 151656.23 | AB10: =IF(INDEX(Escenarios!$L$12:$L$36,MATCH($A10,Escenarios!$A$12:$A$36,0))>0,$D10,0) -> 650 | AC10: =$E10*INDEX(Escenarios!$L$12:$L$36,MATCH($A10,Escenarios!$A$12:$A$36,0))*F10 -> 136490.6 | AD10: =$E10*INDEX(Escenarios!$L$12:$L$36,MATCH($A10,Escenarios!$A$12:$A$36,0))*G10 -> 15165.622 | AE10: =$E10*INDEX(Escenarios!$L$12:$L$36,MATCH($A10,Escenarios!$A$12:$A$36,0))*H10 -> 0 | AF10: =$E10*INDEX(Escenarios!$L$12:$L$36,MATCH($A10,Escenarios!$A$12:$A$36,0))*I10 -> 0 | AG10: =SUM(AC10:AF10) -> 151656.23
A11: S21 | B11: Radiological Shielding Basis of Design | C11: =INDEX(Escenarios!$D$12:$D$36,MATCH($A11,Escenarios!$A$12:$A$36,0)) -> IDOM | D11: =SUMIFS(Datos!$H$5:$H$291,Datos!$E$5:$E$291,$A11,Datos!$F$5:$F$291,"S3") -> 385 | E11: =SUMIFS(Datos!$J$5:$J$291,Datos!$E$5:$E$291,$A11,Datos!$F$5:$F$291,"S3") -> 89229 | F11: =INDEX(Escenarios!$E$12:$E$36,MATCH($A11,Escenarios!$A$12:$A$36,0)) -> 1 | G11: =INDEX(Escenarios!$F$12:$F$36,MATCH($A11,Escenarios!$A$12:$A$36,0)) -> 0 | H11: =INDEX(Escenarios!$G$12:$G$36,MATCH($A11,Escenarios!$A$12:$A$36,0)) -> 0 | I11: =INDEX(Escenarios!$H$12:$H$36,MATCH($A11,Escenarios!$A$12:$A$36,0)) -> 0 | J11: =IF(INDEX(Escenarios!$I$12:$I$36,MATCH($A11,Escenarios!$A$12:$A$36,0))>0,$D11,0) -> 385 | K11: =$E11*INDEX(Escenarios!$I$12:$I$36,MATCH($A11,Escenarios!$A$12:$A$36,0))*F11 -> 89229 | L11: =$E11*INDEX(Escenarios!$I$12:$I$36,MATCH($A11,Escenarios!$A$12:$A$36,0))*G11 -> 0 | M11: =$E11*INDEX(Escenarios!$I$12:$I$36,MATCH($A11,Escenarios!$A$12:$A$36,0))*H11 -> 0 | N11: =$E11*INDEX(Escenarios!$I$12:$I$36,MATCH($A11,Escenarios!$A$12:$A$36,0))*I11 -> 0 | O11: =SUM(K11:N11) -> 89229 | P11: =IF(INDEX(Escenarios!$J$12:$J$36,MATCH($A11,Escenarios!$A$12:$A$36,0))>0,$D11,0) -> 385 | Q11: =$E11*INDEX(Escenarios!$J$12:$J$36,MATCH($A11,Escenarios!$A$12:$A$36,0))*F11 -> 89229 | R11: =$E11*INDEX(Escenarios!$J$12:$J$36,MATCH($A11,Escenarios!$A$12:$A$36,0))*G11 -> 0 | S11: =$E11*INDEX(Escenarios!$J$12:$J$36,MATCH($A11,Escenarios!$A$12:$A$36,0))*H11 -> 0 | T11: =$E11*INDEX(Escenarios!$J$12:$J$36,MATCH($A11,Escenarios!$A$12:$A$36,0))*I11 -> 0 | U11: =SUM(Q11:T11) -> 89229 | V11: =IF(INDEX(Escenarios!$K$12:$K$36,MATCH($A11,Escenarios!$A$12:$A$36,0))>0,$D11,0) -> 385 | W11: =$E11*INDEX(Escenarios!$K$12:$K$36,MATCH($A11,Escenarios!$A$12:$A$36,0))*F11 -> 89229 | X11: =$E11*INDEX(Escenarios!$K$12:$K$36,MATCH($A11,Escenarios!$A$12:$A$36,0))*G11 -> 0 | Y11: =$E11*INDEX(Escenarios!$K$12:$K$36,MATCH($A11,Escenarios!$A$12:$A$36,0))*H11 -> 0 | Z11: =$E11*INDEX(Escenarios!$K$12:$K$36,MATCH($A11,Escenarios!$A$12:$A$36,0))*I11 -> 0 | AA11: =SUM(W11:Z11) -> 89229 | AB11: =IF(INDEX(Escenarios!$L$12:$L$36,MATCH($A11,Escenarios!$A$12:$A$36,0))>0,$D11,0) -> 385 | AC11: =$E11*INDEX(Escenarios!$L$12:$L$36,MATCH($A11,Escenarios!$A$12:$A$36,0))*F11 -> 89229 | AD11: =$E11*INDEX(Escenarios!$L$12:$L$36,MATCH($A11,Escenarios!$A$12:$A$36,0))*G11 -> 0 | AE11: =$E11*INDEX(Escenarios!$L$12:$L$36,MATCH($A11,Escenarios!$A$12:$A$36,0))*H11 -> 0 | AF11: =$E11*INDEX(Escenarios!$L$12:$L$36,MATCH($A11,Escenarios!$A$12:$A$36,0))*I11 -> 0 | AG11: =SUM(AC11:AF11) -> 89229
A12: S22 | B12: Radiological Shielding Assessment | C12: =INDEX(Escenarios!$D$12:$D$36,MATCH($A12,Escenarios!$A$12:$A$36,0)) -> IDOM | D12: =SUMIFS(Datos!$H$5:$H$291,Datos!$E$5:$E$291,$A12,Datos!$F$5:$F$291,"S3") -> 675 | E12: =SUMIFS(Datos!$J$5:$J$291,Datos!$E$5:$E$291,$A12,Datos!$F$5:$F$291,"S3") -> 155044.58 | F12: =INDEX(Escenarios!$E$12:$E$36,MATCH($A12,Escenarios!$A$12:$A$36,0)) -> 1 | G12: =INDEX(Escenarios!$F$12:$F$36,MATCH($A12,Escenarios!$A$12:$A$36,0)) -> 0 | H12: =INDEX(Escenarios!$G$12:$G$36,MATCH($A12,Escenarios!$A$12:$A$36,0)) -> 0 | I12: =INDEX(Escenarios!$H$12:$H$36,MATCH($A12,Escenarios!$A$12:$A$36,0)) -> 0 | J12: =IF(INDEX(Escenarios!$I$12:$I$36,MATCH($A12,Escenarios!$A$12:$A$36,0))>0,$D12,0) -> 675 | K12: =$E12*INDEX(Escenarios!$I$12:$I$36,MATCH($A12,Escenarios!$A$12:$A$36,0))*F12 -> 155044.58 | L12: =$E12*INDEX(Escenarios!$I$12:$I$36,MATCH($A12,Escenarios!$A$12:$A$36,0))*G12 -> 0 | M12: =$E12*INDEX(Escenarios!$I$12:$I$36,MATCH($A12,Escenarios!$A$12:$A$36,0))*H12 -> 0 | N12: =$E12*INDEX(Escenarios!$I$12:$I$36,MATCH($A12,Escenarios!$A$12:$A$36,0))*I12 -> 0 | O12: =SUM(K12:N12) -> 155044.58 | P12: =IF(INDEX(Escenarios!$J$12:$J$36,MATCH($A12,Escenarios!$A$12:$A$36,0))>0,$D12,0) -> 675 | Q12: =$E12*INDEX(Escenarios!$J$12:$J$36,MATCH($A12,Escenarios!$A$12:$A$36,0))*F12 -> 155044.58 | R12: =$E12*INDEX(Escenarios!$J$12:$J$36,MATCH($A12,Escenarios!$A$12:$A$36,0))*G12 -> 0 | S12: =$E12*INDEX(Escenarios!$J$12:$J$36,MATCH($A12,Escenarios!$A$12:$A$36,0))*H12 -> 0 | T12: =$E12*INDEX(Escenarios!$J$12:$J$36,MATCH($A12,Escenarios!$A$12:$A$36,0))*I12 -> 0 | U12: =SUM(Q12:T12) -> 155044.58 | V12: =IF(INDEX(Escenarios!$K$12:$K$36,MATCH($A12,Escenarios!$A$12:$A$36,0))>0,$D12,0) -> 675 | W12: =$E12*INDEX(Escenarios!$K$12:$K$36,MATCH($A12,Escenarios!$A$12:$A$36,0))*F12 -> 155044.58 | X12: =$E12*INDEX(Escenarios!$K$12:$K$36,MATCH($A12,Escenarios!$A$12:$A$36,0))*G12 -> 0 | Y12: =$E12*INDEX(Escenarios!$K$12:$K$36,MATCH($A12,Escenarios!$A$12:$A$36,0))*H12 -> 0 | Z12: =$E12*INDEX(Escenarios!$K$12:$K$36,MATCH($A12,Escenarios!$A$12:$A$36,0))*I12 -> 0 | AA12: =SUM(W12:Z12) -> 155044.58 | AB12: =IF(INDEX(Escenarios!$L$12:$L$36,MATCH($A12,Escenarios!$A$12:$A$36,0))>0,$D12,0) -> 675 | AC12: =$E12*INDEX(Escenarios!$L$12:$L$36,MATCH($A12,Escenarios!$A$12:$A$36,0))*F12 -> 155044.58 | AD12: =$E12*INDEX(Escenarios!$L$12:$L$36,MATCH($A12,Escenarios!$A$12:$A$36,0))*G12 -> 0 | AE12: =$E12*INDEX(Escenarios!$L$12:$L$36,MATCH($A12,Escenarios!$A$12:$A$36,0))*H12 -> 0 | AF12: =$E12*INDEX(Escenarios!$L$12:$L$36,MATCH($A12,Escenarios!$A$12:$A$36,0))*I12 -> 0 | AG12: =SUM(AC12:AF12) -> 155044.58
A13: S23 | B13: Radiological Contamination Control Strategy | C13: =INDEX(Escenarios!$D$12:$D$36,MATCH($A13,Escenarios!$A$12:$A$36,0)) -> Compartido | D13: =SUMIFS(Datos!$H$5:$H$291,Datos!$E$5:$E$291,$A13,Datos!$F$5:$F$291,"S3") -> 480 | E13: =SUMIFS(Datos!$J$5:$J$291,Datos!$E$5:$E$291,$A13,Datos!$F$5:$F$291,"S3") -> 110536.65 | F13: =INDEX(Escenarios!$E$12:$E$36,MATCH($A13,Escenarios!$A$12:$A$36,0)) -> 0.9 | G13: =INDEX(Escenarios!$F$12:$F$36,MATCH($A13,Escenarios!$A$12:$A$36,0)) -> 0.1 | H13: =INDEX(Escenarios!$G$12:$G$36,MATCH($A13,Escenarios!$A$12:$A$36,0)) -> 0 | I13: =INDEX(Escenarios!$H$12:$H$36,MATCH($A13,Escenarios!$A$12:$A$36,0)) -> 0 | J13: =IF(INDEX(Escenarios!$I$12:$I$36,MATCH($A13,Escenarios!$A$12:$A$36,0))>0,$D13,0) -> 480 | K13: =$E13*INDEX(Escenarios!$I$12:$I$36,MATCH($A13,Escenarios!$A$12:$A$36,0))*F13 -> 99482.985 | L13: =$E13*INDEX(Escenarios!$I$12:$I$36,MATCH($A13,Escenarios!$A$12:$A$36,0))*G13 -> 11053.665 | M13: =$E13*INDEX(Escenarios!$I$12:$I$36,MATCH($A13,Escenarios!$A$12:$A$36,0))*H13 -> 0 | N13: =$E13*INDEX(Escenarios!$I$12:$I$36,MATCH($A13,Escenarios!$A$12:$A$36,0))*I13 -> 0 | O13: =SUM(K13:N13) -> 110536.65 | P13: =IF(INDEX(Escenarios!$J$12:$J$36,MATCH($A13,Escenarios!$A$12:$A$36,0))>0,$D13,0) -> 480 | Q13: =$E13*INDEX(Escenarios!$J$12:$J$36,MATCH($A13,Escenarios!$A$12:$A$36,0))*F13 -> 99482.985 | R13: =$E13*INDEX(Escenarios!$J$12:$J$36,MATCH($A13,Escenarios!$A$12:$A$36,0))*G13 -> 11053.665 | S13: =$E13*INDEX(Escenarios!$J$12:$J$36,MATCH($A13,Escenarios!$A$12:$A$36,0))*H13 -> 0 | T13: =$E13*INDEX(Escenarios!$J$12:$J$36,MATCH($A13,Escenarios!$A$12:$A$36,0))*I13 -> 0 | U13: =SUM(Q13:T13) -> 110536.65 | V13: =IF(INDEX(Escenarios!$K$12:$K$36,MATCH($A13,Escenarios!$A$12:$A$36,0))>0,$D13,0) -> 480 | W13: =$E13*INDEX(Escenarios!$K$12:$K$36,MATCH($A13,Escenarios!$A$12:$A$36,0))*F13 -> 99482.985 | X13: =$E13*INDEX(Escenarios!$K$12:$K$36,MATCH($A13,Escenarios!$A$12:$A$36,0))*G13 -> 11053.665 | Y13: =$E13*INDEX(Escenarios!$K$12:$K$36,MATCH($A13,Escenarios!$A$12:$A$36,0))*H13 -> 0 | Z13: =$E13*INDEX(Escenarios!$K$12:$K$36,MATCH($A13,Escenarios!$A$12:$A$36,0))*I13 -> 0 | AA13: =SUM(W13:Z13) -> 110536.65 | AB13: =IF(INDEX(Escenarios!$L$12:$L$36,MATCH($A13,Escenarios!$A$12:$A$36,0))>0,$D13,0) -> 480 | AC13: =$E13*INDEX(Escenarios!$L$12:$L$36,MATCH($A13,Escenarios!$A$12:$A$36,0))*F13 -> 99482.985 | AD13: =$E13*INDEX(Escenarios!$L$12:$L$36,MATCH($A13,Escenarios!$A$12:$A$36,0))*G13 -> 11053.665 | AE13: =$E13*INDEX(Escenarios!$L$12:$L$36,MATCH($A13,Escenarios!$A$12:$A$36,0))*H13 -> 0 | AF13: =$E13*INDEX(Escenarios!$L$12:$L$36,MATCH($A13,Escenarios!$A$12:$A$36,0))*I13 -> 0 | AG13: =SUM(AC13:AF13) -> 110536.65
A14: S24 | B14: Radiological Classification of Areas (RCA) | C14: =INDEX(Escenarios!$D$12:$D$36,MATCH($A14,Escenarios!$A$12:$A$36,0)) -> IDOM | D14: =SUMIFS(Datos!$H$5:$H$291,Datos!$E$5:$E$291,$A14,Datos!$F$5:$F$291,"S3") -> 490 | E14: =SUMIFS(Datos!$J$5:$J$291,Datos!$E$5:$E$291,$A14,Datos!$F$5:$F$291,"S3") -> 112300.65 | F14: =INDEX(Escenarios!$E$12:$E$36,MATCH($A14,Escenarios!$A$12:$A$36,0)) -> 1 | G14: =INDEX(Escenarios!$F$12:$F$36,MATCH($A14,Escenarios!$A$12:$A$36,0)) -> 0 | H14: =INDEX(Escenarios!$G$12:$G$36,MATCH($A14,Escenarios!$A$12:$A$36,0)) -> 0 | I14: =INDEX(Escenarios!$H$12:$H$36,MATCH($A14,Escenarios!$A$12:$A$36,0)) -> 0 | J14: =IF(INDEX(Escenarios!$I$12:$I$36,MATCH($A14,Escenarios!$A$12:$A$36,0))>0,$D14,0) -> 490 | K14: =$E14*INDEX(Escenarios!$I$12:$I$36,MATCH($A14,Escenarios!$A$12:$A$36,0))*F14 -> 112300.65 | L14: =$E14*INDEX(Escenarios!$I$12:$I$36,MATCH($A14,Escenarios!$A$12:$A$36,0))*G14 -> 0 | M14: =$E14*INDEX(Escenarios!$I$12:$I$36,MATCH($A14,Escenarios!$A$12:$A$36,0))*H14 -> 0 | N14: =$E14*INDEX(Escenarios!$I$12:$I$36,MATCH($A14,Escenarios!$A$12:$A$36,0))*I14 -> 0 | O14: =SUM(K14:N14) -> 112300.65 | P14: =IF(INDEX(Escenarios!$J$12:$J$36,MATCH($A14,Escenarios!$A$12:$A$36,0))>0,$D14,0) -> 490 | Q14: =$E14*INDEX(Escenarios!$J$12:$J$36,MATCH($A14,Escenarios!$A$12:$A$36,0))*F14 -> 112300.65 | R14: =$E14*INDEX(Escenarios!$J$12:$J$36,MATCH($A14,Escenarios!$A$12:$A$36,0))*G14 -> 0 | S14: =$E14*INDEX(Escenarios!$J$12:$J$36,MATCH($A14,Escenarios!$A$12:$A$36,0))*H14 -> 0 | T14: =$E14*INDEX(Escenarios!$J$12:$J$36,MATCH($A14,Escenarios!$A$12:$A$36,0))*I14 -> 0 | U14: =SUM(Q14:T14) -> 112300.65 | V14: =IF(INDEX(Escenarios!$K$12:$K$36,MATCH($A14,Escenarios!$A$12:$A$36,0))>0,$D14,0) -> 490 | W14: =$E14*INDEX(Escenarios!$K$12:$K$36,MATCH($A14,Escenarios!$A$12:$A$36,0))*F14 -> 112300.65 | X14: =$E14*INDEX(Escenarios!$K$12:$K$36,MATCH($A14,Escenarios!$A$12:$A$36,0))*G14 -> 0 | Y14: =$E14*INDEX(Escenarios!$K$12:$K$36,MATCH($A14,Escenarios!$A$12:$A$36,0))*H14 -> 0 | Z14: =$E14*INDEX(Escenarios!$K$12:$K$36,MATCH($A14,Escenarios!$A$12:$A$36,0))*I14 -> 0 | AA14: =SUM(W14:Z14) -> 112300.65 | AB14: =IF(INDEX(Escenarios!$L$12:$L$36,MATCH($A14,Escenarios!$A$12:$A$36,0))>0,$D14,0) -> 490 | AC14: =$E14*INDEX(Escenarios!$L$12:$L$36,MATCH($A14,Escenarios!$A$12:$A$36,0))*F14 -> 112300.65 | AD14: =$E14*INDEX(Escenarios!$L$12:$L$36,MATCH($A14,Escenarios!$A$12:$A$36,0))*G14 -> 0 | AE14: =$E14*INDEX(Escenarios!$L$12:$L$36,MATCH($A14,Escenarios!$A$12:$A$36,0))*H14 -> 0 | AF14: =$E14*INDEX(Escenarios!$L$12:$L$36,MATCH($A14,Escenarios!$A$12:$A$36,0))*I14 -> 0 | AG14: =SUM(AC14:AF14) -> 112300.65
A15: S26 | B15: Structures Systems and Components (SSC) Categorisation Report | C15: =INDEX(Escenarios!$D$12:$D$36,MATCH($A15,Escenarios!$A$12:$A$36,0)) -> IDOM | D15: =SUMIFS(Datos!$H$5:$H$291,Datos!$E$5:$E$291,$A15,Datos!$F$5:$F$291,"S3") -> 470 | E15: =SUMIFS(Datos!$J$5:$J$291,Datos!$E$5:$E$291,$A15,Datos!$F$5:$F$291,"S3") -> 108941.7 | F15: =INDEX(Escenarios!$E$12:$E$36,MATCH($A15,Escenarios!$A$12:$A$36,0)) -> 1 | G15: =INDEX(Escenarios!$F$12:$F$36,MATCH($A15,Escenarios!$A$12:$A$36,0)) -> 0 | H15: =INDEX(Escenarios!$G$12:$G$36,MATCH($A15,Escenarios!$A$12:$A$36,0)) -> 0 | I15: =INDEX(Escenarios!$H$12:$H$36,MATCH($A15,Escenarios!$A$12:$A$36,0)) -> 0 | J15: =IF(INDEX(Escenarios!$I$12:$I$36,MATCH($A15,Escenarios!$A$12:$A$36,0))>0,$D15,0) -> 470 | K15: =$E15*INDEX(Escenarios!$I$12:$I$36,MATCH($A15,Escenarios!$A$12:$A$36,0))*F15 -> 108941.7 | L15: =$E15*INDEX(Escenarios!$I$12:$I$36,MATCH($A15,Escenarios!$A$12:$A$36,0))*G15 -> 0 | M15: =$E15*INDEX(Escenarios!$I$12:$I$36,MATCH($A15,Escenarios!$A$12:$A$36,0))*H15 -> 0 | N15: =$E15*INDEX(Escenarios!$I$12:$I$36,MATCH($A15,Escenarios!$A$12:$A$36,0))*I15 -> 0 | O15: =SUM(K15:N15) -> 108941.7 | P15: =IF(INDEX(Escenarios!$J$12:$J$36,MATCH($A15,Escenarios!$A$12:$A$36,0))>0,$D15,0) -> 470 | Q15: =$E15*INDEX(Escenarios!$J$12:$J$36,MATCH($A15,Escenarios!$A$12:$A$36,0))*F15 -> 108941.7 | R15: =$E15*INDEX(Escenarios!$J$12:$J$36,MATCH($A15,Escenarios!$A$12:$A$36,0))*G15 -> 0 | S15: =$E15*INDEX(Escenarios!$J$12:$J$36,MATCH($A15,Escenarios!$A$12:$A$36,0))*H15 -> 0 | T15: =$E15*INDEX(Escenarios!$J$12:$J$36,MATCH($A15,Escenarios!$A$12:$A$36,0))*I15 -> 0 | U15: =SUM(Q15:T15) -> 108941.7 | V15: =IF(INDEX(Escenarios!$K$12:$K$36,MATCH($A15,Escenarios!$A$12:$A$36,0))>0,$D15,0) -> 0 | W15: =$E15*INDEX(Escenarios!$K$12:$K$36,MATCH($A15,Escenarios!$A$12:$A$36,0))*F15 -> 0 | X15: =$E15*INDEX(Escenarios!$K$12:$K$36,MATCH($A15,Escenarios!$A$12:$A$36,0))*G15 -> 0 | Y15: =$E15*INDEX(Escenarios!$K$12:$K$36,MATCH($A15,Escenarios!$A$12:$A$36,0))*H15 -> 0 | Z15: =$E15*INDEX(Escenarios!$K$12:$K$36,MATCH($A15,Escenarios!$A$12:$A$36,0))*I15 -> 0 | AA15: =SUM(W15:Z15) -> 0 | AB15: =IF(INDEX(Escenarios!$L$12:$L$36,MATCH($A15,Escenarios!$A$12:$A$36,0))>0,$D15,0) -> 0 | AC15: =$E15*INDEX(Escenarios!$L$12:$L$36,MATCH($A15,Escenarios!$A$12:$A$36,0))*F15 -> 0 | AD15: =$E15*INDEX(Escenarios!$L$12:$L$36,MATCH($A15,Escenarios!$A$12:$A$36,0))*G15 -> 0 | AE15: =$E15*INDEX(Escenarios!$L$12:$L$36,MATCH($A15,Escenarios!$A$12:$A$36,0))*H15 -> 0 | AF15: =$E15*INDEX(Escenarios!$L$12:$L$36,MATCH($A15,Escenarios!$A$12:$A$36,0))*I15 -> 0 | AG15: =SUM(AC15:AF15) -> 0
A16: S27 | B16: Structures Systems and Components (SSC) Register | C16: =INDEX(Escenarios!$D$12:$D$36,MATCH($A16,Escenarios!$A$12:$A$36,0)) -> IDOM | D16: =SUMIFS(Datos!$H$5:$H$291,Datos!$E$5:$E$291,$A16,Datos!$F$5:$F$291,"S3") -> 395 | E16: =SUMIFS(Datos!$J$5:$J$291,Datos!$E$5:$E$291,$A16,Datos!$F$5:$F$291,"S3") -> 89100.375 | F16: =INDEX(Escenarios!$E$12:$E$36,MATCH($A16,Escenarios!$A$12:$A$36,0)) -> 1 | G16: =INDEX(Escenarios!$F$12:$F$36,MATCH($A16,Escenarios!$A$12:$A$36,0)) -> 0 | H16: =INDEX(Escenarios!$G$12:$G$36,MATCH($A16,Escenarios!$A$12:$A$36,0)) -> 0 | I16: =INDEX(Escenarios!$H$12:$H$36,MATCH($A16,Escenarios!$A$12:$A$36,0)) -> 0 | J16: =IF(INDEX(Escenarios!$I$12:$I$36,MATCH($A16,Escenarios!$A$12:$A$36,0))>0,$D16,0) -> 395 | K16: =$E16*INDEX(Escenarios!$I$12:$I$36,MATCH($A16,Escenarios!$A$12:$A$36,0))*F16 -> 89100.375 | L16: =$E16*INDEX(Escenarios!$I$12:$I$36,MATCH($A16,Escenarios!$A$12:$A$36,0))*G16 -> 0 | M16: =$E16*INDEX(Escenarios!$I$12:$I$36,MATCH($A16,Escenarios!$A$12:$A$36,0))*H16 -> 0 | N16: =$E16*INDEX(Escenarios!$I$12:$I$36,MATCH($A16,Escenarios!$A$12:$A$36,0))*I16 -> 0 | O16: =SUM(K16:N16) -> 89100.375 | P16: =IF(INDEX(Escenarios!$J$12:$J$36,MATCH($A16,Escenarios!$A$12:$A$36,0))>0,$D16,0) -> 395 | Q16: =$E16*INDEX(Escenarios!$J$12:$J$36,MATCH($A16,Escenarios!$A$12:$A$36,0))*F16 -> 89100.375 | R16: =$E16*INDEX(Escenarios!$J$12:$J$36,MATCH($A16,Escenarios!$A$12:$A$36,0))*G16 -> 0 | S16: =$E16*INDEX(Escenarios!$J$12:$J$36,MATCH($A16,Escenarios!$A$12:$A$36,0))*H16 -> 0 | T16: =$E16*INDEX(Escenarios!$J$12:$J$36,MATCH($A16,Escenarios!$A$12:$A$36,0))*I16 -> 0 | U16: =SUM(Q16:T16) -> 89100.375 | V16: =IF(INDEX(Escenarios!$K$12:$K$36,MATCH($A16,Escenarios!$A$12:$A$36,0))>0,$D16,0) -> 0 | W16: =$E16*INDEX(Escenarios!$K$12:$K$36,MATCH($A16,Escenarios!$A$12:$A$36,0))*F16 -> 0 | X16: =$E16*INDEX(Escenarios!$K$12:$K$36,MATCH($A16,Escenarios!$A$12:$A$36,0))*G16 -> 0 | Y16: =$E16*INDEX(Escenarios!$K$12:$K$36,MATCH($A16,Escenarios!$A$12:$A$36,0))*H16 -> 0 | Z16: =$E16*INDEX(Escenarios!$K$12:$K$36,MATCH($A16,Escenarios!$A$12:$A$36,0))*I16 -> 0 | AA16: =SUM(W16:Z16) -> 0 | AB16: =IF(INDEX(Escenarios!$L$12:$L$36,MATCH($A16,Escenarios!$A$12:$A$36,0))>0,$D16,0) -> 0 | AC16: =$E16*INDEX(Escenarios!$L$12:$L$36,MATCH($A16,Escenarios!$A$12:$A$36,0))*F16 -> 0 | AD16: =$E16*INDEX(Escenarios!$L$12:$L$36,MATCH($A16,Escenarios!$A$12:$A$36,0))*G16 -> 0 | AE16: =$E16*INDEX(Escenarios!$L$12:$L$36,MATCH($A16,Escenarios!$A$12:$A$36,0))*H16 -> 0 | AF16: =$E16*INDEX(Escenarios!$L$12:$L$36,MATCH($A16,Escenarios!$A$12:$A$36,0))*I16 -> 0 | AG16: =SUM(AC16:AF16) -> 0
A17: S29 | B17: Design Substantiation Report | C17: =INDEX(Escenarios!$D$12:$D$36,MATCH($A17,Escenarios!$A$12:$A$36,0)) -> Compartido | D17: =SUMIFS(Datos!$H$5:$H$291,Datos!$E$5:$E$291,$A17,Datos!$F$5:$F$291,"S3") -> 350 | E17: =SUMIFS(Datos!$J$5:$J$291,Datos!$E$5:$E$291,$A17,Datos!$F$5:$F$291,"S3") -> 80445.75 | F17: =INDEX(Escenarios!$E$12:$E$36,MATCH($A17,Escenarios!$A$12:$A$36,0)) -> 0.9 | G17: =INDEX(Escenarios!$F$12:$F$36,MATCH($A17,Escenarios!$A$12:$A$36,0)) -> 0.1 | H17: =INDEX(Escenarios!$G$12:$G$36,MATCH($A17,Escenarios!$A$12:$A$36,0)) -> 0 | I17: =INDEX(Escenarios!$H$12:$H$36,MATCH($A17,Escenarios!$A$12:$A$36,0)) -> 0 | J17: =IF(INDEX(Escenarios!$I$12:$I$36,MATCH($A17,Escenarios!$A$12:$A$36,0))>0,$D17,0) -> 350 | K17: =$E17*INDEX(Escenarios!$I$12:$I$36,MATCH($A17,Escenarios!$A$12:$A$36,0))*F17 -> 72401.175 | L17: =$E17*INDEX(Escenarios!$I$12:$I$36,MATCH($A17,Escenarios!$A$12:$A$36,0))*G17 -> 8044.575 | M17: =$E17*INDEX(Escenarios!$I$12:$I$36,MATCH($A17,Escenarios!$A$12:$A$36,0))*H17 -> 0 | N17: =$E17*INDEX(Escenarios!$I$12:$I$36,MATCH($A17,Escenarios!$A$12:$A$36,0))*I17 -> 0 | O17: =SUM(K17:N17) -> 80445.75 | P17: =IF(INDEX(Escenarios!$J$12:$J$36,MATCH($A17,Escenarios!$A$12:$A$36,0))>0,$D17,0) -> 350 | Q17: =$E17*INDEX(Escenarios!$J$12:$J$36,MATCH($A17,Escenarios!$A$12:$A$36,0))*F17 -> 72401.175 | R17: =$E17*INDEX(Escenarios!$J$12:$J$36,MATCH($A17,Escenarios!$A$12:$A$36,0))*G17 -> 8044.575 | S17: =$E17*INDEX(Escenarios!$J$12:$J$36,MATCH($A17,Escenarios!$A$12:$A$36,0))*H17 -> 0 | T17: =$E17*INDEX(Escenarios!$J$12:$J$36,MATCH($A17,Escenarios!$A$12:$A$36,0))*I17 -> 0 | U17: =SUM(Q17:T17) -> 80445.75 | V17: =IF(INDEX(Escenarios!$K$12:$K$36,MATCH($A17,Escenarios!$A$12:$A$36,0))>0,$D17,0) -> 350 | W17: =$E17*INDEX(Escenarios!$K$12:$K$36,MATCH($A17,Escenarios!$A$12:$A$36,0))*F17 -> 72401.175 | X17: =$E17*INDEX(Escenarios!$K$12:$K$36,MATCH($A17,Escenarios!$A$12:$A$36,0))*G17 -> 8044.575 | Y17: =$E17*INDEX(Escenarios!$K$12:$K$36,MATCH($A17,Escenarios!$A$12:$A$36,0))*H17 -> 0 | Z17: =$E17*INDEX(Escenarios!$K$12:$K$36,MATCH($A17,Escenarios!$A$12:$A$36,0))*I17 -> 0 | AA17: =SUM(W17:Z17) -> 80445.75 | AB17: =IF(INDEX(Escenarios!$L$12:$L$36,MATCH($A17,Escenarios!$A$12:$A$36,0))>0,$D17,0) -> 350 | AC17: =$E17*INDEX(Escenarios!$L$12:$L$36,MATCH($A17,Escenarios!$A$12:$A$36,0))*F17 -> 72401.175 | AD17: =$E17*INDEX(Escenarios!$L$12:$L$36,MATCH($A17,Escenarios!$A$12:$A$36,0))*G17 -> 8044.575 | AE17: =$E17*INDEX(Escenarios!$L$12:$L$36,MATCH($A17,Escenarios!$A$12:$A$36,0))*H17 -> 0 | AF17: =$E17*INDEX(Escenarios!$L$12:$L$36,MATCH($A17,Escenarios!$A$12:$A$36,0))*I17 -> 0 | AG17: =SUM(AC17:AF17) -> 80445.75
A18: S3 | B18: Human Factors Hazards Identification and Control Plan (HFHICP) | C18: =INDEX(Escenarios!$D$12:$D$36,MATCH($A18,Escenarios!$A$12:$A$36,0)) -> Plan Safe | D18: =SUMIFS(Datos!$H$5:$H$291,Datos!$E$5:$E$291,$A18,Datos!$F$5:$F$291,"S3") -> 540 | E18: =SUMIFS(Datos!$J$5:$J$291,Datos!$E$5:$E$291,$A18,Datos!$F$5:$F$291,"S3") -> 124531.05 | F18: =INDEX(Escenarios!$E$12:$E$36,MATCH($A18,Escenarios!$A$12:$A$36,0)) -> 0 | G18: =INDEX(Escenarios!$F$12:$F$36,MATCH($A18,Escenarios!$A$12:$A$36,0)) -> 1 | H18: =INDEX(Escenarios!$G$12:$G$36,MATCH($A18,Escenarios!$A$12:$A$36,0)) -> 0 | I18: =INDEX(Escenarios!$H$12:$H$36,MATCH($A18,Escenarios!$A$12:$A$36,0)) -> 0 | J18: =IF(INDEX(Escenarios!$I$12:$I$36,MATCH($A18,Escenarios!$A$12:$A$36,0))>0,$D18,0) -> 540 | K18: =$E18*INDEX(Escenarios!$I$12:$I$36,MATCH($A18,Escenarios!$A$12:$A$36,0))*F18 -> 0 | L18: =$E18*INDEX(Escenarios!$I$12:$I$36,MATCH($A18,Escenarios!$A$12:$A$36,0))*G18 -> 124531.05 | M18: =$E18*INDEX(Escenarios!$I$12:$I$36,MATCH($A18,Escenarios!$A$12:$A$36,0))*H18 -> 0 | N18: =$E18*INDEX(Escenarios!$I$12:$I$36,MATCH($A18,Escenarios!$A$12:$A$36,0))*I18 -> 0 | O18: =SUM(K18:N18) -> 124531.05 | P18: =IF(INDEX(Escenarios!$J$12:$J$36,MATCH($A18,Escenarios!$A$12:$A$36,0))>0,$D18,0) -> 0 | Q18: =$E18*INDEX(Escenarios!$J$12:$J$36,MATCH($A18,Escenarios!$A$12:$A$36,0))*F18 -> 0 | R18: =$E18*INDEX(Escenarios!$J$12:$J$36,MATCH($A18,Escenarios!$A$12:$A$36,0))*G18 -> 0 | S18: =$E18*INDEX(Escenarios!$J$12:$J$36,MATCH($A18,Escenarios!$A$12:$A$36,0))*H18 -> 0 | T18: =$E18*INDEX(Escenarios!$J$12:$J$36,MATCH($A18,Escenarios!$A$12:$A$36,0))*I18 -> 0 | U18: =SUM(Q18:T18) -> 0 | V18: =IF(INDEX(Escenarios!$K$12:$K$36,MATCH($A18,Escenarios!$A$12:$A$36,0))>0,$D18,0) -> 0 | W18: =$E18*INDEX(Escenarios!$K$12:$K$36,MATCH($A18,Escenarios!$A$12:$A$36,0))*F18 -> 0 | X18: =$E18*INDEX(Escenarios!$K$12:$K$36,MATCH($A18,Escenarios!$A$12:$A$36,0))*G18 -> 0 | Y18: =$E18*INDEX(Escenarios!$K$12:$K$36,MATCH($A18,Escenarios!$A$12:$A$36,0))*H18 -> 0 | Z18: =$E18*INDEX(Escenarios!$K$12:$K$36,MATCH($A18,Escenarios!$A$12:$A$36,0))*I18 -> 0 | AA18: =SUM(W18:Z18) -> 0 | AB18: =IF(INDEX(Escenarios!$L$12:$L$36,MATCH($A18,Escenarios!$A$12:$A$36,0))>0,$D18,0) -> 540 | AC18: =$E18*INDEX(Escenarios!$L$12:$L$36,MATCH($A18,Escenarios!$A$12:$A$36,0))*F18 -> 0 | AD18: =$E18*INDEX(Escenarios!$L$12:$L$36,MATCH($A18,Escenarios!$A$12:$A$36,0))*G18 -> 62265.525 | AE18: =$E18*INDEX(Escenarios!$L$12:$L$36,MATCH($A18,Escenarios!$A$12:$A$36,0))*H18 -> 0 | AF18: =$E18*INDEX(Escenarios!$L$12:$L$36,MATCH($A18,Escenarios!$A$12:$A$36,0))*I18 -> 0 | AG18: =SUM(AC18:AF18) -> 62265.525
A19: S30 | B19: Human Factors Substantiation/Assurance Report | C19: =INDEX(Escenarios!$D$12:$D$36,MATCH($A19,Escenarios!$A$12:$A$36,0)) -> Plan Safe | D19: =SUMIFS(Datos!$H$5:$H$291,Datos!$E$5:$E$291,$A19,Datos!$F$5:$F$291,"S3") -> 285 | E19: =SUMIFS(Datos!$J$5:$J$291,Datos!$E$5:$E$291,$A19,Datos!$F$5:$F$291,"S3") -> 65275.35 | F19: =INDEX(Escenarios!$E$12:$E$36,MATCH($A19,Escenarios!$A$12:$A$36,0)) -> 0 | G19: =INDEX(Escenarios!$F$12:$F$36,MATCH($A19,Escenarios!$A$12:$A$36,0)) -> 1 | H19: =INDEX(Escenarios!$G$12:$G$36,MATCH($A19,Escenarios!$A$12:$A$36,0)) -> 0 | I19: =INDEX(Escenarios!$H$12:$H$36,MATCH($A19,Escenarios!$A$12:$A$36,0)) -> 0 | J19: =IF(INDEX(Escenarios!$I$12:$I$36,MATCH($A19,Escenarios!$A$12:$A$36,0))>0,$D19,0) -> 285 | K19: =$E19*INDEX(Escenarios!$I$12:$I$36,MATCH($A19,Escenarios!$A$12:$A$36,0))*F19 -> 0 | L19: =$E19*INDEX(Escenarios!$I$12:$I$36,MATCH($A19,Escenarios!$A$12:$A$36,0))*G19 -> 65275.35 | M19: =$E19*INDEX(Escenarios!$I$12:$I$36,MATCH($A19,Escenarios!$A$12:$A$36,0))*H19 -> 0 | N19: =$E19*INDEX(Escenarios!$I$12:$I$36,MATCH($A19,Escenarios!$A$12:$A$36,0))*I19 -> 0 | O19: =SUM(K19:N19) -> 65275.35 | P19: =IF(INDEX(Escenarios!$J$12:$J$36,MATCH($A19,Escenarios!$A$12:$A$36,0))>0,$D19,0) -> 0 | Q19: =$E19*INDEX(Escenarios!$J$12:$J$36,MATCH($A19,Escenarios!$A$12:$A$36,0))*F19 -> 0 | R19: =$E19*INDEX(Escenarios!$J$12:$J$36,MATCH($A19,Escenarios!$A$12:$A$36,0))*G19 -> 0 | S19: =$E19*INDEX(Escenarios!$J$12:$J$36,MATCH($A19,Escenarios!$A$12:$A$36,0))*H19 -> 0 | T19: =$E19*INDEX(Escenarios!$J$12:$J$36,MATCH($A19,Escenarios!$A$12:$A$36,0))*I19 -> 0 | U19: =SUM(Q19:T19) -> 0 | V19: =IF(INDEX(Escenarios!$K$12:$K$36,MATCH($A19,Escenarios!$A$12:$A$36,0))>0,$D19,0) -> 0 | W19: =$E19*INDEX(Escenarios!$K$12:$K$36,MATCH($A19,Escenarios!$A$12:$A$36,0))*F19 -> 0 | X19: =$E19*INDEX(Escenarios!$K$12:$K$36,MATCH($A19,Escenarios!$A$12:$A$36,0))*G19 -> 0 | Y19: =$E19*INDEX(Escenarios!$K$12:$K$36,MATCH($A19,Escenarios!$A$12:$A$36,0))*H19 -> 0 | Z19: =$E19*INDEX(Escenarios!$K$12:$K$36,MATCH($A19,Escenarios!$A$12:$A$36,0))*I19 -> 0 | AA19: =SUM(W19:Z19) -> 0 | AB19: =IF(INDEX(Escenarios!$L$12:$L$36,MATCH($A19,Escenarios!$A$12:$A$36,0))>0,$D19,0) -> 285 | AC19: =$E19*INDEX(Escenarios!$L$12:$L$36,MATCH($A19,Escenarios!$A$12:$A$36,0))*F19 -> 0 | AD19: =$E19*INDEX(Escenarios!$L$12:$L$36,MATCH($A19,Escenarios!$A$12:$A$36,0))*G19 -> 32637.675 | AE19: =$E19*INDEX(Escenarios!$L$12:$L$36,MATCH($A19,Escenarios!$A$12:$A$36,0))*H19 -> 0 | AF19: =$E19*INDEX(Escenarios!$L$12:$L$36,MATCH($A19,Escenarios!$A$12:$A$36,0))*I19 -> 0 | AG19: =SUM(AC19:AF19) -> 32637.675
B20: Subtotal Stage 3 (entregables) | D20: =SUM(D8:D19) -> 6420 | E20: =SUM(E8:E19) -> 1469323.8 | J20: =SUM(J8:J19) -> 6420 | K20: =SUM(K8:K19) -> 1212914.3 | L20: =SUM(L8:L19) -> 256409.53 | M20: =SUM(M8:M19) -> 0 | N20: =SUM(N8:N19) -> 0 | O20: =SUM(O8:O19) -> 1469323.8 | P20: =SUM(P8:P19) -> 5595 | Q20: =SUM(Q8:Q19) -> 1212914.3 | ... AG20: =SUM(AG8:AG19) -> 1176378.5
B21: Ajustes (ninguno en este stage) | K21: 0 | L21: 0 | M21: 0 | N21: 0 | O21: 0 | Q21: 0 | R21: 0 | S21: 0 | T21: 0 | U21: 0 | W21: 0 | X21: 0 | Y21: 0 | Z21: 0 | AA21: 0 | AC21: 0 | AD21: 0 | AE21: 0 | AF21: 0 | AG21: 0
B22: TOTAL STAGE 3 | D22: =D20 -> 6420 | E22: =E20 -> 1469323.8 | J22: =J20 -> 6420 | K22: =K20+K21 -> 1212914.3 | L22: =L20+L21 -> 256409.53 | M22: =M20+M21 -> 0 | N22: =N20+N21 -> 0 | O22: =O20+O21 -> 1469323.8 | P22: =P20 -> 5595 | Q22: =Q20+Q21 -> 1212914.3 | R22: =R20+R21 -> 66603.128 | S22: =S20+S21 -> 0 | T22: =T20+T21 -> 0 | U22: =U20+U21 -> 1279517.4 | V22: =V20 -> 4730 | W22: =W20+W21 -> 1014872.2 | X22: =X20+X21 -> 66603.128 | Y22: =Y20+Y21 -> 0 | Z22: =Z20+Z21 -> 0 | AA22: =AA20+AA21 -> 1081475.3 | AB22: =AB20 -> 5555 | AC22: =AC20+AC21 -> 1014872.2 | AD22: =AD20+AD21 -> 161506.33 | AE22: =AE20+AE21 -> 0 | AF22: =AF20+AF21 -> 0 | AG22: =AG20+AG21 -> 1176378.5
B24: Referencia: oferta original por empresa (sin escenarios ni ajustes) | E24: =SUM(F24:I24) -> 1469323.8 | F24: =SUMPRODUCT($E$8:$E$19,F$8:F$19) -> 1212914.3 | G24: =SUMPRODUCT($E$8:$E$19,G$8:G$19) -> 256409.53 | H24: =SUMPRODUCT($E$8:$E$19,H$8:H$19) -> 0 | I24: =SUMPRODUCT($E$8:$E$19,I$8:I$19) -> 0

Sheet Resumen
B1: Resumen · Lump sum Stages 1–3 por empresa y escenario (AUD)
B2: NMMP · PSC002818 · alcance nuclear y radiológico de IDOM. La referencia es la oferta original (horas × tarifa) sin escenarios ni ajustes.
B4: Panel de control
B5: Reducción de precio del Stage 1 | C5: 0 | D5: Indicador: escribe el % y todo el libro se actualiza.
B6: Quién absorbe la reducción del Stage 1 | C6: IDOM | D6: IDOM = sale entera de IDOM · Proporcional = cada empresa en proporción a su parte del Stage 1.
B7: Descontar el retrabajo del Stage 2 | C7: ='Stage 2'!$C$4 -> No | D7: Se cambia en la pestaña Stage 2 (celda C4).
B8: Participación de Plan Safe / Synertec en compartidos | C8: =TEXT(Escenarios!$B$5,"0%")&" / "&TEXT(Escenarios!$B$6,"0%") -> 10% / 0% | D8: Se cambia en la pestaña Escenarios.
B11: 1 · Lump sum Stages 1–3 por empresa
B12: Escenario | C12: Horas | D12: IDOM | E12: Plan Safe | F12: Synertec | G12: INVAP | H12: Total | I12: Δ vs original | J12: % reducción
B13: Oferta original (referencia) | C13: ='Stage 1'!D14+'Stage 2'!D18+'Stage 3'!D22 -> 11025 | D13: ='Stage 1'!F16+'Stage 2'!F20+'Stage 3'!F24 -> 1882791.1 | E13: ='Stage 1'!G16+'Stage 2'!G20+'Stage 3'!G24 -> 575618.56 | F13: ='Stage 1'!H16+'Stage 2'!H20+'Stage 3'!H24 -> 0 | G13: ='Stage 1'!I16+'Stage 2'!I20+'Stage 3'!I24 -> 78836.1 | H13: =SUM(D13:G13) -> 2537245.7 | I13: - | J13: -
B14: ="Esc. 1 · "&Escenarios!I$11 -> Esc. 1 · Original | C14: ='Stage 1'!J14+'Stage 2'!J18+'Stage 3'!J22 -> 11025 | D14: ='Stage 1'!K14+'Stage 2'!K18+'Stage 3'!K22 -> 1882791.1 | E14: ='Stage 1'!L14+'Stage 2'!L18+'Stage 3'!L22 -> 575618.56 | F14: ='Stage 1'!M14+'Stage 2'!M18+'Stage 3'!M22 -> 0 | G14: ='Stage 1'!N14+'Stage 2'!N18+'Stage 3'!N22 -> 78836.1 | H14: =SUM(D14:G14) -> 2537245.7 | I14: =H14-$H$13 -> 0 | J14: =IF($H$13=0,0,1-H14/$H$13) -> 0
B15: ="Esc. 2 · "&Escenarios!J$11 -> Esc. 2 · Sin las 4 tareas de Plan Safe | C15: ='Stage 1'!P14+'Stage 2'!P18+'Stage 3'!P22 -> 9050 | D15: ='Stage 1'!Q14+'Stage 2'!Q18+'Stage 3'!Q22 -> 1882791.1 | E15: ='Stage 1'!R14+'Stage 2'!R18+'Stage 3'!R22 -> 118878.53 | F15: ='Stage 1'!S14+'Stage 2'!S18+'Stage 3'!S22 -> 0 | G15: ='Stage 1'!T14+'Stage 2'!T18+'Stage 3'!T22 -> 78836.1 | H15: =SUM(D15:G15) -> 2080505.7 | I15: =H15-$H$13 -> -456740.03 | J15: =IF($H$13=0,0,1-H15/$H$13) -> 0.18001411
B16: ="Esc. 3 · "&Escenarios!K$11 -> Esc. 3 · Sin tareas Plan Safe ni SSC | C16: ='Stage 1'!V14+'Stage 2'!V18+'Stage 3'!V22 -> 7750 | D16: ='Stage 1'!W14+'Stage 2'!W18+'Stage 3'!W22 -> 1585013.2 | E16: ='Stage 1'!X14+'Stage 2'!X18+'Stage 3'!X22 -> 118878.53 | F16: ='Stage 1'!Y14+'Stage 2'!Y18+'Stage 3'!Y22 -> 0 | G16: ='Stage 1'!Z14+'Stage 2'!Z18+'Stage 3'!Z22 -> 78836.1 | H16: =SUM(D16:G16) -> 1782727.8 | I16: =H16-$H$13 -> -754517.93 | J16: =IF($H$13=0,0,1-H16/$H$13) -> 0.29737676
B17: ="Esc. 4 · "&Escenarios!L$11 -> Esc. 4 · Sin SSC, tareas Plan Safe al 50 % | C17: ='Stage 1'!AB14+'Stage 2'!AB18+'Stage 3'!AB22 -> 9725 | D17: ='Stage 1'!AC14+'Stage 2'!AC18+'Stage 3'!AC22 -> 1585013.2 | E17: ='Stage 1'!AD14+'Stage 2'!AD18+'Stage 3'!AD22 -> 347248.54 | F17: ='Stage 1'!AE14+'Stage 2'!AE18+'Stage 3'!AE22 -> 0 | G17: ='Stage 1'!AF14+'Stage 2'!AF18+'Stage 3'!AF22 -> 78836.1 | H17: =SUM(D17:G17) -> 2011097.8 | I17: =H17-$H$13 -> -526147.91 | J17: =IF($H$13=0,0,1-H17/$H$13) -> 0.20736971
B18: Control: total de la herramienta para S1–S3 (Precio y contingencias, bloque «S1–S3 · fijo y firme») | H18: 2537246 | I18: =ROUND(H13-H18,0) -> 0 | J18: =IF(ABS(I18)<=1,"cuadra","revisar") -> cuadra
B21: 2 · Reducción por empresa respecto a la oferta original
B22: Escenario | D22: IDOM | E22: Plan Safe | F22: Synertec | G22: INVAP | H22: Total
B23: =B14 -> Esc. 1 · Original | D23: =IF(D$13=0,0,1-D14/D$13) -> 0 | E23: =IF(E$13=0,0,1-E14/E$13) -> 0 | F23: =IF(F$13=0,0,1-F14/F$13) -> 0 | G23: =IF(G$13=0,0,1-G14/G$13) -> 0 | H23: =IF(H$13=0,0,1-H14/H$13) -> 0
B24: =B15 -> Esc. 2 · Sin las 4 tareas de Plan Safe | D24: =IF(D$13=0,0,1-D15/D$13) -> 0 | E24: =IF(E$13=0,0,1-E15/E$13) -> 0.79347689 | F24: =IF(F$13=0,0,1-F15/F$13) -> 0 | G24: =IF(G$13=0,0,1-G15/G$13) -> 0 | H24: =IF(H$13=0,0,1-H15/H$13) -> 0.18001411
B25: =B16 -> Esc. 3 · Sin tareas Plan Safe ni SSC | D25: =IF(D$13=0,0,1-D16/D$13) -> 0.1581577 | E25: =IF(E$13=0,0,1-E16/E$13) -> 0.79347689 | F25: =IF(F$13=0,0,1-F16/F$13) -> 0 | G25: =IF(G$13=0,0,1-G16/G$13) -> 0 | H25: =IF(H$13=0,0,1-H16/H$13) -> 0.29737676
B26: =B17 -> Esc. 4 · Sin SSC, tareas Plan Safe al 50 % | D26: =IF(D$13=0,0,1-D17/D$13) -> 0.1581577 | E26: =IF(E$13=0,0,1-E17/E$13) -> 0.39673845 | F26: =IF(F$13=0,0,1-F17/F$13) -> 0 | G26: =IF(G$13=0,0,1-G17/G$13) -> 0 | H26: =IF(H$13=0,0,1-H17/H$13) -> 0.20736971
B27: Porcentaje de lo que cada empresa deja de facturar frente a su parte de la oferta original. Negativo = factura más.
B29: 3 · Peso de cada empresa en el lump sum
B30: Escenario | D30: IDOM | E30: Plan Safe | F30: Synertec | G30: INVAP | H30: Total
B31: =B13 -> Oferta original (referencia) | D31: =IF($H13=0,0,D13/$H13) -> 0.74206099 | E31: =IF($H13=0,0,E13/$H13) -> 0.22686749 | F31: =IF($H13=0,0,F13/$H13) -> 0 | G31: =IF($H13=0,0,G13/$H13) -> 0.031071527 | H31: =IF($H13=0,0,H13/$H13) -> 1
B32: =B14 -> Esc. 1 · Original | D32: =IF($H14=0,0,D14/$H14) -> 0.74206099 | E32: =IF($H14=0,0,E14/$H14) -> 0.22686749 | F32: =IF($H14=0,0,F14/$H14) -> 0 | G32: =IF($H14=0,0,G14/$H14) -> 0.031071527 | H32: =IF($H14=0,0,H14/$H14) -> 1
B33: =B15 -> Esc. 2 · Sin las 4 tareas de Plan Safe | D33: =IF($H15=0,0,D15/$H15) -> 0.90496799 | E33: =IF($H15=0,0,E15/$H15) -> 0.057139249 | F33: =IF($H15=0,0,F15/$H15) -> 0 | G33: =IF($H15=0,0,G15/$H15) -> 0.037892758 | H33: =IF($H15=0,0,H15/$H15) -> 1
B34: =B16 -> Esc. 3 · Sin tareas Plan Safe ni SSC | D34: =IF($H16=0,0,D16/$H16) -> 0.88909432 | E34: =IF($H16=0,0,E16/$H16) -> 0.066683502 | F34: =IF($H16=0,0,F16/$H16) -> 0 | G34: =IF($H16=0,0,G16/$H16) -> 0.044222175 | H34: =IF($H16=0,0,H16/$H16) -> 1
B35: =B17 -> Esc. 4 · Sin SSC, tareas Plan Safe al 50 % | D35: =IF($H17=0,0,D17/$H17) -> 0.78813331 | E35: =IF($H17=0,0,E17/$H17) -> 0.17266616 | F35: =IF($H17=0,0,F17/$H17) -> 0 | G35: =IF($H17=0,0,G17/$H17) -> 0.03920053 | H35: =IF($H17=0,0,H17/$H17) -> 1
B38: 4 · Precio por stage y escenario
B39: Escenario | D39: Stage 1 | E39: Stage 2 | F39: Stage 3 | G39: Total S1–S3 | H39: % reducción
B40: Oferta original (referencia) | D40: ='Stage 1'!E16 -> 335082.83 | E40: ='Stage 2'!E20 -> 732839.1 | F40: ='Stage 3'!E24 -> 1469323.8 | G40: =SUM(D40:F40) -> 2537245.7 | H40: -
B41: =B14 -> Esc. 1 · Original | D41: ='Stage 1'!O14 -> 335082.83 | E41: ='Stage 2'!O18 -> 732839.1 | F41: ='Stage 3'!O22 -> 1469323.8 | G41: =SUM(D41:F41) -> 2537245.7 | H41: =IF($G$40=0,0,1-G41/$G$40) -> 0
B42: =B15 -> Esc. 2 · Sin las 4 tareas de Plan Safe | D42: ='Stage 1'!U14 -> 227015.77 | E42: ='Stage 2'!U18 -> 573972.53 | F42: ='Stage 3'!U22 -> 1279517.4 | G42: =SUM(D42:F42) -> 2080505.7 | H42: =IF($G$40=0,0,1-G42/$G$40) -> 0.18001411
B43: =B16 -> Esc. 3 · Sin tareas Plan Safe ni SSC | D43: ='Stage 1'!AA14 -> 227015.77 | E43: ='Stage 2'!AA18 -> 474236.7 | F43: ='Stage 3'!AA22 -> 1081475.3 | G43: =SUM(D43:F43) -> 1782727.8 | H43: =IF($G$40=0,0,1-G43/$G$40) -> 0.29737676
B44: =B17 -> Esc. 4 · Sin SSC, tareas Plan Safe al 50 % | D44: ='Stage 1'!AG14 -> 281049.3 | E44: ='Stage 2'!AG18 -> 553669.99 | F44: ='Stage 3'!AG22 -> 1176378.5 | G44: =SUM(D44:F44) -> 2011097.8 | H44: =IF($G$40=0,0,1-G44/$G$40) -> 0.20736971
B47: 5 · Indicador del Stage 1 y retrabajo del Stage 2
B48: Escenario | D48: S1 antes de reducir | E48: Reducción S1 | F48: S1 final | G48: Reducción / lump sum | H48: Retrabajo S2 descontado
B49: =B14 -> Esc. 1 · Original | D49: ='Stage 1'!O12 -> 335082.83 | E49: ='Stage 1'!O13 -> 0 | F49: =D49+E49 -> 335082.83 | G49: =IF(H14=0,0,-E49/(H14-E49-H49)) -> 0 | H49: ='Stage 2'!O17 -> 0
B50: =B15 -> Esc. 2 · Sin las 4 tareas de Plan Safe | D50: ='Stage 1'!U12 -> 227015.77 | E50: ='Stage 1'!U13 -> 0 | F50: =D50+E50 -> 227015.77 | G50: =IF(H15=0,0,-E50/(H15-E50-H50)) -> 0 | H50: ='Stage 2'!U17 -> 0
B51: =B16 -> Esc. 3 · Sin tareas Plan Safe ni SSC | D51: ='Stage 1'!AA12 -> 227015.77 | E51: ='Stage 1'!AA13 -> 0 | F51: =D51+E51 -> 227015.77 | G51: =IF(H16=0,0,-E51/(H16-E51-H51)) -> 0 | H51: ='Stage 2'!AA17 -> 0
B52: =B17 -> Esc. 4 · Sin SSC, tareas Plan Safe al 50 % | D52: ='Stage 1'!AG12 -> 281049.3 | E52: ='Stage 1'!AG13 -> 0 | F52: =D52+E52 -> 281049.3 | G52: =IF(H17=0,0,-E52/(H17-E52-H52)) -> 0 | H52: ='Stage 2'!AG17 -> 0
B53: «Reducción / lump sum» = lo que pesa la reducción del Stage 1 sobre el lump sum S1–S3 del escenario antes de aplicar ningún ajuste.
B55: Criterios:
B56: · Importes en AUD = horas × tarifa de venta de la oferta (ya incluye el factor 1,05). Plan Safe e INVAP facturan sus horas a esa misma tarifa, como en la herramienta.
B57: · El retrabajo no es un coste extra: está dentro del precio de IDOM en el Stage 2. Descontarlo reduce el precio en recargo/(1+recargo) de la parte de IDOM de ese stage.
B58: · PM3 (coordinación transversal, partida C) no forma parte del precio de la oferta en la herramienta y no se incluye.
B59: · Synertec no tiene horas en el alcance nuclear; su columna queda a 0 salvo que se le asigne participación en los compartidos o se cambie el tipo de un entregable en Escenarios.

Sheet Escenarios
A1: Definición de escenarios y parámetros de reparto
A2: Azul = editable. Factor de escenario: 1 = entregable incluido a precio completo, 0 = excluido, 0,5 = a mitad de precio.
A4: Parámetro | B4: Valor | C4: Nota
A5: Participación de Plan Safe en los entregables compartidos | B5: 0.1 | C5: Valor de la herramienta (Plan Safe → participación en compartidos). Afecta solo a los entregables «IDOM lidera + inputs especialista».
A6: Participación de Synertec en los entregables compartidos | B6: 0 | C6: Synertec no tiene horas en el modelo nuclear (cubre la ingeniería GMP, fuera de este alcance). 0 % por defecto; súbelo si se le cede parte de los compartidos.
A7: Factor de precio de las tareas de Plan Safe en el escenario 4 | B7: 0.5 | C7: Petición: tareas de Plan Safe a mitad de precio.
A8: Recargo de retrabajo del Stage 2 | B8: 0.35 | C8: Valor de la herramienta. Es un recargo sobre las tareas de IDOM del Stage 2: con 35 %, el retrabajo es 35/135 del precio de IDOM en esa etapa.
I10: Escenario 1 | J10: Escenario 2 | K10: Escenario 3 | L10: Escenario 4
A11: Código | B11: Entregable | C11: Familia técnica | D11: Tipo de reparto | E11: % IDOM | F11: % Plan Safe | G11: % Synertec | H11: % INVAP | I11: Original | J11: Sin las 4 tareas de Plan Safe | K11: Sin tareas Plan Safe ni SSC | L11: Sin SSC, tareas Plan Safe al 50 %
A12: E94 | B12: Radiological Zoning Layout drawing(s) | C12: Zonificación y dosis | D12: IDOM | E12: =IF(D12="IDOM",1,IF(D12="Compartido",1-Escenarios!$B$5-Escenarios!$B$6,0)) -> 1 | F12: =IF(D12="Plan Safe",1,IF(D12="Compartido",Escenarios!$B$5,0)) -> 0 | G12: =IF(D12="Synertec",1,IF(D12="Compartido",Escenarios!$B$6,0)) -> 0 | H12: =IF(D12="INVAP",1,0) -> 0 | I12: 1 | J12: 1 | K12: 1 | L12: 1
A13: S1 | B13: Safety Assurance Plan / Safety Integration Plan | C13: Gestión y aseguramiento de la seguridad | D13: Compartido | E13: =IF(D13="IDOM",1,IF(D13="Compartido",1-Escenarios!$B$5-Escenarios!$B$6,0)) -> 0.9 | F13: =IF(D13="Plan Safe",1,IF(D13="Compartido",Escenarios!$B$5,0)) -> 0.1 | G13: =IF(D13="Synertec",1,IF(D13="Compartido",Escenarios!$B$6,0)) -> 0 | H13: =IF(D13="INVAP",1,0) -> 0 | I13: 1 | J13: 1 | K13: 1 | L13: 1
A14: S9 | B14: Deterministic Safety Assessment(s) (DSA) / Inherent Risk Assessment(s) | C14: Análisis de seguridad | D14: Compartido | E14: =IF(D14="IDOM",1,IF(D14="Compartido",1-Escenarios!$B$5-Escenarios!$B$6,0)) -> 0.9 | F14: =IF(D14="Plan Safe",1,IF(D14="Compartido",Escenarios!$B$5,0)) -> 0.1 | G14: =IF(D14="Synertec",1,IF(D14="Compartido",Escenarios!$B$6,0)) -> 0 | H14: =IF(D14="INVAP",1,0) -> 0 | I14: 1 | J14: 1 | K14: 1 | L14: 1
A15: S10 | B15: Probablisitic Safety Assessment / Quantitative Risk Assessment (s) (QRA) | C15: Análisis de seguridad | D15: Compartido | E15: =IF(D15="IDOM",1,IF(D15="Compartido",1-Escenarios!$B$5-Escenarios!$B$6,0)) -> 0.9 | F15: =IF(D15="Plan Safe",1,IF(D15="Compartido",Escenarios!$B$5,0)) -> 0.1 | G15: =IF(D15="Synertec",1,IF(D15="Compartido",Escenarios!$B$6,0)) -> 0 | H15: =IF(D15="INVAP",1,0) -> 0 | I15: 1 | J15: 1 | K15: 1 | L15: 1
A16: S17 | B16: ALARP (Optioneering) Study | C16: ALARP / optimización | D16: Compartido | E16: =IF(D16="IDOM",1,IF(D16="Compartido",1-Escenarios!$B$5-Escenarios!$B$6,0)) -> 0.9 | F16: =IF(D16="Plan Safe",1,IF(D16="Compartido",Escenarios!$B$5,0)) -> 0.1 | G16: =IF(D16="Synertec",1,IF(D16="Compartido",Escenarios!$B$6,0)) -> 0 | H16: =IF(D16="INVAP",1,0) -> 0 | I16: 1 | J16: 1 | K16: 1 | L16: 1
A17: S18 | B17: ALARP Summary Report (ALARP/SFARP Statement Report) | C17: ALARP / optimización | D17: Compartido | E17: =IF(D17="IDOM",1,IF(D17="Compartido",1-Escenarios!$B$5-Escenarios!$B$6,0)) -> 0.9 | F17: =IF(D17="Plan Safe",1,IF(D17="Compartido",Escenarios!$B$5,0)) -> 0.1 | G17: =IF(D17="Synertec",1,IF(D17="Compartido",Escenarios!$B$6,0)) -> 0 | H17: =IF(D17="INVAP",1,0) -> 0 | I17: 1 | J17: 1 | K17: 1 | L17: 1
A18: S20 | B18: Safety in Design (SiD) Report | C18: Safety in Design | D18: IDOM | E18: =IF(D18="IDOM",1,IF(D18="Compartido",1-Escenarios!$B$5-Escenarios!$B$6,0)) -> 1 | F18: =IF(D18="Plan Safe",1,IF(D18="Compartido",Escenarios!$B$5,0)) -> 0 | G18: =IF(D18="Synertec",1,IF(D18="Compartido",Escenarios!$B$6,0)) -> 0 | H18: =IF(D18="INVAP",1,0) -> 0 | I18: 1 | J18: 1 | K18: 1 | L18: 1
A19: S21 | B19: Radiological Shielding Basis of Design | C19: Blindaje radiológico | D19: IDOM | E19: =IF(D19="IDOM",1,IF(D19="Compartido",1-Escenarios!$B$5-Escenarios!$B$6,0)) -> 1 | F19: =IF(D19="Plan Safe",1,IF(D19="Compartido",Escenarios!$B$5,0)) -> 0 | G19: =IF(D19="Synertec",1,IF(D19="Compartido",Escenarios!$B$6,0)) -> 0 | H19: =IF(D19="INVAP",1,0) -> 0 | I19: 1 | J19: 1 | K19: 1 | L19: 1
A20: S22 | B20: Radiological Shielding Assessment | C20: Blindaje radiológico | D20: IDOM | E20: =IF(D20="IDOM",1,IF(D20="Compartido",1-Escenarios!$B$5-Escenarios!$B$6,0)) -> 1 | F20: =IF(D20="Plan Safe",1,IF(D20="Compartido",Escenarios!$B$5,0)) -> 0 | G20: =IF(D20="Synertec",1,IF(D20="Compartido",Escenarios!$B$6,0)) -> 0 | H20: =IF(D20="INVAP",1,0) -> 0 | I20: 1 | J20: 1 | K20: 1 | L20: 1
A21: S23 | B21: Radiological Contamination Control Strategy | C21: Contaminación y confinamiento | D21: Compartido | E21: =IF(D21="IDOM",1,IF(D21="Compartido",1-Escenarios!$B$5-Escenarios!$B$6,0)) -> 0.9 | F21: =IF(D21="Plan Safe",1,IF(D21="Compartido",Escenarios!$B$5,0)) -> 0.1 | G21: =IF(D21="Synertec",1,IF(D21="Compartido",Escenarios!$B$6,0)) -> 0 | H21: =IF(D21="INVAP",1,0) -> 0 | I21: 1 | J21: 1 | K21: 1 | L21: 1
A22: S24 | B22: Radiological Classification of Areas (RCA) | C22: Zonificación y dosis | D22: IDOM | E22: =IF(D22="IDOM",1,IF(D22="Compartido",1-Escenarios!$B$5-Escenarios!$B$6,0)) -> 1 | F22: =IF(D22="Plan Safe",1,IF(D22="Compartido",Escenarios!$B$5,0)) -> 0 | G22: =IF(D22="Synertec",1,IF(D22="Compartido",Escenarios!$B$6,0)) -> 0 | H22: =IF(D22="INVAP",1,0) -> 0 | I22: 1 | J22: 1 | K22: 1 | L22: 1
A23: S25 | B23: Radiation Dose Assessment /Normal) Operations Dose Assessment | C23: Zonificación y dosis | D23: IDOM | E23: =IF(D23="IDOM",1,IF(D23="Compartido",1-Escenarios!$B$5-Escenarios!$B$6,0)) -> 1 | F23: =IF(D23="Plan Safe",1,IF(D23="Compartido",Escenarios!$B$5,0)) -> 0 | G23: =IF(D23="Synertec",1,IF(D23="Compartido",Escenarios!$B$6,0)) -> 0 | H23: =IF(D23="INVAP",1,0) -> 0 | I23: 1 | J23: 1 | K23: 1 | L23: 1
... A32: Pre | B32: Conceptual Design Verification | C32: Revisión del diseño conceptual | D32: INVAP | E32: =IF(D32="IDOM",1,IF(D32="Compartido",1-Escenarios!$B$5-Escenarios!$B$6,0)) -> 0 | F32: =IF(D32="Plan Safe",1,IF(D32="Compartido",Escenarios!$B$5,0)) -> 0 | G32: =IF(D32="Synertec",1,IF(D32="Compartido",Escenarios!$B$6,0)) -> 0 | H32: =IF(D32="INVAP",1,0) -> 1 | I32: 1 | J32: 1 | K32: 1 | L32: 1
A33: S2 | B33: Human Factors Assurance Plan / Human Factors Integration Plan (HFIP) | C33: Factores humanos | D33: Plan Safe | E33: =IF(D33="IDOM",1,IF(D33="Compartido",1-Escenarios!$B$5-Escenarios!$B$6,0)) -> 0 | F33: =IF(D33="Plan Safe",1,IF(D33="Compartido",Escenarios!$B$5,0)) -> 1 | G33: =IF(D33="Synertec",1,IF(D33="Compartido",Escenarios!$B$6,0)) -> 0 | H33: =IF(D33="INVAP",1,0) -> 0 | I33: 1 | J33: 0 | K33: 0 | L33: =$B$7 -> 0.5
A34: S3 | B34: Human Factors Hazards Identification and Control Plan (HFHICP) | C34: Factores humanos | D34: Plan Safe | E34: =IF(D34="IDOM",1,IF(D34="Compartido",1-Escenarios!$B$5-Escenarios!$B$6,0)) -> 0 | F34: =IF(D34="Plan Safe",1,IF(D34="Compartido",Escenarios!$B$5,0)) -> 1 | G34: =IF(D34="Synertec",1,IF(D34="Compartido",Escenarios!$B$6,0)) -> 0 | H34: =IF(D34="INVAP",1,0) -> 0 | I34: 1 | J34: 0 | K34: 0 | L34: =$B$7 -> 0.5
A35: S8 | B35: Human Factor Task Assessments | C35: Factores humanos | D35: Plan Safe | E35: =IF(D35="IDOM",1,IF(D35="Compartido",1-Escenarios!$B$5-Escenarios!$B$6,0)) -> 0 | F35: =IF(D35="Plan Safe",1,IF(D35="Compartido",Escenarios!$B$5,0)) -> 1 | G35: =IF(D35="Synertec",1,IF(D35="Compartido",Escenarios!$B$6,0)) -> 0 | H35: =IF(D35="INVAP",1,0) -> 0 | I35: 1 | J35: 0 | K35: 0 | L35: =$B$7 -> 0.5
A36: S30 | B36: Human Factors Substantiation/Assurance Report | C36: Factores humanos | D36: Plan Safe | E36: =IF(D36="IDOM",1,IF(D36="Compartido",1-Escenarios!$B$5-Escenarios!$B$6,0)) -> 0 | F36: =IF(D36="Plan Safe",1,IF(D36="Compartido",Escenarios!$B$5,0)) -> 1 | G36: =IF(D36="Synertec",1,IF(D36="Compartido",Escenarios!$B$6,0)) -> 0 | H36: =IF(D36="INVAP",1,0) -> 0 | I36: 1 | J36: 0 | K36: 0 | L36: =$B$7 -> 0.5
A38: Tipo de reparto (de la herramienta): IDOM = 100 % IDOM · Compartido = «IDOM lidera + inputs especialista», se cede a Plan Safe/Synertec la participación indicada arriba · Plan Safe = sus 4 tareas propias (S2, S3, S8, S30) · INVAP = Conceptual Design Verification (Pre).
A39: Escenario 2 excluye las 4 tareas propias de Plan Safe (S2, S3, S8, S30). Escenario 3 excluye además los SSC (S26, S27, S28). Escenario 4 excluye los SSC y aplica a las 4 tareas de Plan Safe el factor de B7.
A40: Al excluir S28, que es compartido, también desaparece la parte de Plan Safe en ese entregable. En el Stage 1–3 solo S26 y S27 tienen horas; S28 empieza en el Stage 4.
A41: Celdas con fondo amarillo claro = factor distinto de 1. El factor del escenario 4 para Plan Safe es una fórmula que apunta a B7.

Sheet Datos
A1: Datos de partida — tarifas y horas por perfil (modelo bottom-up de la oferta)
A2: Fuente: herramienta «NMMP · Alcance nuclear IDOM» (ANSTO.html), escenario «Oferta mayo». Tarifas de venta con descuento en AUD/h, ya con el factor 1,05. Azul = editable.
A4: Perfil | B4: Descripción | C4: Tarifa AUD/h | E4: Código | F4: Stage | G4: Perfil | H4: Horas | I4: Tarifa AUD/h | J4: Importe AUD
A5: P7 | B5: Associate Director 2 | C5: 256.515 | E5: E94 | F5: S2 | G5: P7 | H5: 20 | I5: =INDEX($C$5:$C$26,MATCH(G5,$A$5:$A$26,0)) -> 256.515 | J5: =H5*I5 -> 5130.3
A6: P6 | B6: Principal Professional | C6: 236.67 | E6: E94 | F6: S2 | G6: P6 | H6: 40 | I6: =INDEX($C$5:$C$26,MATCH(G6,$A$5:$A$26,0)) -> 236.67 | J6: =H6*I6 -> 9466.8
A7: P5 | B7: Senior Professional 1 | C7: 224.175 | E7: E94 | F7: S2 | G7: P5 | H7: 40 | I7: =INDEX($C$5:$C$26,MATCH(G7,$A$5:$A$26,0)) -> 224.175 | J7: =H7*I7 -> 8967
A8: P4 | B8: Senior Professional 2 | C8: 206.535 | E8: E94 | F8: S2 | G8: TO3 | H8: 55 | I8: =INDEX($C$5:$C$26,MATCH(G8,$A$5:$A$26,0)) -> 145.53 | J8: =H8*I8 -> 8004.15
A9: TO4 | B9: Senior Technical Officer | C9: 182.28 | E9: E94 | F9: S2 | G9: TO2 | H9: 30 | I9: =INDEX($C$5:$C$26,MATCH(G9,$A$5:$A$26,0)) -> 121.275 | J9: =H9*I9 -> 3638.25
A10: TO3 | B10: Technical Officer 1 | C10: 145.53 | E10: E94 | F10: S3 | G10: P7 | H10: 30 | I10: =INDEX($C$5:$C$26,MATCH(G10,$A$5:$A$26,0)) -> 256.515 | J10: =H10*I10 -> 7695.45
A11: TO2 | B11: Technical Officer 2 | C11: 121.275 | E11: E94 | F11: S3 | G11: P6 | H11: 55 | I11: =INDEX($C$5:$C$26,MATCH(G11,$A$5:$A$26,0)) -> 236.67 | J11: =H11*I11 -> 13016.85
A12: PM3 | B12: Project Director / Project Manager | C12: 360.15 | E12: E94 | F12: S3 | G12: P5 | H12: 75 | I12: =INDEX($C$5:$C$26,MATCH(G12,$A$5:$A$26,0)) -> 224.175 | J12: =H12*I12 -> 16813.125
A13: PM2 | B13: Senior Executive | C13: 349.125 | E13: E94 | F13: S3 | G13: TO3 | H13: 105 | I13: =INDEX($C$5:$C$26,MATCH(G13,$A$5:$A$26,0)) -> 145.53 | J13: =H13*I13 -> 15280.65
A14: PM1 | B14: Discipline Lead / Design Manager | C14: 323.4 | E14: E94 | F14: S3 | G14: TO2 | H14: 50 | I14: =INDEX($C$5:$C$26,MATCH(G14,$A$5:$A$26,0)) -> 121.275 | J14: =H14*I14 -> 6063.75
A15: P10 | B15: Industry / International Specialist | C15: 360.15 | E15: E94 | F15: S4 | G15: P7 | H15: 35 | I15: =INDEX($C$5:$C$26,MATCH(G15,$A$5:$A$26,0)) -> 256.515 | J15: =H15*I15 -> 8978.025
A16: P9 | B16: Technical Director | C16: 293.265 | E16: E94 | F16: S4 | G16: P6 | H16: 80 | I16: =INDEX($C$5:$C$26,MATCH(G16,$A$5:$A$26,0)) -> 236.67 | J16: =H16*I16 -> 18933.6
... A26: A1 | B26: Admin Assistant | C26: 66.885 | E26: S1 | F26: S2 | G26: P5 | H26: 295 | I26: =INDEX($C$5:$C$26,MATCH(G26,$A$5:$A$26,0)) -> 224.175 | J26: =H26*I26 -> 66131.625
E27: S1 | F27: S2 | G27: P4 | H27: 130 | I27: =INDEX($C$5:$C$26,MATCH(G27,$A$5:$A$26,0)) -> 206.535 | J27: =H27*I27 -> 26849.55
E28: S9 | F28: S3 | G28: P7 | H28: 275 | I28: =INDEX($C$5:$C$26,MATCH(G28,$A$5:$A$26,0)) -> 256.515 | J28: =H28*I28 -> 70541.625
E29: S9 | F29: S3 | G29: P6 | H29: 505 | I29: =INDEX($C$5:$C$26,MATCH(G29,$A$5:$A$26,0)) -> 236.67 | J29: =H29*I29 -> 119518.35
E30: S9 | F30: S3 | G30: P5 | H30: 475 | I30: =INDEX($C$5:$C$26,MATCH(G30,$A$5:$A$26,0)) -> 224.175 | J30: =H30*I30 -> 106483.12
E31: S9 | F31: S3 | G31: P4 | H31: 130 | I31: =INDEX($C$5:$C$26,MATCH(G31,$A$5:$A$26,0)) -> 206.535 | J31: =H31*I31 -> 26849.55
E32: S9 | F32: S4 | G32: P7 | H32: 210 | I32: =INDEX($C$5:$C$26,MATCH(G32,$A$5:$A$26,0)) -> 256.515 | J32: =H32*I32 -> 53868.15
E33: S9 | F33: S4 | G33: P6 | H33: 370 | I33: =INDEX($C$5:$C$26,MATCH(G33,$A$5:$A$26,0)) -> 236.67 | J33: =H33*I33 -> 87567.9
E34: S9 | F34: S4 | G34: P5 | H34: 360 | I34: =INDEX($C$5:$C$26,MATCH(G34,$A$5:$A$26,0)) -> 224.175 | J34: =H34*I34 -> 80703
E35: S9 | F35: S4 | G35: P4 | H35: 75 | I35: =INDEX($C$5:$C$26,MATCH(G35,$A$5:$A$26,0)) -> 206.535 | J35: =H35*I35 -> 15490.125
E36: S9 | F36: S6 | G36: P7 | H36: 130 | I36: =INDEX($C$5:$C$26,MATCH(G36,$A$5:$A$26,0)) -> 256.515 | J36: =H36*I36 -> 33346.95
E37: S9 | F37: S6 | G37: P6 | H37: 120 | I37: =INDEX($C$5:$C$26,MATCH(G37,$A$5:$A$26,0)) -> 236.67 | J37: =H37*I37 -> 28400.4
E38: S9 | F38: S6 | G38: P5 | H38: 105 | I38: =INDEX($C$5:$C$26,MATCH(G38,$A$5:$A$26,0)) -> 224.175 | J38: =H38*I38 -> 23538.375
... E291: S30 | F291: S7 | G291: P4 | H291: 40 | I291: =INDEX($C$5:$C$26,MATCH(G291,$A$5:$A$26,0)) -> 206.535 | J291: =H291*I291 -> 8261.4
