Workbook

Sheet Executive Summary
B1: NMMP — Nuclear and Radiological Scope (PSC002818)
B2: Executive summary of price reduction options
B3: ="Basis for every scenario: Stage 2 rework allowance released ("&TEXT(Assumptions!$C$6,"0%")&" instead of "&TEXT(Assumptions!$C$5,"0%")&", all deliverables assumed right first time) and a "&TEXT(Assumptions!$C$7,"0.0%")&" commercial discount on IDOM's scope. Figures in A$, excluding GST." -> Basis for every scenario: Stage 2 rework allowance released (0% instead of 35%, all deliverables assumed right first time) and a 4.0% commercial discount on IDOM's scope. Figures in A$, excluding GST.
B5: 1 · Offer price by scenario
B6: Scenario | C6: Total offer price | D6: Reduction A$ | E6: Reduction % | F6: Lump sum S1–S3 | G6: Stages 1–5 | H6: Provisional S4–S7 | I6: Synertec benchmark | J6: Deviation vs benchmark A$ | K6: Deviation vs benchmark %
B7: Original offer (as submitted) | C7: ='Scenario Detail'!G6 -> 7530724 | D7: =$C$7-C7 -> 0 | E7: =IF($C$7=0,0,D7/$C$7) -> 0 | F7: ='Scenario Detail'!G16 -> 2537245.7 | G7: ='Scenario Detail'!G46 -> 6261739.2 | H7: ='Scenario Detail'!G26+'Scenario Detail'!G36 -> 4993478.3 | I7: ='Scenario Detail'!J6 -> 3809000 | J7: =C7-I7 -> 3721724 | K7: =IF(C7=0,0,(I7-C7)/C7) -> -0.49420534
B8: Scenario 1 · Base offer | C8: ='Scenario Detail'!G7 -> 7162862.6 | D8: =$C$7-C8 -> 367861.36 | E8: =IF($C$7=0,0,D8/$C$7) -> 0.048848074 | F8: ='Scenario Detail'!G17 -> 2328401.4 | G8: ='Scenario Detail'!G47 -> 5933727 | H8: ='Scenario Detail'!G27+'Scenario Detail'!G37 -> 4834461.2 | I8: ='Scenario Detail'!J7 -> 3809000 | J8: =C8-I8 -> 3353862.6 | K8: =IF(C8=0,0,(I8-C8)/C8) -> -0.46822937
B9: Scenario 2 · Without Plan Safe HF tasks | C9: ='Scenario Detail'!G8 -> 5941147.1 | D9: =$C$7-C9 -> 1589576.9 | E9: =IF($C$7=0,0,D9/$C$7) -> 0.21107889 | F9: ='Scenario Detail'!G18 -> 1871661.4 | G9: ='Scenario Detail'!G48 -> 4915349.2 | H9: ='Scenario Detail'!G28+'Scenario Detail'!G38 -> 4069485.7 | I9: ='Scenario Detail'!J8 -> 3809000 | J9: =C9-I9 -> 2132147.1 | K9: =IF(C9=0,0,(I9-C9)/C9) -> -0.35887802
B10: Scenario 3 · Without Plan Safe HF tasks and SSC | C10: ='Scenario Detail'!G9 -> 4376618.9 | D10: =$C$7-C10 -> 3154105.1 | E10: =IF($C$7=0,0,D10/$C$7) -> 0.41883159 | F10: ='Scenario Detail'!G19 -> 1533068.1 | G10: ='Scenario Detail'!G49 -> 3737301.9 | H10: ='Scenario Detail'!G29+'Scenario Detail'!G39 -> 2843550.9 | I10: ='Scenario Detail'!J9 -> 3809000 | J10: =C10-I10 -> 567618.92 | K10: =IF(C10=0,0,(I10-C10)/C10) -> -0.12969348
B11: Scenario 4 · Without SSC, Plan Safe HF tasks at reduced price | C11: ='Scenario Detail'!G10 -> 4987476.7 | D11: =$C$7-C11 -> 2543247.3 | E11: =IF($C$7=0,0,D11/$C$7) -> 0.33771618 | F11: ='Scenario Detail'!G20 -> 1761438.1 | G11: ='Scenario Detail'!G50 -> 4246490.8 | H11: ='Scenario Detail'!G30+'Scenario Detail'!G40 -> 3226038.6 | I11: ='Scenario Detail'!J10 -> 3809000 | J11: =C11-I11 -> 1178476.7 | K11: =IF(C11=0,0,(I11-C11)/C11) -> -0.23628716
B12: Scenario 5 · Plan Safe as offered, without SSC | C12: ='Scenario Detail'!G11 -> 5598334.5 | D12: =$C$7-C12 -> 1932389.6 | E12: =IF($C$7=0,0,D12/$C$7) -> 0.25660077 | F12: ='Scenario Detail'!G21 -> 1989808.1 | G12: ='Scenario Detail'!G51 -> 4755679.7 | H12: ='Scenario Detail'!G31+'Scenario Detail'!G41 -> 3608526.4 | I12: ='Scenario Detail'!J11 -> 3809000 | J12: =C12-I12 -> 1789334.5 | K12: =IF(C12=0,0,(I12-C12)/C12) -> -0.31961907
B15: 2 · Who receives what (total offer, A$)
B16: Scenario | C16: IDOM | D16: Plan Safe | E16: INVAP | F16: Total | G16: IDOM share | H16: Hours
B17: =B7 -> Original offer (as submitted) | C17: ='Scenario Detail'!D6 -> 5858217.9 | D17: ='Scenario Detail'!E6 -> 1593670 | E17: ='Scenario Detail'!F6 -> 78836.1 | F17: =SUM(C17:E17) -> 7530724 | G17: =IF(F17=0,0,C17/F17) -> 0.77790899 | H17: ='Scenario Detail'!C6 -> 32722
B18: =B8 -> Scenario 1 · Base offer | C18: ='Scenario Detail'!D7 -> 5490356.5 | D18: ='Scenario Detail'!E7 -> 1593670 | E18: ='Scenario Detail'!F7 -> 78836.1 | F18: =SUM(C18:E18) -> 7162862.6 | G18: =IF(F18=0,0,C18/F18) -> 0.76650312 | H18: ='Scenario Detail'!C7 -> 32722
B19: =B9 -> Scenario 2 · Without Plan Safe HF tasks | C19: ='Scenario Detail'!D8 -> 5490356.5 | D19: ='Scenario Detail'!E8 -> 371954.47 | E19: ='Scenario Detail'!F8 -> 78836.1 | F19: =SUM(C19:E19) -> 5941147.1 | G19: =IF(F19=0,0,C19/F19) -> 0.92412399 | H19: ='Scenario Detail'!C8 -> 27415
B20: =B10 -> Scenario 3 · Without Plan Safe HF tasks and SSC | C20: ='Scenario Detail'!D9 -> 4003833.2 | D20: ='Scenario Detail'!E9 -> 293949.65 | E20: ='Scenario Detail'!F9 -> 78836.1 | F20: =SUM(C20:E20) -> 4376618.9 | G20: =IF(F20=0,0,C20/F20) -> 0.91482335 | H20: ='Scenario Detail'!C9 -> 20220
B21: =B11 -> Scenario 4 · Without SSC, Plan Safe HF tasks at reduced price | C21: ='Scenario Detail'!D10 -> 4003833.2 | D21: ='Scenario Detail'!E10 -> 904807.42 | E21: ='Scenario Detail'!F10 -> 78836.1 | F21: =SUM(C21:E21) -> 4987476.7 | G21: =IF(F21=0,0,C21/F21) -> 0.80277732 | H21: ='Scenario Detail'!C10 -> 25527
B22: =B12 -> Scenario 5 · Plan Safe as offered, without SSC | C22: ='Scenario Detail'!D11 -> 4003833.2 | D22: ='Scenario Detail'!E11 -> 1515665.2 | E22: ='Scenario Detail'!F11 -> 78836.1 | F22: =SUM(C22:E22) -> 5598334.5 | G22: =IF(F22=0,0,C22/F22) -> 0.71518292 | H22: ='Scenario Detail'!C11 -> 25527
B25: 3 · Key messages
B26: • | C26: ="Commercial measures alone (rework release and "&TEXT(Assumptions!$C$7,"0.0%")&" discount) bring the offer from A$"&TEXT(C7,"#,##0")&" to A$"&TEXT(C8,"#,##0")&", a reduction of "&TEXT(E8,"0.0%")&", without changing the scope." -> Commercial measures alone (rework release and 4.0% discount) bring the offer from A$7,530,724 to A$7,162,863, a reduction of 4.9%, without changing the scope.
B27: • | C27: ="Releasing the Stage 2 rework allowance is worth A$"&TEXT('Reduction Levers'!D6,"#,##0")&" and the commercial discount A$"&TEXT('Reduction Levers'!D7,"#,##0")&" in the base offer; both assume the design proceeds right first time on a stable basis of design." -> Releasing the Stage 2 rework allowance is worth A$139,097 and the commercial discount A$228,765 in the base offer; both assume the design proceeds right first time on a stable basis of design.
B28: • | C28: ="The largest further reductions require scope changes to be agreed with ANSTO: removing the SSC group (S26–S29) saves up to A$"&TEXT(MAX('Reduction Levers'!D9:H9),"#,##0")&" and removing Plan Safe's HF deliverables up to A$"&TEXT(MAX('Reduction Levers'!D8:H8),"#,##0")&"." -> The largest further reductions require scope changes to be agreed with ANSTO: removing the SSC group (S26–S29) saves up to A$1,652,324 and removing Plan Safe's HF deliverables up to A$1,221,716.
B29: • | C29: ="Against the Synertec benchmark of A$"&TEXT(I7,"#,##0")&", the gap falls from "&TEXT(K7,"0.0%")&" in the original offer to between "&TEXT(MAX(K8:K12),"0.0%")&" and "&TEXT(MIN(K8:K12),"0.0%")&" across the scenarios; the lump sum S1–S3 is the block closest to the benchmark (see Synertec Benchmark tab)." -> Against the Synertec benchmark of A$3,809,000, the gap falls from -49.4% in the original offer to between -13.0% and -46.8% across the scenarios; the lump sum S1–S3 is the block closest to the benchmark (see Synertec Benchmark tab).
B30: • | C30: =IF(Assumptions!$C$10="Yes","Deliverable S1 is priced as a two-week single issue (A$"&TEXT(Assumptions!$C$12,"#,##0")&"); see the justification and its limits in the Reduction Levers tab.","Pricing deliverable S1 as a two-week single issue (A$"&TEXT(Assumptions!$C$12,"#,##0")&") is available as an optional lever worth about A$"&TEXT(SUM(Calculation!M6:S6)-Assumptions!$C$12,"#,##0")&"; it is not included in these figures.") -> Pricing deliverable S1 as a two-week single issue (A$38,675) is available as an optional lever worth about A$393,744; it is not included in these figures.
B32: Tabs: Reduction Levers (value and justification of each lever) · Scenario Detail (by price block and company) · Synertec Benchmark (by stage) · Assumptions (inputs) · Calculation and Data (engine and source).

Sheet Reduction Levers
B1: Reduction levers and justification
B2: Reduction in A$ against the original offer, by lever and scenario. Positive = price reduction. Levers are applied in this order: scope (scenario), deliverable S1 option, Stage 2 rework release, commercial discount.
B4: A · Total offer (Stages 1–7)
B5: Lever | C5: Type | D5: Sc. 1 Base offer | E5: Sc. 2 Without Plan Safe HF tasks | F5: Sc. 3 Without Plan Safe HF tasks and SSC | G5: Sc. 4 Without SSC, Plan Safe HF tasks at reduced price | H5: Sc. 5 Plan Safe as offered, without SSC
B6: Stage 2 rework allowance released | C6: Commercial (all) | D6: =-SUM(Calculation!M56:S56) -> 139096.5 | E6: =-SUM(Calculation!M73:S73) -> 139096.5 | F6: =-SUM(Calculation!M90:S90) -> 113239.07 | G6: =-SUM(Calculation!M107:S107) -> 113239.07 | H6: =-SUM(Calculation!M124:S124) -> 113239.07
B7: Commercial discount on IDOM's scope | C7: Commercial (all) | D7: =-SUM(Calculation!M57:S57) -> 228764.86 | E7: =-SUM(Calculation!M74:S74) -> 228764.86 | F7: =-SUM(Calculation!M91:S91) -> 166826.38 | G7: =-SUM(Calculation!M108:S108) -> 166826.38 | H7: =-SUM(Calculation!M125:S125) -> 166826.38
B8: Plan Safe human factors deliverables | C8: Scope | D8: =SUMPRODUCT((Calculation!$D$5:$D$29="Plan Safe task")*Calculation!$AE$5:$AE$29*(1-Calculation!$H$5:$H$29)) -> 0 | E8: =SUMPRODUCT((Calculation!$D$5:$D$29="Plan Safe task")*Calculation!$AE$5:$AE$29*(1-Calculation!$I$5:$I$29)) -> 1221715.5 | F8: =SUMPRODUCT((Calculation!$D$5:$D$29="Plan Safe task")*Calculation!$AE$5:$AE$29*(1-Calculation!$J$5:$J$29)) -> 1221715.5 | G8: =SUMPRODUCT((Calculation!$D$5:$D$29="Plan Safe task")*Calculation!$AE$5:$AE$29*(1-Calculation!$K$5:$K$29)) -> 610857.77 | H8: =SUMPRODUCT((Calculation!$D$5:$D$29="Plan Safe task")*Calculation!$AE$5:$AE$29*(1-Calculation!$L$5:$L$29)) -> 0
B9: SSC group (S26, S27, S28, S29) | C9: Scope | D9: =SUMPRODUCT((Calculation!$D$5:$D$29="SSC")*Calculation!$AE$5:$AE$29*(1-Calculation!$H$5:$H$29)) -> 0 | E9: =SUMPRODUCT((Calculation!$D$5:$D$29="SSC")*Calculation!$AE$5:$AE$29*(1-Calculation!$I$5:$I$29)) -> 0 | F9: =SUMPRODUCT((Calculation!$D$5:$D$29="SSC")*Calculation!$AE$5:$AE$29*(1-Calculation!$J$5:$J$29)) -> 1652324.1 | G9: =SUMPRODUCT((Calculation!$D$5:$D$29="SSC")*Calculation!$AE$5:$AE$29*(1-Calculation!$K$5:$K$29)) -> 1652324.1 | H9: =SUMPRODUCT((Calculation!$D$5:$D$29="SSC")*Calculation!$AE$5:$AE$29*(1-Calculation!$L$5:$L$29)) -> 1652324.1
B10: INVAP conceptual design verification | C10: Optional | D10: =SUMPRODUCT((Calculation!$D$5:$D$29="INVAP")*Calculation!$AE$5:$AE$29*(1-Calculation!$H$5:$H$29)) -> 0 | E10: =SUMPRODUCT((Calculation!$D$5:$D$29="INVAP")*Calculation!$AE$5:$AE$29*(1-Calculation!$I$5:$I$29)) -> 0 | F10: =SUMPRODUCT((Calculation!$D$5:$D$29="INVAP")*Calculation!$AE$5:$AE$29*(1-Calculation!$J$5:$J$29)) -> 0 | G10: =SUMPRODUCT((Calculation!$D$5:$D$29="INVAP")*Calculation!$AE$5:$AE$29*(1-Calculation!$K$5:$K$29)) -> 0 | H10: =SUMPRODUCT((Calculation!$D$5:$D$29="INVAP")*Calculation!$AE$5:$AE$29*(1-Calculation!$L$5:$L$29)) -> 0
B11: Deliverable S1 as a two-week single issue | C11: Optional | D11: =-(SUM(Calculation!M54:S54)+SUM(Calculation!M55:S55)) -> 0 | E11: =-(SUM(Calculation!M71:S71)+SUM(Calculation!M72:S72)) -> 0 | F11: =-(SUM(Calculation!M88:S88)+SUM(Calculation!M89:S89)) -> 0 | G11: =-(SUM(Calculation!M105:S105)+SUM(Calculation!M106:S106)) -> 0 | H11: =-(SUM(Calculation!M122:S122)+SUM(Calculation!M123:S123)) -> 0
B12: Total reduction | D12: =SUM(D6:D11) -> 367861.36 | E12: =SUM(E6:E11) -> 1589576.9 | F12: =SUM(F6:F11) -> 3154105.1 | G12: =SUM(G6:G11) -> 2543247.3 | H12: =SUM(H6:H11) -> 1932389.6
B13: Original offer price | D13: =SUM(Calculation!M44:S44) -> 7530724 | E13: =SUM(Calculation!M44:S44) -> 7530724 | F13: =SUM(Calculation!M44:S44) -> 7530724 | G13: =SUM(Calculation!M44:S44) -> 7530724 | H13: =SUM(Calculation!M44:S44) -> 7530724
B14: Resulting price | D14: =SUM(Calculation!M61:S61) -> 7162862.6 | E14: =SUM(Calculation!M78:S78) -> 5941147.1 | F14: =SUM(Calculation!M95:S95) -> 4376618.9 | G14: =SUM(Calculation!M112:S112) -> 4987476.7 | H14: =SUM(Calculation!M129:S129) -> 5598334.5
B15: % reduction | D15: =IF(D13=0,0,D12/D13) -> 0.048848074 | E15: =IF(E13=0,0,E12/E13) -> 0.21107889 | F15: =IF(F13=0,0,F12/F13) -> 0.41883159 | G15: =IF(G13=0,0,G12/G13) -> 0.33771618 | H15: =IF(H13=0,0,H12/H13) -> 0.25660077
B16: Check: original − resulting − total reduction | D16: =ROUND(D13-D14-D12,0) -> 0 | E16: =ROUND(E13-E14-E12,0) -> 0 | F16: =ROUND(F13-F14-F12,0) -> 0 | G16: =ROUND(G13-G14-G12,0) -> 0 | H16: =ROUND(H13-H14-H12,0) -> 0
B19: B · Lump sum (Stages 1–3)
B20: Lever | C20: Type | D20: Sc. 1 Base offer | E20: Sc. 2 Without Plan Safe HF tasks | F20: Sc. 3 Without Plan Safe HF tasks and SSC | G20: Sc. 4 Without SSC, Plan Safe HF tasks at reduced price | H20: Sc. 5 Plan Safe as offered, without SSC
B21: Stage 2 rework allowance released | C21: Commercial (all) | D21: =-SUM(Calculation!M56:O56) -> 139096.5 | E21: =-SUM(Calculation!M73:O73) -> 139096.5 | F21: =-SUM(Calculation!M90:O90) -> 113239.07 | G21: =-SUM(Calculation!M107:O107) -> 113239.07 | H21: =-SUM(Calculation!M124:O124) -> 113239.07
B22: Commercial discount on IDOM's scope | C22: Commercial (all) | D22: =-SUM(Calculation!M57:O57) -> 69747.783 | E22: =-SUM(Calculation!M74:O74) -> 69747.783 | F22: =-SUM(Calculation!M91:O91) -> 55974.917 | G22: =-SUM(Calculation!M108:O108) -> 55974.917 | H22: =-SUM(Calculation!M125:O125) -> 55974.917
B23: Plan Safe human factors deliverables | C23: Scope | D23: =SUMPRODUCT((Calculation!$D$5:$D$29="Plan Safe task")*Calculation!$AA$5:$AA$29*(1-Calculation!$H$5:$H$29)) -> 0 | E23: =SUMPRODUCT((Calculation!$D$5:$D$29="Plan Safe task")*Calculation!$AA$5:$AA$29*(1-Calculation!$I$5:$I$29)) -> 456740.03 | F23: =SUMPRODUCT((Calculation!$D$5:$D$29="Plan Safe task")*Calculation!$AA$5:$AA$29*(1-Calculation!$J$5:$J$29)) -> 456740.03 | G23: =SUMPRODUCT((Calculation!$D$5:$D$29="Plan Safe task")*Calculation!$AA$5:$AA$29*(1-Calculation!$K$5:$K$29)) -> 228370.01 | H23: =SUMPRODUCT((Calculation!$D$5:$D$29="Plan Safe task")*Calculation!$AA$5:$AA$29*(1-Calculation!$L$5:$L$29)) -> 0
B24: SSC group (S26, S27, S28, S29) | C24: Scope | D24: =SUMPRODUCT((Calculation!$D$5:$D$29="SSC")*Calculation!$AA$5:$AA$29*(1-Calculation!$H$5:$H$29)) -> 0 | E24: =SUMPRODUCT((Calculation!$D$5:$D$29="SSC")*Calculation!$AA$5:$AA$29*(1-Calculation!$I$5:$I$29)) -> 0 | F24: =SUMPRODUCT((Calculation!$D$5:$D$29="SSC")*Calculation!$AA$5:$AA$29*(1-Calculation!$J$5:$J$29)) -> 378223.65 | G24: =SUMPRODUCT((Calculation!$D$5:$D$29="SSC")*Calculation!$AA$5:$AA$29*(1-Calculation!$K$5:$K$29)) -> 378223.65 | H24: =SUMPRODUCT((Calculation!$D$5:$D$29="SSC")*Calculation!$AA$5:$AA$29*(1-Calculation!$L$5:$L$29)) -> 378223.65
B25: INVAP conceptual design verification | C25: Optional | D25: =SUMPRODUCT((Calculation!$D$5:$D$29="INVAP")*Calculation!$AA$5:$AA$29*(1-Calculation!$H$5:$H$29)) -> 0 | E25: =SUMPRODUCT((Calculation!$D$5:$D$29="INVAP")*Calculation!$AA$5:$AA$29*(1-Calculation!$I$5:$I$29)) -> 0 | F25: =SUMPRODUCT((Calculation!$D$5:$D$29="INVAP")*Calculation!$AA$5:$AA$29*(1-Calculation!$J$5:$J$29)) -> 0 | G25: =SUMPRODUCT((Calculation!$D$5:$D$29="INVAP")*Calculation!$AA$5:$AA$29*(1-Calculation!$K$5:$K$29)) -> 0 | H25: =SUMPRODUCT((Calculation!$D$5:$D$29="INVAP")*Calculation!$AA$5:$AA$29*(1-Calculation!$L$5:$L$29)) -> 0
B26: Deliverable S1 as a two-week single issue | C26: Optional | D26: =-(SUM(Calculation!M54:O54)+SUM(Calculation!M55:O55)) -> 0 | E26: =-(SUM(Calculation!M71:O71)+SUM(Calculation!M72:O72)) -> 0 | F26: =-(SUM(Calculation!M88:O88)+SUM(Calculation!M89:O89)) -> 0 | G26: =-(SUM(Calculation!M105:O105)+SUM(Calculation!M106:O106)) -> 0 | H26: =-(SUM(Calculation!M122:O122)+SUM(Calculation!M123:O123)) -> 0
B27: Total reduction | D27: =SUM(D21:D26) -> 208844.29 | E27: =SUM(E21:E26) -> 665584.31 | F27: =SUM(F21:F26) -> 1004177.7 | G27: =SUM(G21:G26) -> 775807.65 | H27: =SUM(H21:H26) -> 547437.64
B28: Original offer price | D28: =SUM(Calculation!M44:O44) -> 2537245.7 | E28: =SUM(Calculation!M44:O44) -> 2537245.7 | F28: =SUM(Calculation!M44:O44) -> 2537245.7 | G28: =SUM(Calculation!M44:O44) -> 2537245.7 | H28: =SUM(Calculation!M44:O44) -> 2537245.7
B29: Resulting price | D29: =SUM(Calculation!M61:O61) -> 2328401.4 | E29: =SUM(Calculation!M78:O78) -> 1871661.4 | F29: =SUM(Calculation!M95:O95) -> 1533068.1 | G29: =SUM(Calculation!M112:O112) -> 1761438.1 | H29: =SUM(Calculation!M129:O129) -> 1989808.1
B30: % reduction | D30: =IF(D28=0,0,D27/D28) -> 0.082311415 | E30: =IF(E28=0,0,E27/E28) -> 0.26232552 | F30: =IF(F28=0,0,F27/F28) -> 0.3957747 | G30: =IF(G28=0,0,G27/G28) -> 0.30576764 | H30: =IF(H28=0,0,H27/H28) -> 0.21576059
B31: Check: original − resulting − total reduction | D31: =ROUND(D28-D29-D27,0) -> 0 | E31: =ROUND(E28-E29-E27,0) -> 0 | F31: =ROUND(F28-F29-F27,0) -> 0 | G31: =ROUND(G28-G29-G27,0) -> 0 | H31: =ROUND(H28-H29-H27,0) -> 0
B34: C · Stages 1–5 (design to IFC)
B35: Lever | C35: Type | D35: Sc. 1 Base offer | E35: Sc. 2 Without Plan Safe HF tasks | F35: Sc. 3 Without Plan Safe HF tasks and SSC | G35: Sc. 4 Without SSC, Plan Safe HF tasks at reduced price | H35: Sc. 5 Plan Safe as offered, without SSC
B36: Stage 2 rework allowance released | C36: Commercial (all) | D36: =-SUM(Calculation!M56:Q56) -> 139096.5 | E36: =-SUM(Calculation!M73:Q73) -> 139096.5 | F36: =-SUM(Calculation!M90:Q90) -> 113239.07 | G36: =-SUM(Calculation!M107:Q107) -> 113239.07 | H36: =-SUM(Calculation!M124:Q124) -> 113239.07
B37: Commercial discount on IDOM's scope | C37: Commercial (all) | D37: =-SUM(Calculation!M57:Q57) -> 188915.63 | E37: =-SUM(Calculation!M74:Q74) -> 188915.63 | F37: =-SUM(Calculation!M91:Q91) -> 142162.77 | G37: =-SUM(Calculation!M108:Q108) -> 142162.77 | H37: =-SUM(Calculation!M125:Q125) -> 142162.77
B38: Plan Safe human factors deliverables | C38: Scope | D38: =SUMPRODUCT((Calculation!$D$5:$D$29="Plan Safe task")*Calculation!$AD$5:$AD$29*(1-Calculation!$H$5:$H$29)) -> 0 | E38: =SUMPRODUCT((Calculation!$D$5:$D$29="Plan Safe task")*Calculation!$AD$5:$AD$29*(1-Calculation!$I$5:$I$29)) -> 1018377.8 | F38: =SUMPRODUCT((Calculation!$D$5:$D$29="Plan Safe task")*Calculation!$AD$5:$AD$29*(1-Calculation!$J$5:$J$29)) -> 1018377.8 | G38: =SUMPRODUCT((Calculation!$D$5:$D$29="Plan Safe task")*Calculation!$AD$5:$AD$29*(1-Calculation!$K$5:$K$29)) -> 509188.89 | H38: =SUMPRODUCT((Calculation!$D$5:$D$29="Plan Safe task")*Calculation!$AD$5:$AD$29*(1-Calculation!$L$5:$L$29)) -> 0
B39: SSC group (S26, S27, S28, S29) | C39: Scope | D39: =SUMPRODUCT((Calculation!$D$5:$D$29="SSC")*Calculation!$AD$5:$AD$29*(1-Calculation!$H$5:$H$29)) -> 0 | E39: =SUMPRODUCT((Calculation!$D$5:$D$29="SSC")*Calculation!$AD$5:$AD$29*(1-Calculation!$I$5:$I$29)) -> 0 | F39: =SUMPRODUCT((Calculation!$D$5:$D$29="SSC")*Calculation!$AD$5:$AD$29*(1-Calculation!$J$5:$J$29)) -> 1250657.6 | G39: =SUMPRODUCT((Calculation!$D$5:$D$29="SSC")*Calculation!$AD$5:$AD$29*(1-Calculation!$K$5:$K$29)) -> 1250657.6 | H39: =SUMPRODUCT((Calculation!$D$5:$D$29="SSC")*Calculation!$AD$5:$AD$29*(1-Calculation!$L$5:$L$29)) -> 1250657.6
B40: INVAP conceptual design verification | C40: Optional | D40: =SUMPRODUCT((Calculation!$D$5:$D$29="INVAP")*Calculation!$AD$5:$AD$29*(1-Calculation!$H$5:$H$29)) -> 0 | E40: =SUMPRODUCT((Calculation!$D$5:$D$29="INVAP")*Calculation!$AD$5:$AD$29*(1-Calculation!$I$5:$I$29)) -> 0 | F40: =SUMPRODUCT((Calculation!$D$5:$D$29="INVAP")*Calculation!$AD$5:$AD$29*(1-Calculation!$J$5:$J$29)) -> 0 | G40: =SUMPRODUCT((Calculation!$D$5:$D$29="INVAP")*Calculation!$AD$5:$AD$29*(1-Calculation!$K$5:$K$29)) -> 0 | H40: =SUMPRODUCT((Calculation!$D$5:$D$29="INVAP")*Calculation!$AD$5:$AD$29*(1-Calculation!$L$5:$L$29)) -> 0
B41: Deliverable S1 as a two-week single issue | C41: Optional | D41: =-(SUM(Calculation!M54:Q54)+SUM(Calculation!M55:Q55)) -> 0 | E41: =-(SUM(Calculation!M71:Q71)+SUM(Calculation!M72:Q72)) -> 0 | F41: =-(SUM(Calculation!M88:Q88)+SUM(Calculation!M89:Q89)) -> 0 | G41: =-(SUM(Calculation!M105:Q105)+SUM(Calculation!M106:Q106)) -> 0 | H41: =-(SUM(Calculation!M122:Q122)+SUM(Calculation!M123:Q123)) -> 0
B42: Total reduction | D42: =SUM(D36:D41) -> 328012.13 | E42: =SUM(E36:E41) -> 1346389.9 | F42: =SUM(F36:F41) -> 2524437.2 | G42: =SUM(G36:G41) -> 2015248.3 | H42: =SUM(H36:H41) -> 1506059.5
B43: Original offer price | D43: =SUM(Calculation!M44:Q44) -> 6261739.2 | E43: =SUM(Calculation!M44:Q44) -> 6261739.2 | F43: =SUM(Calculation!M44:Q44) -> 6261739.2 | G43: =SUM(Calculation!M44:Q44) -> 6261739.2 | H43: =SUM(Calculation!M44:Q44) -> 6261739.2
B44: Resulting price | D44: =SUM(Calculation!M61:Q61) -> 5933727 | E44: =SUM(Calculation!M78:Q78) -> 4915349.2 | F44: =SUM(Calculation!M95:Q95) -> 3737301.9 | G44: =SUM(Calculation!M112:Q112) -> 4246490.8 | H44: =SUM(Calculation!M129:Q129) -> 4755679.7
B45: % reduction | D45: =IF(D43=0,0,D42/D43) -> 0.052383551 | E45: =IF(E43=0,0,E42/E43) -> 0.21501852 | F45: =IF(F43=0,0,F42/F43) -> 0.40315273 | G45: =IF(G43=0,0,G42/G43) -> 0.32183524 | H45: =IF(H43=0,0,H42/H43) -> 0.24051776
B46: Check: original − resulting − total reduction | D46: =ROUND(D43-D44-D42,0) -> 0 | E46: =ROUND(E43-E44-E42,0) -> 0 | F46: =ROUND(F43-F44-F42,0) -> 0 | G46: =ROUND(G43-G44-G42,0) -> 0 | H46: =ROUND(H43-H44-H42,0) -> 0
B49: D · Justification of each lever
B50: Lever | C50: Justification
B51: Stage 2 rework allowance released | C51: Applied in every scenario. The original offer carried a 35% rework allowance on IDOM's Stage 2 tasks. This proposal assumes that all deliverables are right first time: the basis of design is stable, inputs from ANSTO and the other design parties are complete and timely, and comments are resolved within the normal review cycle. The allowance is therefore released in full. Rework caused by changes to client inputs or requirements would be managed as a variation.
B52: Commercial discount on IDOM's scope | C52: Applied in every scenario. A commercial discount on everything IDOM invoices, calculated after the rework release, as a gesture towards ANSTO's budget. It is borne entirely by IDOM and does not change the price of Plan Safe or INVAP.
B53: Plan Safe human factors deliverables | C53: Scenarios 2 and 3 remove Plan Safe's four HF deliverables (S2 HF Assurance / Integration Plan, S3 HF Hazards Identification and Control Plan, S8 HF Task Assessments, S30 HF Substantiation Report); scenario 4 prices them at a reduced factor. Assumption to be confirmed with ANSTO: the HF programme is either delivered by another party or reduced in extent. Plan Safe keeps its share of the shared deliverables, so HF inputs to IDOM's safety documents remain covered.
B54: SSC group (S26, S27, S28, S29) | C54: Scenarios 3, 4 and 5 remove the SSC Categorisation Report (S26), the SSC Register (S27), the Engineering Schedule and V&V Report for safety controls (S28) and the Design Substantiation Report (S29), including Plan Safe's share of S28 and S29. Assumption to be confirmed with ANSTO: these deliverables are produced by another design party or taken back by ANSTO; IDOM would provide inputs only.
B55: INVAP conceptual design verification | C55: Optional lever (Assumptions tab). INVAP's Conceptual Design Verification in Stage 1 would be removed and its review of the reliance information covered by IDOM's own Basis of Design Gap Analysis Report.
B56: Deliverable S1 as a two-week single issue | C56: Optional lever (Assumptions tab). Delivering the Safety Assurance Plan and the Safety Integration Plan as a single, unrevised issue within two weeks of commencement is estimated at 165 hours, or 38,675 AUD (41,769 AUD inclusive of variable costs). The figure is governed by elapsed time rather than by content: ten working days allow approximately 2.2 senior authors to produce a coherent document set, and additional resources would extend the duration rather than shorten it. On this basis both plans can be issued at framework level, establishing the design approach for reconciling operational requirements with ALARP and Safety in Design principles together with the safety principles, organisational structure, processes and lifecycle, which is sufficient to authorise commencement of the design stage. It does not, however, discharge deliverable S1 as defined in Appendix B and Part F.1 Task 2.E C.i, since the risk screening and DSA methodologies, the requirements placed on each design party in respect of the DSAs and the SAR, the hazard log management process, the treatment of Objective Quality Evidence within the Verification and Validation Procedure, and the mapping of the 134 Quality Level 'A' sub-systems against their applicable safety assessments cannot be developed in that period, and no allowance is made for the review and comment-response cycles required by Section 6 of Part F.1. Accordingly, the two-week date should be understood as the first issue of S1, with the remaining content developed during Stage 2; if the issue is to be final and unrevised, that content must be reallocated to a separate deliverable and priced separately, as the Deterministic Safety Assessments, the SSC categorisation and the hazard log all depend on it.
B58: Scope levers marked "assumption to be confirmed" require ANSTO's agreement on who delivers the removed content; they are presented as options, not as a recommendation.

Sheet Scenario Detail
B1: Scenario detail by price block and company (A$)
B2: Every scenario includes the Stage 2 rework release and the commercial discount on IDOM. The reference row is the original offer with no adjustments.
B4: Total offer (Stages 1–7)
B5: Scenario | C5: Hours | D5: IDOM | E5: Plan Safe | F5: INVAP | G5: Total price | H5: Reduction A$ | I5: Reduction % | J5: Synertec benchmark | K5: Deviation A$ | L5: Deviation %
B6: Original offer (reference) | C6: =SUM(Calculation!M47:S47) -> 32722 | D6: =SUM(Calculation!M41:S41) -> 5858217.9 | E6: =SUM(Calculation!M42:S42) -> 1593670 | F6: =SUM(Calculation!M43:S43) -> 78836.1 | G6: =SUM(D6:F6) -> 7530724 | H6: =$G$6-G6 -> 0 | I6: =IF($G$6=0,0,H6/$G$6) -> 0 | J6: =('Synertec Benchmark'!$D$5+'Synertec Benchmark'!$D$6+'Synertec Benchmark'!$D$7+'Synertec Benchmark'!$D$8+'Synertec Benchmark'!$D$9+'Synertec Benchmark'!$D$10+'Synertec Benchmark'!$D$11) -> 3809000 | K6: =G6-J6 -> 3721724 | L6: =IF(G6=0,0,(J6-G6)/G6) -> -0.49420534
B7: Sc. 1 · Base offer | C7: =SUM(Calculation!M64:S64) -> 32722 | D7: =SUM(Calculation!M58:S58) -> 5490356.5 | E7: =SUM(Calculation!M59:S59) -> 1593670 | F7: =SUM(Calculation!M60:S60) -> 78836.1 | G7: =SUM(D7:F7) -> 7162862.6 | H7: =$G$6-G7 -> 367861.36 | I7: =IF($G$6=0,0,H7/$G$6) -> 0.048848074 | J7: =('Synertec Benchmark'!$D$5+'Synertec Benchmark'!$D$6+'Synertec Benchmark'!$D$7+'Synertec Benchmark'!$D$8+'Synertec Benchmark'!$D$9+'Synertec Benchmark'!$D$10+'Synertec Benchmark'!$D$11) -> 3809000 | K7: =G7-J7 -> 3353862.6 | L7: =IF(G7=0,0,(J7-G7)/G7) -> -0.46822937
B8: Sc. 2 · Without Plan Safe HF tasks | C8: =SUM(Calculation!M81:S81) -> 27415 | D8: =SUM(Calculation!M75:S75) -> 5490356.5 | E8: =SUM(Calculation!M76:S76) -> 371954.47 | F8: =SUM(Calculation!M77:S77) -> 78836.1 | G8: =SUM(D8:F8) -> 5941147.1 | H8: =$G$6-G8 -> 1589576.9 | I8: =IF($G$6=0,0,H8/$G$6) -> 0.21107889 | J8: =('Synertec Benchmark'!$D$5+'Synertec Benchmark'!$D$6+'Synertec Benchmark'!$D$7+'Synertec Benchmark'!$D$8+'Synertec Benchmark'!$D$9+'Synertec Benchmark'!$D$10+'Synertec Benchmark'!$D$11) -> 3809000 | K8: =G8-J8 -> 2132147.1 | L8: =IF(G8=0,0,(J8-G8)/G8) -> -0.35887802
B9: Sc. 3 · Without Plan Safe HF tasks and SSC | C9: =SUM(Calculation!M98:S98) -> 20220 | D9: =SUM(Calculation!M92:S92) -> 4003833.2 | E9: =SUM(Calculation!M93:S93) -> 293949.65 | F9: =SUM(Calculation!M94:S94) -> 78836.1 | G9: =SUM(D9:F9) -> 4376618.9 | H9: =$G$6-G9 -> 3154105.1 | I9: =IF($G$6=0,0,H9/$G$6) -> 0.41883159 | J9: =('Synertec Benchmark'!$D$5+'Synertec Benchmark'!$D$6+'Synertec Benchmark'!$D$7+'Synertec Benchmark'!$D$8+'Synertec Benchmark'!$D$9+'Synertec Benchmark'!$D$10+'Synertec Benchmark'!$D$11) -> 3809000 | K9: =G9-J9 -> 567618.92 | L9: =IF(G9=0,0,(J9-G9)/G9) -> -0.12969348
B10: Sc. 4 · Without SSC, Plan Safe HF tasks at reduced price | C10: =SUM(Calculation!M115:S115) -> 25527 | D10: =SUM(Calculation!M109:S109) -> 4003833.2 | E10: =SUM(Calculation!M110:S110) -> 904807.42 | F10: =SUM(Calculation!M111:S111) -> 78836.1 | G10: =SUM(D10:F10) -> 4987476.7 | H10: =$G$6-G10 -> 2543247.3 | I10: =IF($G$6=0,0,H10/$G$6) -> 0.33771618 | J10: =('Synertec Benchmark'!$D$5+'Synertec Benchmark'!$D$6+'Synertec Benchmark'!$D$7+'Synertec Benchmark'!$D$8+'Synertec Benchmark'!$D$9+'Synertec Benchmark'!$D$10+'Synertec Benchmark'!$D$11) -> 3809000 | K10: =G10-J10 -> 1178476.7 | L10: =IF(G10=0,0,(J10-G10)/G10) -> -0.23628716
B11: Sc. 5 · Plan Safe as offered, without SSC | C11: =SUM(Calculation!M132:S132) -> 25527 | D11: =SUM(Calculation!M126:S126) -> 4003833.2 | E11: =SUM(Calculation!M127:S127) -> 1515665.2 | F11: =SUM(Calculation!M128:S128) -> 78836.1 | G11: =SUM(D11:F11) -> 5598334.5 | H11: =$G$6-G11 -> 1932389.6 | I11: =IF($G$6=0,0,H11/$G$6) -> 0.25660077 | J11: =('Synertec Benchmark'!$D$5+'Synertec Benchmark'!$D$6+'Synertec Benchmark'!$D$7+'Synertec Benchmark'!$D$8+'Synertec Benchmark'!$D$9+'Synertec Benchmark'!$D$10+'Synertec Benchmark'!$D$11) -> 3809000 | K11: =G11-J11 -> 1789334.5 | L11: =IF(G11=0,0,(J11-G11)/G11) -> -0.31961907
B14: Lump sum (Stages 1–3)
B15: Scenario | C15: Hours | D15: IDOM | E15: Plan Safe | F15: INVAP | G15: Total price | H15: Reduction A$ | I15: Reduction % | J15: Synertec benchmark | K15: Deviation A$ | L15: Deviation %
B16: Original offer (reference) | C16: =SUM(Calculation!M47:O47) -> 11025 | D16: =SUM(Calculation!M41:O41) -> 1882791.1 | E16: =SUM(Calculation!M42:O42) -> 575618.56 | F16: =SUM(Calculation!M43:O43) -> 78836.1 | G16: =SUM(D16:F16) -> 2537245.7 | H16: =$G$16-G16 -> 0 | I16: =IF($G$16=0,0,H16/$G$16) -> 0 | J16: =('Synertec Benchmark'!$D$5+'Synertec Benchmark'!$D$6+'Synertec Benchmark'!$D$7) -> 1809000 | K16: =G16-J16 -> 728245.72 | L16: =IF(G16=0,0,(J16-G16)/G16) -> -0.28702215
B17: Sc. 1 · Base offer | C17: =SUM(Calculation!M64:O64) -> 11025 | D17: =SUM(Calculation!M58:O58) -> 1673946.8 | E17: =SUM(Calculation!M59:O59) -> 575618.56 | F17: =SUM(Calculation!M60:O60) -> 78836.1 | G17: =SUM(D17:F17) -> 2328401.4 | H17: =$G$16-G17 -> 208844.29 | I17: =IF($G$16=0,0,H17/$G$16) -> 0.082311415 | J17: =('Synertec Benchmark'!$D$5+'Synertec Benchmark'!$D$6+'Synertec Benchmark'!$D$7) -> 1809000 | K17: =G17-J17 -> 519401.44 | L17: =IF(G17=0,0,(J17-G17)/G17) -> -0.22307212
B18: Sc. 2 · Without Plan Safe HF tasks | C18: =SUM(Calculation!M81:O81) -> 9050 | D18: =SUM(Calculation!M75:O75) -> 1673946.8 | E18: =SUM(Calculation!M76:O76) -> 118878.53 | F18: =SUM(Calculation!M77:O77) -> 78836.1 | G18: =SUM(D18:F18) -> 1871661.4 | H18: =$G$16-G18 -> 665584.31 | I18: =IF($G$16=0,0,H18/$G$16) -> 0.26232552 | J18: =('Synertec Benchmark'!$D$5+'Synertec Benchmark'!$D$6+'Synertec Benchmark'!$D$7) -> 1809000 | K18: =G18-J18 -> 62661.413 | L18: =IF(G18=0,0,(J18-G18)/G18) -> -0.033479033
B19: Sc. 3 · Without Plan Safe HF tasks and SSC | C19: =SUM(Calculation!M98:O98) -> 7400 | D19: =SUM(Calculation!M92:O92) -> 1343398 | E19: =SUM(Calculation!M93:O93) -> 110833.96 | F19: =SUM(Calculation!M94:O94) -> 78836.1 | G19: =SUM(D19:F19) -> 1533068.1 | H19: =$G$16-G19 -> 1004177.7 | I19: =IF($G$16=0,0,H19/$G$16) -> 0.3957747 | J19: =('Synertec Benchmark'!$D$5+'Synertec Benchmark'!$D$6+'Synertec Benchmark'!$D$7) -> 1809000 | K19: =G19-J19 -> -275931.94 | L19: =IF(G19=0,0,(J19-G19)/G19) -> 0.17998675
B20: Sc. 4 · Without SSC, Plan Safe HF tasks at reduced price | C20: =SUM(Calculation!M115:O115) -> 9375 | D20: =SUM(Calculation!M109:O109) -> 1343398 | E20: =SUM(Calculation!M110:O110) -> 339203.97 | F20: =SUM(Calculation!M111:O111) -> 78836.1 | G20: =SUM(D20:F20) -> 1761438.1 | H20: =$G$16-G20 -> 775807.65 | I20: =IF($G$16=0,0,H20/$G$16) -> 0.30576764 | J20: =('Synertec Benchmark'!$D$5+'Synertec Benchmark'!$D$6+'Synertec Benchmark'!$D$7) -> 1809000 | K20: =G20-J20 -> -47561.923 | L20: =IF(G20=0,0,(J20-G20)/G20) -> 0.027001757
B21: Sc. 5 · Plan Safe as offered, without SSC | C21: =SUM(Calculation!M132:O132) -> 9375 | D21: =SUM(Calculation!M126:O126) -> 1343398 | E21: =SUM(Calculation!M127:O127) -> 567573.98 | F21: =SUM(Calculation!M128:O128) -> 78836.1 | G21: =SUM(D21:F21) -> 1989808.1 | H21: =$G$16-G21 -> 547437.64 | I21: =IF($G$16=0,0,H21/$G$16) -> 0.21576059 | J21: =('Synertec Benchmark'!$D$5+'Synertec Benchmark'!$D$6+'Synertec Benchmark'!$D$7) -> 1809000 | K21: =G21-J21 -> 180808.09 | L21: =IF(G21=0,0,(J21-G21)/G21) -> -0.0908671
B24: Provisional sum (Stages 4–5)
B25: Scenario | C25: Hours | D25: IDOM | E25: Plan Safe | F25: INVAP | G25: Total price | H25: Reduction A$ | I25: Reduction % | J25: Synertec benchmark | K25: Deviation A$ | L25: Deviation %
B26: Original offer (reference) | C26: =SUM(Calculation!P47:Q47) -> 16197 | D26: =SUM(Calculation!P41:Q41) -> 2979196.1 | E26: =SUM(Calculation!P42:Q42) -> 745297.35 | F26: =SUM(Calculation!P43:Q43) -> 0 | G26: =SUM(D26:F26) -> 3724493.4 | H26: =$G$26-G26 -> 0 | I26: =IF($G$26=0,0,H26/$G$26) -> 0 | J26: =('Synertec Benchmark'!$D$8+'Synertec Benchmark'!$D$9) -> 1825000 | K26: =G26-J26 -> 1899493.4 | L26: =IF(G26=0,0,(J26-G26)/G26) -> -0.51000048
B27: Sc. 1 · Base offer | C27: =SUM(Calculation!P64:Q64) -> 16197 | D27: =SUM(Calculation!P58:Q58) -> 2860028.2 | E27: =SUM(Calculation!P59:Q59) -> 745297.35 | F27: =SUM(Calculation!P60:Q60) -> 0 | G27: =SUM(D27:F27) -> 3605325.6 | H27: =$G$26-G27 -> 119167.84 | I27: =IF($G$26=0,0,H27/$G$26) -> 0.031995718 | J27: =('Synertec Benchmark'!$D$8+'Synertec Benchmark'!$D$9) -> 1825000 | K27: =G27-J27 -> 1780325.6 | L27: =IF(G27=0,0,(J27-G27)/G27) -> -0.49380439
B28: Sc. 2 · Without Plan Safe HF tasks | C28: =SUM(Calculation!P81:Q81) -> 13750 | D28: =SUM(Calculation!P75:Q75) -> 2860028.2 | E28: =SUM(Calculation!P76:Q76) -> 183659.6 | F28: =SUM(Calculation!P77:Q77) -> 0 | G28: =SUM(D28:F28) -> 3043687.8 | H28: =$G$26-G28 -> 680805.6 | I28: =IF($G$26=0,0,H28/$G$26) -> 0.18279146 | J28: =('Synertec Benchmark'!$D$8+'Synertec Benchmark'!$D$9) -> 1825000 | K28: =G28-J28 -> 1218687.8 | L28: =IF(G28=0,0,(J28-G28)/G28) -> -0.40039843
B29: Sc. 3 · Without Plan Safe HF tasks and SSC | C29: =SUM(Calculation!P98:Q98) -> 9950 | D29: =SUM(Calculation!P92:Q92) -> 2068508.4 | E29: =SUM(Calculation!P93:Q93) -> 135725.47 | F29: =SUM(Calculation!P94:Q94) -> 0 | G29: =SUM(D29:F29) -> 2204233.9 | H29: =$G$26-G29 -> 1520259.6 | I29: =IF($G$26=0,0,H29/$G$26) -> 0.40817889 | J29: =('Synertec Benchmark'!$D$8+'Synertec Benchmark'!$D$9) -> 1825000 | K29: =G29-J29 -> 379233.85 | L29: =IF(G29=0,0,(J29-G29)/G29) -> -0.17204792
B30: Sc. 4 · Without SSC, Plan Safe HF tasks at reduced price | C30: =SUM(Calculation!P115:Q115) -> 12397 | D30: =SUM(Calculation!P109:Q109) -> 2068508.4 | E30: =SUM(Calculation!P110:Q110) -> 416544.34 | F30: =SUM(Calculation!P111:Q111) -> 0 | G30: =SUM(D30:F30) -> 2485052.7 | H30: =$G$26-G30 -> 1239440.7 | I30: =IF($G$26=0,0,H30/$G$26) -> 0.33278101 | J30: =('Synertec Benchmark'!$D$8+'Synertec Benchmark'!$D$9) -> 1825000 | K30: =G30-J30 -> 660052.73 | L30: =IF(G30=0,0,(J30-G30)/G30) -> -0.26560914
B31: Sc. 5 · Plan Safe as offered, without SSC | C31: =SUM(Calculation!P132:Q132) -> 12397 | D31: =SUM(Calculation!P126:Q126) -> 2068508.4 | E31: =SUM(Calculation!P127:Q127) -> 697363.22 | F31: =SUM(Calculation!P128:Q128) -> 0 | G31: =SUM(D31:F31) -> 2765871.6 | H31: =$G$26-G31 -> 958621.82 | I31: =IF($G$26=0,0,H31/$G$26) -> 0.25738314 | J31: =('Synertec Benchmark'!$D$8+'Synertec Benchmark'!$D$9) -> 1825000 | K31: =G31-J31 -> 940871.61 | L31: =IF(G31=0,0,(J31-G31)/G31) -> -0.34017183
B34: Provisional sum (Stages 6–7)
B35: Scenario | C35: Hours | D35: IDOM | E35: Plan Safe | F35: INVAP | G35: Total price | H35: Reduction A$ | I35: Reduction % | J35: Synertec benchmark | K35: Deviation A$ | L35: Deviation %
B36: Original offer (reference) | C36: =SUM(Calculation!R47:S47) -> 5500 | D36: =SUM(Calculation!R41:S41) -> 996230.76 | E36: =SUM(Calculation!R42:S42) -> 272754.09 | F36: =SUM(Calculation!R43:S43) -> 0 | G36: =SUM(D36:F36) -> 1268984.9 | H36: =$G$36-G36 -> 0 | I36: =IF($G$36=0,0,H36/$G$36) -> 0 | J36: =('Synertec Benchmark'!$D$10+'Synertec Benchmark'!$D$11) -> 175000 | K36: =G36-J36 -> 1093984.9 | L36: =IF(G36=0,0,(J36-G36)/G36) -> -0.86209449
B37: Sc. 1 · Base offer | C37: =SUM(Calculation!R64:S64) -> 5500 | D37: =SUM(Calculation!R58:S58) -> 956381.53 | E37: =SUM(Calculation!R59:S59) -> 272754.09 | F37: =SUM(Calculation!R60:S60) -> 0 | G37: =SUM(D37:F37) -> 1229135.6 | H37: =$G$36-G37 -> 39849.23 | I37: =IF($G$36=0,0,H37/$G$36) -> 0.031402448 | J37: =('Synertec Benchmark'!$D$10+'Synertec Benchmark'!$D$11) -> 175000 | K37: =G37-J37 -> 1054135.6 | L37: =IF(G37=0,0,(J37-G37)/G37) -> -0.85762352
B38: Sc. 2 · Without Plan Safe HF tasks | C38: =SUM(Calculation!R81:S81) -> 4615 | D38: =SUM(Calculation!R75:S75) -> 956381.53 | E38: =SUM(Calculation!R76:S76) -> 69416.34 | F38: =SUM(Calculation!R77:S77) -> 0 | G38: =SUM(D38:F38) -> 1025797.9 | H38: =$G$36-G38 -> 243186.98 | I38: =IF($G$36=0,0,H38/$G$36) -> 0.19163899 | J38: =('Synertec Benchmark'!$D$10+'Synertec Benchmark'!$D$11) -> 175000 | K38: =G38-J38 -> 850797.87 | L38: =IF(G38=0,0,(J38-G38)/G38) -> -0.82940109
B39: Sc. 3 · Without Plan Safe HF tasks and SSC | C39: =SUM(Calculation!R98:S98) -> 2870 | D39: =SUM(Calculation!R92:S92) -> 591926.78 | E39: =SUM(Calculation!R93:S93) -> 47390.228 | F39: =SUM(Calculation!R94:S94) -> 0 | G39: =SUM(D39:F39) -> 639317.01 | H39: =$G$36-G39 -> 629667.84 | I39: =IF($G$36=0,0,H39/$G$36) -> 0.49619808 | J39: =('Synertec Benchmark'!$D$10+'Synertec Benchmark'!$D$11) -> 175000 | K39: =G39-J39 -> 464317.01 | L39: =IF(G39=0,0,(J39-G39)/G39) -> -0.72627038
B40: Sc. 4 · Without SSC, Plan Safe HF tasks at reduced price | C40: =SUM(Calculation!R115:S115) -> 3755 | D40: =SUM(Calculation!R109:S109) -> 591926.78 | E40: =SUM(Calculation!R110:S110) -> 149059.1 | F40: =SUM(Calculation!R111:S111) -> 0 | G40: =SUM(D40:F40) -> 740985.88 | H40: =$G$36-G40 -> 527998.97 | I40: =IF($G$36=0,0,H40/$G$36) -> 0.4160798 | J40: =('Synertec Benchmark'!$D$10+'Synertec Benchmark'!$D$11) -> 175000 | K40: =G40-J40 -> 565985.88 | L40: =IF(G40=0,0,(J40-G40)/G40) -> -0.76382816
B41: Sc. 5 · Plan Safe as offered, without SSC | C41: =SUM(Calculation!R132:S132) -> 3755 | D41: =SUM(Calculation!R126:S126) -> 591926.78 | E41: =SUM(Calculation!R127:S127) -> 250727.98 | F41: =SUM(Calculation!R128:S128) -> 0 | G41: =SUM(D41:F41) -> 842654.76 | H41: =$G$36-G41 -> 426330.09 | I41: =IF($G$36=0,0,H41/$G$36) -> 0.33596153 | J41: =('Synertec Benchmark'!$D$10+'Synertec Benchmark'!$D$11) -> 175000 | K41: =G41-J41 -> 667654.76 | L41: =IF(G41=0,0,(J41-G41)/G41) -> -0.79232301
B44: Stages 1–5 (design to IFC)
B45: Scenario | C45: Hours | D45: IDOM | E45: Plan Safe | F45: INVAP | G45: Total price | H45: Reduction A$ | I45: Reduction % | J45: Synertec benchmark | K45: Deviation A$ | L45: Deviation %
B46: Original offer (reference) | C46: =SUM(Calculation!M47:Q47) -> 27222 | D46: =SUM(Calculation!M41:Q41) -> 4861987.1 | E46: =SUM(Calculation!M42:Q42) -> 1320915.9 | F46: =SUM(Calculation!M43:Q43) -> 78836.1 | G46: =SUM(D46:F46) -> 6261739.2 | H46: =$G$46-G46 -> 0 | I46: =IF($G$46=0,0,H46/$G$46) -> 0 | J46: =('Synertec Benchmark'!$D$5+'Synertec Benchmark'!$D$6+'Synertec Benchmark'!$D$7+'Synertec Benchmark'!$D$8+'Synertec Benchmark'!$D$9) -> 3634000 | K46: =G46-J46 -> 2627739.2 | L46: =IF(G46=0,0,(J46-G46)/G46) -> -0.41965005
B47: Sc. 1 · Base offer | C47: =SUM(Calculation!M64:Q64) -> 27222 | D47: =SUM(Calculation!M58:Q58) -> 4533975 | E47: =SUM(Calculation!M59:Q59) -> 1320915.9 | F47: =SUM(Calculation!M60:Q60) -> 78836.1 | G47: =SUM(D47:F47) -> 5933727 | H47: =$G$46-G47 -> 328012.13 | I47: =IF($G$46=0,0,H47/$G$46) -> 0.052383551 | J47: =('Synertec Benchmark'!$D$5+'Synertec Benchmark'!$D$6+'Synertec Benchmark'!$D$7+'Synertec Benchmark'!$D$8+'Synertec Benchmark'!$D$9) -> 3634000 | K47: =G47-J47 -> 2299727 | L47: =IF(G47=0,0,(J47-G47)/G47) -> -0.38756873
B48: Sc. 2 · Without Plan Safe HF tasks | C48: =SUM(Calculation!M81:Q81) -> 22800 | D48: =SUM(Calculation!M75:Q75) -> 4533975 | E48: =SUM(Calculation!M76:Q76) -> 302538.13 | F48: =SUM(Calculation!M77:Q77) -> 78836.1 | G48: =SUM(D48:F48) -> 4915349.2 | H48: =$G$46-G48 -> 1346389.9 | I48: =IF($G$46=0,0,H48/$G$46) -> 0.21501852 | J48: =('Synertec Benchmark'!$D$5+'Synertec Benchmark'!$D$6+'Synertec Benchmark'!$D$7+'Synertec Benchmark'!$D$8+'Synertec Benchmark'!$D$9) -> 3634000 | K48: =G48-J48 -> 1281349.2 | L48: =IF(G48=0,0,(J48-G48)/G48) -> -0.26068326
B49: Sc. 3 · Without Plan Safe HF tasks and SSC | C49: =SUM(Calculation!M98:Q98) -> 17350 | D49: =SUM(Calculation!M92:Q92) -> 3411906.4 | E49: =SUM(Calculation!M93:Q93) -> 246559.42 | F49: =SUM(Calculation!M94:Q94) -> 78836.1 | G49: =SUM(D49:F49) -> 3737301.9 | H49: =$G$46-G49 -> 2524437.2 | I49: =IF($G$46=0,0,H49/$G$46) -> 0.40315273 | J49: =('Synertec Benchmark'!$D$5+'Synertec Benchmark'!$D$6+'Synertec Benchmark'!$D$7+'Synertec Benchmark'!$D$8+'Synertec Benchmark'!$D$9) -> 3634000 | K49: =G49-J49 -> 103301.92 | L49: =IF(G49=0,0,(J49-G49)/G49) -> -0.027640773
B50: Sc. 4 · Without SSC, Plan Safe HF tasks at reduced price | C50: =SUM(Calculation!M115:Q115) -> 21772 | D50: =SUM(Calculation!M109:Q109) -> 3411906.4 | E50: =SUM(Calculation!M110:Q110) -> 755748.31 | F50: =SUM(Calculation!M111:Q111) -> 78836.1 | G50: =SUM(D50:F50) -> 4246490.8 | H50: =$G$46-G50 -> 2015248.3 | I50: =IF($G$46=0,0,H50/$G$46) -> 0.32183524 | J50: =('Synertec Benchmark'!$D$5+'Synertec Benchmark'!$D$6+'Synertec Benchmark'!$D$7+'Synertec Benchmark'!$D$8+'Synertec Benchmark'!$D$9) -> 3634000 | K50: =G50-J50 -> 612490.81 | L50: =IF(G50=0,0,(J50-G50)/G50) -> -0.14423458
B51: Sc. 5 · Plan Safe as offered, without SSC | C51: =SUM(Calculation!M132:Q132) -> 21772 | D51: =SUM(Calculation!M126:Q126) -> 3411906.4 | E51: =SUM(Calculation!M127:Q127) -> 1264937.2 | F51: =SUM(Calculation!M128:Q128) -> 78836.1 | G51: =SUM(D51:F51) -> 4755679.7 | H51: =$G$46-G51 -> 1506059.5 | I51: =IF($G$46=0,0,H51/$G$46) -> 0.24051776 | J51: =('Synertec Benchmark'!$D$5+'Synertec Benchmark'!$D$6+'Synertec Benchmark'!$D$7+'Synertec Benchmark'!$D$8+'Synertec Benchmark'!$D$9) -> 3634000 | K51: =G51-J51 -> 1121679.7 | L51: =IF(G51=0,0,(J51-G51)/G51) -> -0.23586107
B54: Reduction = original offer − scenario price (positive = cheaper). Deviation % = (benchmark − price) / price.

Sheet Synertec Benchmark
B1: Synertec benchmark comparison
B2: Synertec proposal for the nuclear and radiological scope, by stage (A$). Fixed for every scenario. Deviation A$ = price − benchmark; deviation % = (benchmark − price) / price.
B4: Stage | C4: Description | D4: Synertec proposal (A$) | E4: Original offer (A$) | F4: Deviation A$ | G4: Deviation %
B5: S1 | C5: Project Familiarisation & Initiation | D5: 106000 | E5: =Calculation!M44 -> 335082.83 | F5: =E5-D5 -> 229082.83 | G5: =IF(E5=0,0,(D5-E5)/E5) -> -0.6836603
B6: S2 | C6: Concept Design | D6: 453000 | E6: =Calculation!N44 -> 732839.1 | F6: =E6-D6 -> 279839.1 | G6: =IF(E6=0,0,(D6-E6)/E6) -> -0.38185613
B7: S3 | C7: Preliminary Design | D7: 1250000 | E7: =Calculation!O44 -> 1469323.8 | F7: =E7-D7 -> 219323.8 | G7: =IF(E7=0,0,(D7-E7)/E7) -> -0.14926853
B8: S4 | C8: Detailed Design | D8: 1455000 | E8: =Calculation!P44 -> 3183882.6 | F8: =E8-D8 -> 1728882.6 | G8: =IF(E8=0,0,(D8-E8)/E8) -> -0.54301078
B9: S5 | C9: Issued For Construction | D9: 370000 | E9: =Calculation!Q44 -> 540610.88 | F9: =E9-D9 -> 170610.88 | G9: =IF(E9=0,0,(D9-E9)/E9) -> -0.31558905
B10: S6 | C10: Construction Support | D10: 102000 | E10: =Calculation!R44 -> 775079.55 | F10: =E10-D10 -> 673079.55 | G10: =IF(E10=0,0,(D10-E10)/E10) -> -0.8684006
B11: S7 | C11: Commissioning, Qualification & Validation | D11: 73000 | E11: =Calculation!S44 -> 493905.3 | F11: =E11-D11 -> 420905.3 | G11: =IF(E11=0,0,(D11-E11)/E11) -> -0.85219839
B12: TOTAL | D12: =SUM(D5:D11) -> 3809000 | E12: =SUM(E5:E11) -> 7530724 | F12: =SUM(F5:F11) -> 3721724 | G12: =IF(E12=0,0,(D12-E12)/E12) -> -0.49420534
B15: Scenario prices against the benchmark, by stage (with the commercial assumptions applied)
D16: Sc. 1 · Base offer | F16: Sc. 2 · Without Plan Safe HF tasks | H16: Sc. 3 · Without Plan Safe HF tasks and SSC | J16: Sc. 4 · Without SSC, Plan Safe HF tasks at reduced price | L16: Sc. 5 · Plan Safe as offered, without SSC
B17: Stage | C17: Synertec | D17: Price (A$) | E17: Deviation % | F17: Price (A$) | G17: Deviation % | H17: Price (A$) | I17: Deviation % | J17: Price (A$) | K17: Deviation % | L17: Price (A$) | M17: Deviation %
B18: S1 | C18: ='Synertec Benchmark'!$D$5 -> 106000 | D18: =Calculation!M61 -> 329748.36 | E18: =IF(D18=0,0,($C18-D18)/D18) -> -0.67854275 | F18: =Calculation!M78 -> 221681.31 | G18: =IF(F18=0,0,($C18-F18)/F18) -> -0.52183609 | H18: =Calculation!M95 -> 221681.31 | I18: =IF(H18=0,0,($C18-H18)/H18) -> -0.52183609 | J18: =Calculation!M112 -> 275714.83 | K18: =IF(J18=0,0,($C18-J18)/J18) -> -0.6155448 | L18: =Calculation!M129 -> 329748.36 | M18: =IF(L18=0,0,($C18-L18)/L18) -> -0.67854275
B19: S2 | C19: ='Synertec Benchmark'!$D$6 -> 453000 | D19: =Calculation!N61 -> 577845.85 | E19: =IF(D19=0,0,($C19-D19)/D19) -> -0.2160539 | F19: =Calculation!N78 -> 418979.28 | G19: =IF(F19=0,0,($C19-F19)/F19) -> 0.081199058 | H19: =Calculation!N95 -> 348056.02 | I19: =IF(H19=0,0,($C19-H19)/H19) -> 0.30151461 | J19: =Calculation!N112 -> 427489.31 | K19: =IF(J19=0,0,($C19-J19)/J19) -> 0.059675617 | L19: =Calculation!N129 -> 506922.6 | M19: =IF(L19=0,0,($C19-L19)/L19) -> -0.10637245
B20: S3 | C20: ='Synertec Benchmark'!$D$7 -> 1250000 | D20: =Calculation!O61 -> 1420807.2 | E20: =IF(D20=0,0,($C20-D20)/D20) -> -0.12021844 | F20: =Calculation!O78 -> 1231000.8 | G20: =IF(F20=0,0,($C20-F20)/F20) -> 0.015433922 | H20: =Calculation!O95 -> 963330.73 | I20: =IF(H20=0,0,($C20-H20)/H20) -> 0.29758136 | J20: =Calculation!O112 -> 1058233.9 | K20: =IF(J20=0,0,($C20-J20)/J20) -> 0.1812133 | L20: =Calculation!O129 -> 1153137.1 | M20: =IF(L20=0,0,($C20-L20)/L20) -> 0.083999433
B21: S4 | C21: ='Synertec Benchmark'!$D$8 -> 1455000 | D21: =Calculation!P61 -> 3079920.1 | E21: =IF(D21=0,0,($C21-D21)/D21) -> -0.52758515 | F21: =Calculation!P78 -> 2646815.5 | G21: =IF(F21=0,0,($C21-F21)/F21) -> -0.4502828 | H21: =Calculation!P95 -> 2045662.6 | I21: =IF(H21=0,0,($C21-H21)/H21) -> -0.28873901 | J21: =Calculation!P112 -> 2262214.9 | K21: =IF(J21=0,0,($C21-J21)/J21) -> -0.35682503 | L21: =Calculation!P129 -> 2478767.2 | M21: =IF(L21=0,0,($C21-L21)/L21) -> -0.41301467
B22: S5 | C22: ='Synertec Benchmark'!$D$9 -> 370000 | D22: =Calculation!Q61 -> 525405.49 | E22: =IF(D22=0,0,($C22-D22)/D22) -> -0.29578201 | F22: =Calculation!Q78 -> 396872.36 | G22: =IF(F22=0,0,($C22-F22)/F22) -> -0.067710343 | H22: =Calculation!Q95 -> 158571.25 | I22: =IF(H22=0,0,($C22-H22)/H22) -> 1.3333359 | J22: =Calculation!Q112 -> 222837.81 | K22: =IF(J22=0,0,($C22-J22)/J22) -> 0.66040042 | L22: =Calculation!Q129 -> 287104.38 | M22: =IF(L22=0,0,($C22-L22)/L22) -> 0.28872992
B23: S6 | C23: ='Synertec Benchmark'!$D$10 -> 102000 | D23: =Calculation!R61 -> 751719.06 | E23: =IF(D23=0,0,($C23-D23)/D23) -> -0.86431101 | F23: =Calculation!R78 -> 604829.31 | G23: =IF(F23=0,0,($C23-F23)/F23) -> -0.83135738 | H23: =Calculation!R95 -> 349428.25 | I23: =IF(H23=0,0,($C23-H23)/H23) -> -0.70809458 | J23: =Calculation!R112 -> 422873.12 | K23: =IF(J23=0,0,($C23-J23)/J23) -> -0.7587929 | L23: =Calculation!R129 -> 496318 | M23: =IF(L23=0,0,($C23-L23)/L23) -> -0.7944866
B24: S7 | C24: ='Synertec Benchmark'!$D$11 -> 73000 | D24: =Calculation!S61 -> 477416.56 | E24: =IF(D24=0,0,($C24-D24)/D24) -> -0.8470937 | F24: =Calculation!S78 -> 420968.56 | G24: =IF(F24=0,0,($C24-F24)/F24) -> -0.82659038 | H24: =Calculation!S95 -> 289888.76 | I24: =IF(H24=0,0,($C24-H24)/H24) -> -0.74817927 | J24: =Calculation!S112 -> 318112.76 | K24: =IF(J24=0,0,($C24-J24)/J24) -> -0.77052162 | L24: =Calculation!S129 -> 346336.76 | M24: =IF(L24=0,0,($C24-L24)/L24) -> -0.78922249
B25: S1–S3 | C25: =('Synertec Benchmark'!$D$5+'Synertec Benchmark'!$D$6+'Synertec Benchmark'!$D$7) -> 1809000 | D25: =SUM(Calculation!M61:O61) -> 2328401.4 | E25: =IF(D25=0,0,($C25-D25)/D25) -> -0.22307212 | F25: =SUM(Calculation!M78:O78) -> 1871661.4 | G25: =IF(F25=0,0,($C25-F25)/F25) -> -0.033479033 | H25: =SUM(Calculation!M95:O95) -> 1533068.1 | I25: =IF(H25=0,0,($C25-H25)/H25) -> 0.17998675 | J25: =SUM(Calculation!M112:O112) -> 1761438.1 | K25: =IF(J25=0,0,($C25-J25)/J25) -> 0.027001757 | L25: =SUM(Calculation!M129:O129) -> 1989808.1 | M25: =IF(L25=0,0,($C25-L25)/L25) -> -0.0908671
B26: S4–S5 | C26: =('Synertec Benchmark'!$D$8+'Synertec Benchmark'!$D$9) -> 1825000 | D26: =SUM(Calculation!P61:Q61) -> 3605325.6 | E26: =IF(D26=0,0,($C26-D26)/D26) -> -0.49380439 | F26: =SUM(Calculation!P78:Q78) -> 3043687.8 | G26: =IF(F26=0,0,($C26-F26)/F26) -> -0.40039843 | H26: =SUM(Calculation!P95:Q95) -> 2204233.9 | I26: =IF(H26=0,0,($C26-H26)/H26) -> -0.17204792 | J26: =SUM(Calculation!P112:Q112) -> 2485052.7 | K26: =IF(J26=0,0,($C26-J26)/J26) -> -0.26560914 | L26: =SUM(Calculation!P129:Q129) -> 2765871.6 | M26: =IF(L26=0,0,($C26-L26)/L26) -> -0.34017183
B27: S6–S7 | C27: =('Synertec Benchmark'!$D$10+'Synertec Benchmark'!$D$11) -> 175000 | D27: =SUM(Calculation!R61:S61) -> 1229135.6 | E27: =IF(D27=0,0,($C27-D27)/D27) -> -0.85762352 | F27: =SUM(Calculation!R78:S78) -> 1025797.9 | G27: =IF(F27=0,0,($C27-F27)/F27) -> -0.82940109 | H27: =SUM(Calculation!R95:S95) -> 639317.01 | I27: =IF(H27=0,0,($C27-H27)/H27) -> -0.72627038 | J27: =SUM(Calculation!R112:S112) -> 740985.88 | K27: =IF(J27=0,0,($C27-J27)/J27) -> -0.76382816 | L27: =SUM(Calculation!R129:S129) -> 842654.76 | M27: =IF(L27=0,0,($C27-L27)/L27) -> -0.79232301
B28: S1–S5 | C28: =('Synertec Benchmark'!$D$5+'Synertec Benchmark'!$D$6+'Synertec Benchmark'!$D$7+'Synertec Benchmark'!$D$8+'Synertec Benchmark'!$D$9) -> 3634000 | D28: =SUM(Calculation!M61:Q61) -> 5933727 | E28: =IF(D28=0,0,($C28-D28)/D28) -> -0.38756873 | F28: =SUM(Calculation!M78:Q78) -> 4915349.2 | G28: =IF(F28=0,0,($C28-F28)/F28) -> -0.26068326 | H28: =SUM(Calculation!M95:Q95) -> 3737301.9 | I28: =IF(H28=0,0,($C28-H28)/H28) -> -0.027640773 | J28: =SUM(Calculation!M112:Q112) -> 4246490.8 | K28: =IF(J28=0,0,($C28-J28)/J28) -> -0.14423458 | L28: =SUM(Calculation!M129:Q129) -> 4755679.7 | M28: =IF(L28=0,0,($C28-L28)/L28) -> -0.23586107
B29: TOTAL | C29: =('Synertec Benchmark'!$D$5+'Synertec Benchmark'!$D$6+'Synertec Benchmark'!$D$7+'Synertec Benchmark'!$D$8+'Synertec Benchmark'!$D$9+'Synertec Benchmark'!$D$10+'Synertec Benchmark'!$D$11) -> 3809000 | D29: =SUM(Calculation!M61:S61) -> 7162862.6 | E29: =IF(D29=0,0,($C29-D29)/D29) -> -0.46822937 | F29: =SUM(Calculation!M78:S78) -> 5941147.1 | G29: =IF(F29=0,0,($C29-F29)/F29) -> -0.35887802 | H29: =SUM(Calculation!M95:S95) -> 4376618.9 | I29: =IF(H29=0,0,($C29-H29)/H29) -> -0.12969348 | J29: =SUM(Calculation!M112:S112) -> 4987476.7 | K29: =IF(J29=0,0,($C29-J29)/J29) -> -0.23628716 | L29: =SUM(Calculation!M129:S129) -> 5598334.5 | M29: =IF(L29=0,0,($C29-L29)/L29) -> -0.31961907
B31: Negative deviation = the Synertec benchmark is below the scenario price. Blocks: S1–S3 lump sum, S4–S5 and S6–S7 provisional sums, S1–S5 design to IFC.

Sheet Assumptions
B1: Assumptions and inputs
B2: Yellow cells with blue text are inputs; grey cells are fixed values from the original offer. Every sheet recalculates from these cells.
B4: Commercial assumptions applied to every scenario
B5: Stage 2 rework allowance included in the original offer | C5: 0.35 | D5: Carried in the original offer as a 35% surcharge on IDOM's Stage 2 tasks.
B6: Stage 2 rework allowance considered in this proposal | C6: 0 | D6: 0% = the allowance is released in full: all deliverables are assumed right first time.
B7: Commercial discount on IDOM's scope | C7: 0.04 | D7: Applied to everything IDOM invoices, after the rework release. Not applied to Plan Safe or INVAP.
B8: Optional levers
B9: Include INVAP (Conceptual Design Verification)? | C9: Yes | D9: No = INVAP's Stage 1 verification is removed from every scenario.
B10: Price deliverable S1 as a two-week single issue? | C10: No | D10: Yes = Safety Assurance Plan / Safety Integration Plan issued once at framework level in Stage 1, with no Stage 2 update.
B11: Deliverable S1 two-week option: hours | C11: 165 | D11: Ten working days, approximately 2.2 senior authors.
B12: Deliverable S1 two-week option: price (A$) | C12: 38675 | D12: A$41,769 inclusive of variable costs (information only).
B13: Subcontractor parameters
B14: Plan Safe share of the shared deliverables | C14: 0.1 | D14: Share of the deliverables led by IDOM with specialist input. Moves money between IDOM and Plan Safe; does not change the total.
B15: Plan Safe HF tasks price factor in scenario 4 | C15: 0.5 | D15: 50% = Plan Safe's own HF deliverables at half price.
B17: Scenario definitions
B18: Scenario | C18: Name | D18: Definition
B19: Scenario 1 | C19: Base offer | D19: Full scope as offered.
B20: Scenario 2 | C20: Without Plan Safe HF tasks | D20: Removes Plan Safe's four human factors deliverables: S2, S3, S8 and S30.
B21: Scenario 3 | C21: Without Plan Safe HF tasks and SSC | D21: Removes the four HF deliverables and the SSC group: S26, S27, S28 and S29.
B22: Scenario 4 | C22: Without SSC, Plan Safe HF tasks at reduced price | D22: Removes the SSC group; Plan Safe's HF deliverables at the price factor above.
B23: Scenario 5 | C23: Plan Safe as offered, without SSC | D23: Removes the SSC group only; Plan Safe scope as offered.
B25: Every scenario includes the commercial assumptions above. The original offer (reference) is the offer as submitted, with no adjustments.

Sheet Calculation
A1: Calculation engine — do not edit (driven by Assumptions and Data)
M3: S1 | N3: S2 | O3: S3 | P3: S4 | Q3: S5 | R3: S6 | S3: S7 | T3: S1 | U3: S2 | V3: S3 | W3: S4 | X3: S5 | Y3: S6 | Z3: S7
A4: Code | B4: Deliverable | C4: Type | D4: Group | E4: % IDOM | F4: % Plan Safe | G4: % INVAP | H4: Factor Sc.1 | I4: Factor Sc.2 | J4: Factor Sc.3 | K4: Factor Sc.4 | L4: Factor Sc.5 | M4: A$ S1 | N4: A$ S2 | O4: A$ S3 | P4: A$ S4 | Q4: A$ S5 | R4: A$ S6 | S4: A$ S7 | T4: h S1 | U4: h S2 | V4: h S3 | W4: h S4 | X4: h S5 | Y4: h S6 | Z4: h S7 | AA4: A$ S1–S3 | AB4: A$ S4–S5 | AC4: A$ S6–S7 | AD4: A$ S1–S5 | AE4: A$ Total
A5: E94 | B5: Radiological Zoning Layout drawing(s) | C5: IDOM | D5: Other | E5: =IF(C5="IDOM",1,IF(C5="Shared",1-Assumptions!$C$14,0)) -> 1 | F5: =IF(C5="Plan Safe",1,IF(C5="Shared",Assumptions!$C$14,0)) -> 0 | G5: =IF(C5="INVAP",1,0) -> 0 | H5: 1 | I5: 1 | J5: 1 | K5: 1 | L5: 1 | M5: =SUMIFS(Data!$J$5:$J$291,Data!$E$5:$E$291,$A5,Data!$F$5:$F$291,"S1") -> 0 | N5: =SUMIFS(Data!$J$5:$J$291,Data!$E$5:$E$291,$A5,Data!$F$5:$F$291,"S2") -> 35206.5 | O5: =SUMIFS(Data!$J$5:$J$291,Data!$E$5:$E$291,$A5,Data!$F$5:$F$291,"S3") -> 58869.825 | P5: =SUMIFS(Data!$J$5:$J$291,Data!$E$5:$E$291,$A5,Data!$F$5:$F$291,"S4") -> 85451.1 | Q5: =SUMIFS(Data!$J$5:$J$291,Data!$E$5:$E$291,$A5,Data!$F$5:$F$291,"S5") -> 0 | R5: =SUMIFS(Data!$J$5:$J$291,Data!$E$5:$E$291,$A5,Data!$F$5:$F$291,"S6") -> 0 | S5: =SUMIFS(Data!$J$5:$J$291,Data!$E$5:$E$291,$A5,Data!$F$5:$F$291,"S7") -> 0 | T5: =SUMIFS(Data!$H$5:$H$291,Data!$E$5:$E$291,$A5,Data!$F$5:$F$291,"S1") -> 0 | U5: =SUMIFS(Data!$H$5:$H$291,Data!$E$5:$E$291,$A5,Data!$F$5:$F$291,"S2") -> 185 | V5: =SUMIFS(Data!$H$5:$H$291,Data!$E$5:$E$291,$A5,Data!$F$5:$F$291,"S3") -> 315 | W5: =SUMIFS(Data!$H$5:$H$291,Data!$E$5:$E$291,$A5,Data!$F$5:$F$291,"S4") -> 430 | X5: =SUMIFS(Data!$H$5:$H$291,Data!$E$5:$E$291,$A5,Data!$F$5:$F$291,"S5") -> 0 | Y5: =SUMIFS(Data!$H$5:$H$291,Data!$E$5:$E$291,$A5,Data!$F$5:$F$291,"S6") -> 0 | Z5: =SUMIFS(Data!$H$5:$H$291,Data!$E$5:$E$291,$A5,Data!$F$5:$F$291,"S7") -> 0 | AA5: =M5+N5+O5 -> 94076.325 | AB5: =P5+Q5 -> 85451.1 | AC5: =R5+S5 -> 0 | AD5: =M5+N5+O5+P5+Q5 -> 179527.42 | AE5: =M5+N5+O5+P5+Q5+R5+S5 -> 179527.42
A6: S1 | B6: Safety Assurance Plan / Safety Integration Plan | C6: Shared | D6: Other | E6: =IF(C6="IDOM",1,IF(C6="Shared",1-Assumptions!$C$14,0)) -> 0.9 | F6: =IF(C6="Plan Safe",1,IF(C6="Shared",Assumptions!$C$14,0)) -> 0.1 | G6: =IF(C6="INVAP",1,0) -> 0 | H6: 1 | I6: 1 | J6: 1 | K6: 1 | L6: 1 | M6: =SUMIFS(Data!$J$5:$J$291,Data!$E$5:$E$291,$A6,Data!$F$5:$F$291,"S1") -> 148179.67 | N6: =SUMIFS(Data!$J$5:$J$291,Data!$E$5:$E$291,$A6,Data!$F$5:$F$291,"S2") -> 284239.2 | O6: =SUMIFS(Data!$J$5:$J$291,Data!$E$5:$E$291,$A6,Data!$F$5:$F$291,"S3") -> 0 | P6: =SUMIFS(Data!$J$5:$J$291,Data!$E$5:$E$291,$A6,Data!$F$5:$F$291,"S4") -> 0 | Q6: =SUMIFS(Data!$J$5:$J$291,Data!$E$5:$E$291,$A6,Data!$F$5:$F$291,"S5") -> 0 | R6: =SUMIFS(Data!$J$5:$J$291,Data!$E$5:$E$291,$A6,Data!$F$5:$F$291,"S6") -> 0 | S6: =SUMIFS(Data!$J$5:$J$291,Data!$E$5:$E$291,$A6,Data!$F$5:$F$291,"S7") -> 0 | T6: =SUMIFS(Data!$H$5:$H$291,Data!$E$5:$E$291,$A6,Data!$F$5:$F$291,"S1") -> 625 | U6: =SUMIFS(Data!$H$5:$H$291,Data!$E$5:$E$291,$A6,Data!$F$5:$F$291,"S2") -> 1200 | V6: =SUMIFS(Data!$H$5:$H$291,Data!$E$5:$E$291,$A6,Data!$F$5:$F$291,"S3") -> 0 | W6: =SUMIFS(Data!$H$5:$H$291,Data!$E$5:$E$291,$A6,Data!$F$5:$F$291,"S4") -> 0 | X6: =SUMIFS(Data!$H$5:$H$291,Data!$E$5:$E$291,$A6,Data!$F$5:$F$291,"S5") -> 0 | Y6: =SUMIFS(Data!$H$5:$H$291,Data!$E$5:$E$291,$A6,Data!$F$5:$F$291,"S6") -> 0 | Z6: =SUMIFS(Data!$H$5:$H$291,Data!$E$5:$E$291,$A6,Data!$F$5:$F$291,"S7") -> 0 | AA6: =M6+N6+O6 -> 432418.88 | AB6: =P6+Q6 -> 0 | AC6: =R6+S6 -> 0 | AD6: =M6+N6+O6+P6+Q6 -> 432418.88 | AE6: =M6+N6+O6+P6+Q6+R6+S6 -> 432418.88
A7: S9 | B7: Deterministic Safety Assessment(s) (DSA) / Inherent Risk Assessment(s) | C7: Shared | D7: Other | E7: =IF(C7="IDOM",1,IF(C7="Shared",1-Assumptions!$C$14,0)) -> 0.9 | F7: =IF(C7="Plan Safe",1,IF(C7="Shared",Assumptions!$C$14,0)) -> 0.1 | G7: =IF(C7="INVAP",1,0) -> 0 | H7: 1 | I7: 1 | J7: 1 | K7: 1 | L7: 1 | M7: =SUMIFS(Data!$J$5:$J$291,Data!$E$5:$E$291,$A7,Data!$F$5:$F$291,"S1") -> 0 | N7: =SUMIFS(Data!$J$5:$J$291,Data!$E$5:$E$291,$A7,Data!$F$5:$F$291,"S2") -> 0 | O7: =SUMIFS(Data!$J$5:$J$291,Data!$E$5:$E$291,$A7,Data!$F$5:$F$291,"S3") -> 323392.65 | P7: =SUMIFS(Data!$J$5:$J$291,Data!$E$5:$E$291,$A7,Data!$F$5:$F$291,"S4") -> 237629.17 | Q7: =SUMIFS(Data!$J$5:$J$291,Data!$E$5:$E$291,$A7,Data!$F$5:$F$291,"S5") -> 0 | R7: =SUMIFS(Data!$J$5:$J$291,Data!$E$5:$E$291,$A7,Data!$F$5:$F$291,"S6") -> 92514.45 | S7: =SUMIFS(Data!$J$5:$J$291,Data!$E$5:$E$291,$A7,Data!$F$5:$F$291,"S7") -> 57256.5 | T7: =SUMIFS(Data!$H$5:$H$291,Data!$E$5:$E$291,$A7,Data!$F$5:$F$291,"S1") -> 0 | U7: =SUMIFS(Data!$H$5:$H$291,Data!$E$5:$E$291,$A7,Data!$F$5:$F$291,"S2") -> 0 | V7: =SUMIFS(Data!$H$5:$H$291,Data!$E$5:$E$291,$A7,Data!$F$5:$F$291,"S3") -> 1385 | W7: =SUMIFS(Data!$H$5:$H$291,Data!$E$5:$E$291,$A7,Data!$F$5:$F$291,"S4") -> 1015 | X7: =SUMIFS(Data!$H$5:$H$291,Data!$E$5:$E$291,$A7,Data!$F$5:$F$291,"S5") -> 0 | Y7: =SUMIFS(Data!$H$5:$H$291,Data!$E$5:$E$291,$A7,Data!$F$5:$F$291,"S6") -> 390 | Z7: =SUMIFS(Data!$H$5:$H$291,Data!$E$5:$E$291,$A7,Data!$F$5:$F$291,"S7") -> 245 | AA7: =M7+N7+O7 -> 323392.65 | AB7: =P7+Q7 -> 237629.17 | AC7: =R7+S7 -> 149770.95 | AD7: =M7+N7+O7+P7+Q7 -> 561021.82 | AE7: =M7+N7+O7+P7+Q7+R7+S7 -> 710792.78
A8: S10 | B8: Probablisitic Safety Assessment / Quantitative Risk Assessment (s) (QRA) | C8: Shared | D8: Other | E8: =IF(C8="IDOM",1,IF(C8="Shared",1-Assumptions!$C$14,0)) -> 0.9 | F8: =IF(C8="Plan Safe",1,IF(C8="Shared",Assumptions!$C$14,0)) -> 0.1 | G8: =IF(C8="INVAP",1,0) -> 0 | H8: 1 | I8: 1 | J8: 1 | K8: 1 | L8: 1 | M8: =SUMIFS(Data!$J$5:$J$291,Data!$E$5:$E$291,$A8,Data!$F$5:$F$291,"S1") -> 0 | N8: =SUMIFS(Data!$J$5:$J$291,Data!$E$5:$E$291,$A8,Data!$F$5:$F$291,"S2") -> 0 | O8: =SUMIFS(Data!$J$5:$J$291,Data!$E$5:$E$291,$A8,Data!$F$5:$F$291,"S3") -> 0 | P8: =SUMIFS(Data!$J$5:$J$291,Data!$E$5:$E$291,$A8,Data!$F$5:$F$291,"S4") -> 222212.55 | Q8: =SUMIFS(Data!$J$5:$J$291,Data!$E$5:$E$291,$A8,Data!$F$5:$F$291,"S5") -> 0 | R8: =SUMIFS(Data!$J$5:$J$291,Data!$E$5:$E$291,$A8,Data!$F$5:$F$291,"S6") -> 42192.675 | S8: =SUMIFS(Data!$J$5:$J$291,Data!$E$5:$E$291,$A8,Data!$F$5:$F$291,"S7") -> 26985.525 | T8: =SUMIFS(Data!$H$5:$H$291,Data!$E$5:$E$291,$A8,Data!$F$5:$F$291,"S1") -> 0 | U8: =SUMIFS(Data!$H$5:$H$291,Data!$E$5:$E$291,$A8,Data!$F$5:$F$291,"S2") -> 0 | V8: =SUMIFS(Data!$H$5:$H$291,Data!$E$5:$E$291,$A8,Data!$F$5:$F$291,"S3") -> 0 | W8: =SUMIFS(Data!$H$5:$H$291,Data!$E$5:$E$291,$A8,Data!$F$5:$F$291,"S4") -> 950 | X8: =SUMIFS(Data!$H$5:$H$291,Data!$E$5:$E$291,$A8,Data!$F$5:$F$291,"S5") -> 0 | Y8: =SUMIFS(Data!$H$5:$H$291,Data!$E$5:$E$291,$A8,Data!$F$5:$F$291,"S6") -> 180 | Z8: =SUMIFS(Data!$H$5:$H$291,Data!$E$5:$E$291,$A8,Data!$F$5:$F$291,"S7") -> 115 | AA8: =M8+N8+O8 -> 0 | AB8: =P8+Q8 -> 222212.55 | AC8: =R8+S8 -> 69178.2 | AD8: =M8+N8+O8+P8+Q8 -> 222212.55 | AE8: =M8+N8+O8+P8+Q8+R8+S8 -> 291390.75
A9: S17 | B9: ALARP (Optioneering) Study | C9: Shared | D9: Other | E9: =IF(C9="IDOM",1,IF(C9="Shared",1-Assumptions!$C$14,0)) -> 0.9 | F9: =IF(C9="Plan Safe",1,IF(C9="Shared",Assumptions!$C$14,0)) -> 0.1 | G9: =IF(C9="INVAP",1,0) -> 0 | H9: 1 | I9: 1 | J9: 1 | K9: 1 | L9: 1 | M9: =SUMIFS(Data!$J$5:$J$291,Data!$E$5:$E$291,$A9,Data!$F$5:$F$291,"S1") -> 0 | N9: =SUMIFS(Data!$J$5:$J$291,Data!$E$5:$E$291,$A9,Data!$F$5:$F$291,"S2") -> 90335.175 | O9: =SUMIFS(Data!$J$5:$J$291,Data!$E$5:$E$291,$A9,Data!$F$5:$F$291,"S3") -> 151656.23 | P9: =SUMIFS(Data!$J$5:$J$291,Data!$E$5:$E$291,$A9,Data!$F$5:$F$291,"S4") -> 211896.83 | Q9: =SUMIFS(Data!$J$5:$J$291,Data!$E$5:$E$291,$A9,Data!$F$5:$F$291,"S5") -> 0 | R9: =SUMIFS(Data!$J$5:$J$291,Data!$E$5:$E$291,$A9,Data!$F$5:$F$291,"S6") -> 0 | S9: =SUMIFS(Data!$J$5:$J$291,Data!$E$5:$E$291,$A9,Data!$F$5:$F$291,"S7") -> 0 | T9: =SUMIFS(Data!$H$5:$H$291,Data!$E$5:$E$291,$A9,Data!$F$5:$F$291,"S1") -> 0 | U9: =SUMIFS(Data!$H$5:$H$291,Data!$E$5:$E$291,$A9,Data!$F$5:$F$291,"S2") -> 385 | V9: =SUMIFS(Data!$H$5:$H$291,Data!$E$5:$E$291,$A9,Data!$F$5:$F$291,"S3") -> 650 | W9: =SUMIFS(Data!$H$5:$H$291,Data!$E$5:$E$291,$A9,Data!$F$5:$F$291,"S4") -> 905 | X9: =SUMIFS(Data!$H$5:$H$291,Data!$E$5:$E$291,$A9,Data!$F$5:$F$291,"S5") -> 0 | Y9: =SUMIFS(Data!$H$5:$H$291,Data!$E$5:$E$291,$A9,Data!$F$5:$F$291,"S6") -> 0 | Z9: =SUMIFS(Data!$H$5:$H$291,Data!$E$5:$E$291,$A9,Data!$F$5:$F$291,"S7") -> 0 | AA9: =M9+N9+O9 -> 241991.4 | AB9: =P9+Q9 -> 211896.83 | AC9: =R9+S9 -> 0 | AD9: =M9+N9+O9+P9+Q9 -> 453888.22 | AE9: =M9+N9+O9+P9+Q9+R9+S9 -> 453888.22
A10: S18 | B10: ALARP Summary Report (ALARP/SFARP Statement Report) | C10: Shared | D10: Other | E10: =IF(C10="IDOM",1,IF(C10="Shared",1-Assumptions!$C$14,0)) -> 0.9 | F10: =IF(C10="Plan Safe",1,IF(C10="Shared",Assumptions!$C$14,0)) -> 0.1 | G10: =IF(C10="INVAP",1,0) -> 0 | H10: 1 | I10: 1 | J10: 1 | K10: 1 | L10: 1 | M10: =SUMIFS(Data!$J$5:$J$291,Data!$E$5:$E$291,$A10,Data!$F$5:$F$291,"S1") -> 0 | N10: =SUMIFS(Data!$J$5:$J$291,Data!$E$5:$E$291,$A10,Data!$F$5:$F$291,"S2") -> 0 | O10: =SUMIFS(Data!$J$5:$J$291,Data!$E$5:$E$291,$A10,Data!$F$5:$F$291,"S3") -> 0 | P10: =SUMIFS(Data!$J$5:$J$291,Data!$E$5:$E$291,$A10,Data!$F$5:$F$291,"S4") -> 142939.12 | Q10: =SUMIFS(Data!$J$5:$J$291,Data!$E$5:$E$291,$A10,Data!$F$5:$F$291,"S5") -> 0 | R10: =SUMIFS(Data!$J$5:$J$291,Data!$E$5:$E$291,$A10,Data!$F$5:$F$291,"S6") -> 0 | S10: =SUMIFS(Data!$J$5:$J$291,Data!$E$5:$E$291,$A10,Data!$F$5:$F$291,"S7") -> 0 | T10: =SUMIFS(Data!$H$5:$H$291,Data!$E$5:$E$291,$A10,Data!$F$5:$F$291,"S1") -> 0 | U10: =SUMIFS(Data!$H$5:$H$291,Data!$E$5:$E$291,$A10,Data!$F$5:$F$291,"S2") -> 0 | V10: =SUMIFS(Data!$H$5:$H$291,Data!$E$5:$E$291,$A10,Data!$F$5:$F$291,"S3") -> 0 | W10: =SUMIFS(Data!$H$5:$H$291,Data!$E$5:$E$291,$A10,Data!$F$5:$F$291,"S4") -> 610 | X10: =SUMIFS(Data!$H$5:$H$291,Data!$E$5:$E$291,$A10,Data!$F$5:$F$291,"S5") -> 0 | Y10: =SUMIFS(Data!$H$5:$H$291,Data!$E$5:$E$291,$A10,Data!$F$5:$F$291,"S6") -> 0 | Z10: =SUMIFS(Data!$H$5:$H$291,Data!$E$5:$E$291,$A10,Data!$F$5:$F$291,"S7") -> 0 | AA10: =M10+N10+O10 -> 0 | AB10: =P10+Q10 -> 142939.12 | AC10: =R10+S10 -> 0 | AD10: =M10+N10+O10+P10+Q10 -> 142939.12 | AE10: =M10+N10+O10+P10+Q10+R10+S10 -> 142939.12
A11: S20 | B11: Safety in Design (SiD) Report | C11: IDOM | D11: Other | E11: =IF(C11="IDOM",1,IF(C11="Shared",1-Assumptions!$C$14,0)) -> 1 | F11: =IF(C11="Plan Safe",1,IF(C11="Shared",Assumptions!$C$14,0)) -> 0 | G11: =IF(C11="INVAP",1,0) -> 0 | H11: 1 | I11: 1 | J11: 1 | K11: 1 | L11: 1 | M11: =SUMIFS(Data!$J$5:$J$291,Data!$E$5:$E$291,$A11,Data!$F$5:$F$291,"S1") -> 0 | N11: =SUMIFS(Data!$J$5:$J$291,Data!$E$5:$E$291,$A11,Data!$F$5:$F$291,"S2") -> 0 | O11: =SUMIFS(Data!$J$5:$J$291,Data!$E$5:$E$291,$A11,Data!$F$5:$F$291,"S3") -> 0 | P11: =SUMIFS(Data!$J$5:$J$291,Data!$E$5:$E$291,$A11,Data!$F$5:$F$291,"S4") -> 129334.27 | Q11: =SUMIFS(Data!$J$5:$J$291,Data!$E$5:$E$291,$A11,Data!$F$5:$F$291,"S5") -> 0 | R11: =SUMIFS(Data!$J$5:$J$291,Data!$E$5:$E$291,$A11,Data!$F$5:$F$291,"S6") -> 0 | S11: =SUMIFS(Data!$J$5:$J$291,Data!$E$5:$E$291,$A11,Data!$F$5:$F$291,"S7") -> 0 | T11: =SUMIFS(Data!$H$5:$H$291,Data!$E$5:$E$291,$A11,Data!$F$5:$F$291,"S1") -> 0 | U11: =SUMIFS(Data!$H$5:$H$291,Data!$E$5:$E$291,$A11,Data!$F$5:$F$291,"S2") -> 0 | V11: =SUMIFS(Data!$H$5:$H$291,Data!$E$5:$E$291,$A11,Data!$F$5:$F$291,"S3") -> 0 | W11: =SUMIFS(Data!$H$5:$H$291,Data!$E$5:$E$291,$A11,Data!$F$5:$F$291,"S4") -> 565 | X11: =SUMIFS(Data!$H$5:$H$291,Data!$E$5:$E$291,$A11,Data!$F$5:$F$291,"S5") -> 0 | Y11: =SUMIFS(Data!$H$5:$H$291,Data!$E$5:$E$291,$A11,Data!$F$5:$F$291,"S6") -> 0 | Z11: =SUMIFS(Data!$H$5:$H$291,Data!$E$5:$E$291,$A11,Data!$F$5:$F$291,"S7") -> 0 | AA11: =M11+N11+O11 -> 0 | AB11: =P11+Q11 -> 129334.27 | AC11: =R11+S11 -> 0 | AD11: =M11+N11+O11+P11+Q11 -> 129334.27 | AE11: =M11+N11+O11+P11+Q11+R11+S11 -> 129334.27
A12: S21 | B12: Radiological Shielding Basis of Design | C12: IDOM | D12: Other | E12: =IF(C12="IDOM",1,IF(C12="Shared",1-Assumptions!$C$14,0)) -> 1 | F12: =IF(C12="Plan Safe",1,IF(C12="Shared",Assumptions!$C$14,0)) -> 0 | G12: =IF(C12="INVAP",1,0) -> 0 | H12: 1 | I12: 1 | J12: 1 | K12: 1 | L12: 1 | M12: =SUMIFS(Data!$J$5:$J$291,Data!$E$5:$E$291,$A12,Data!$F$5:$F$291,"S1") -> 0 | N12: =SUMIFS(Data!$J$5:$J$291,Data!$E$5:$E$291,$A12,Data!$F$5:$F$291,"S2") -> 0 | O12: =SUMIFS(Data!$J$5:$J$291,Data!$E$5:$E$291,$A12,Data!$F$5:$F$291,"S3") -> 89229 | P12: =SUMIFS(Data!$J$5:$J$291,Data!$E$5:$E$291,$A12,Data!$F$5:$F$291,"S4") -> 107835.52 | Q12: =SUMIFS(Data!$J$5:$J$291,Data!$E$5:$E$291,$A12,Data!$F$5:$F$291,"S5") -> 0 | R12: =SUMIFS(Data!$J$5:$J$291,Data!$E$5:$E$291,$A12,Data!$F$5:$F$291,"S6") -> 0 | S12: =SUMIFS(Data!$J$5:$J$291,Data!$E$5:$E$291,$A12,Data!$F$5:$F$291,"S7") -> 0 | T12: =SUMIFS(Data!$H$5:$H$291,Data!$E$5:$E$291,$A12,Data!$F$5:$F$291,"S1") -> 0 | U12: =SUMIFS(Data!$H$5:$H$291,Data!$E$5:$E$291,$A12,Data!$F$5:$F$291,"S2") -> 0 | V12: =SUMIFS(Data!$H$5:$H$291,Data!$E$5:$E$291,$A12,Data!$F$5:$F$291,"S3") -> 385 | W12: =SUMIFS(Data!$H$5:$H$291,Data!$E$5:$E$291,$A12,Data!$F$5:$F$291,"S4") -> 465 | X12: =SUMIFS(Data!$H$5:$H$291,Data!$E$5:$E$291,$A12,Data!$F$5:$F$291,"S5") -> 0 | Y12: =SUMIFS(Data!$H$5:$H$291,Data!$E$5:$E$291,$A12,Data!$F$5:$F$291,"S6") -> 0 | Z12: =SUMIFS(Data!$H$5:$H$291,Data!$E$5:$E$291,$A12,Data!$F$5:$F$291,"S7") -> 0 | AA12: =M12+N12+O12 -> 89229 | AB12: =P12+Q12 -> 107835.52 | AC12: =R12+S12 -> 0 | AD12: =M12+N12+O12+P12+Q12 -> 197064.52 | AE12: =M12+N12+O12+P12+Q12+R12+S12 -> 197064.52
A13: S22 | B13: Radiological Shielding Assessment | C13: IDOM | D13: Other | E13: =IF(C13="IDOM",1,IF(C13="Shared",1-Assumptions!$C$14,0)) -> 1 | F13: =IF(C13="Plan Safe",1,IF(C13="Shared",Assumptions!$C$14,0)) -> 0 | G13: =IF(C13="INVAP",1,0) -> 0 | H13: 1 | I13: 1 | J13: 1 | K13: 1 | L13: 1 | M13: =SUMIFS(Data!$J$5:$J$291,Data!$E$5:$E$291,$A13,Data!$F$5:$F$291,"S1") -> 0 | N13: =SUMIFS(Data!$J$5:$J$291,Data!$E$5:$E$291,$A13,Data!$F$5:$F$291,"S2") -> 0 | O13: =SUMIFS(Data!$J$5:$J$291,Data!$E$5:$E$291,$A13,Data!$F$5:$F$291,"S3") -> 155044.58 | P13: =SUMIFS(Data!$J$5:$J$291,Data!$E$5:$E$291,$A13,Data!$F$5:$F$291,"S4") -> 298608.45 | Q13: =SUMIFS(Data!$J$5:$J$291,Data!$E$5:$E$291,$A13,Data!$F$5:$F$291,"S5") -> 0 | R13: =SUMIFS(Data!$J$5:$J$291,Data!$E$5:$E$291,$A13,Data!$F$5:$F$291,"S6") -> 0 | S13: =SUMIFS(Data!$J$5:$J$291,Data!$E$5:$E$291,$A13,Data!$F$5:$F$291,"S7") -> 0 | T13: =SUMIFS(Data!$H$5:$H$291,Data!$E$5:$E$291,$A13,Data!$F$5:$F$291,"S1") -> 0 | U13: =SUMIFS(Data!$H$5:$H$291,Data!$E$5:$E$291,$A13,Data!$F$5:$F$291,"S2") -> 0 | V13: =SUMIFS(Data!$H$5:$H$291,Data!$E$5:$E$291,$A13,Data!$F$5:$F$291,"S3") -> 675 | W13: =SUMIFS(Data!$H$5:$H$291,Data!$E$5:$E$291,$A13,Data!$F$5:$F$291,"S4") -> 1300 | X13: =SUMIFS(Data!$H$5:$H$291,Data!$E$5:$E$291,$A13,Data!$F$5:$F$291,"S5") -> 0 | Y13: =SUMIFS(Data!$H$5:$H$291,Data!$E$5:$E$291,$A13,Data!$F$5:$F$291,"S6") -> 0 | Z13: =SUMIFS(Data!$H$5:$H$291,Data!$E$5:$E$291,$A13,Data!$F$5:$F$291,"S7") -> 0 | AA13: =M13+N13+O13 -> 155044.58 | AB13: =P13+Q13 -> 298608.45 | AC13: =R13+S13 -> 0 | AD13: =M13+N13+O13+P13+Q13 -> 453653.03 | AE13: =M13+N13+O13+P13+Q13+R13+S13 -> 453653.03
A14: S23 | B14: Radiological Contamination Control Strategy | C14: Shared | D14: Other | E14: =IF(C14="IDOM",1,IF(C14="Shared",1-Assumptions!$C$14,0)) -> 0.9 | F14: =IF(C14="Plan Safe",1,IF(C14="Shared",Assumptions!$C$14,0)) -> 0.1 | G14: =IF(C14="INVAP",1,0) -> 0 | H14: 1 | I14: 1 | J14: 1 | K14: 1 | L14: 1 | M14: =SUMIFS(Data!$J$5:$J$291,Data!$E$5:$E$291,$A14,Data!$F$5:$F$291,"S1") -> 0 | N14: =SUMIFS(Data!$J$5:$J$291,Data!$E$5:$E$291,$A14,Data!$F$5:$F$291,"S2") -> 0 | O14: =SUMIFS(Data!$J$5:$J$291,Data!$E$5:$E$291,$A14,Data!$F$5:$F$291,"S3") -> 110536.65 | P14: =SUMIFS(Data!$J$5:$J$291,Data!$E$5:$E$291,$A14,Data!$F$5:$F$291,"S4") -> 154383.08 | Q14: =SUMIFS(Data!$J$5:$J$291,Data!$E$5:$E$291,$A14,Data!$F$5:$F$291,"S5") -> 0 | R14: =SUMIFS(Data!$J$5:$J$291,Data!$E$5:$E$291,$A14,Data!$F$5:$F$291,"S6") -> 0 | S14: =SUMIFS(Data!$J$5:$J$291,Data!$E$5:$E$291,$A14,Data!$F$5:$F$291,"S7") -> 0 | T14: =SUMIFS(Data!$H$5:$H$291,Data!$E$5:$E$291,$A14,Data!$F$5:$F$291,"S1") -> 0 | U14: =SUMIFS(Data!$H$5:$H$291,Data!$E$5:$E$291,$A14,Data!$F$5:$F$291,"S2") -> 0 | V14: =SUMIFS(Data!$H$5:$H$291,Data!$E$5:$E$291,$A14,Data!$F$5:$F$291,"S3") -> 480 | W14: =SUMIFS(Data!$H$5:$H$291,Data!$E$5:$E$291,$A14,Data!$F$5:$F$291,"S4") -> 670 | X14: =SUMIFS(Data!$H$5:$H$291,Data!$E$5:$E$291,$A14,Data!$F$5:$F$291,"S5") -> 0 | Y14: =SUMIFS(Data!$H$5:$H$291,Data!$E$5:$E$291,$A14,Data!$F$5:$F$291,"S6") -> 0 | Z14: =SUMIFS(Data!$H$5:$H$291,Data!$E$5:$E$291,$A14,Data!$F$5:$F$291,"S7") -> 0 | AA14: =M14+N14+O14 -> 110536.65 | AB14: =P14+Q14 -> 154383.08 | AC14: =R14+S14 -> 0 | AD14: =M14+N14+O14+P14+Q14 -> 264919.72 | AE14: =M14+N14+O14+P14+Q14+R14+S14 -> 264919.72
A15: S24 | B15: Radiological Classification of Areas (RCA) | C15: IDOM | D15: Other | E15: =IF(C15="IDOM",1,IF(C15="Shared",1-Assumptions!$C$14,0)) -> 1 | F15: =IF(C15="Plan Safe",1,IF(C15="Shared",Assumptions!$C$14,0)) -> 0 | G15: =IF(C15="INVAP",1,0) -> 0 | H15: 1 | I15: 1 | J15: 1 | K15: 1 | L15: 1 | M15: =SUMIFS(Data!$J$5:$J$291,Data!$E$5:$E$291,$A15,Data!$F$5:$F$291,"S1") -> 0 | N15: =SUMIFS(Data!$J$5:$J$291,Data!$E$5:$E$291,$A15,Data!$F$5:$F$291,"S2") -> 64455.825 | O15: =SUMIFS(Data!$J$5:$J$291,Data!$E$5:$E$291,$A15,Data!$F$5:$F$291,"S3") -> 112300.65 | P15: =SUMIFS(Data!$J$5:$J$291,Data!$E$5:$E$291,$A15,Data!$F$5:$F$291,"S4") -> 159322.27 | Q15: =SUMIFS(Data!$J$5:$J$291,Data!$E$5:$E$291,$A15,Data!$F$5:$F$291,"S5") -> 0 | R15: =SUMIFS(Data!$J$5:$J$291,Data!$E$5:$E$291,$A15,Data!$F$5:$F$291,"S6") -> 0 | S15: =SUMIFS(Data!$J$5:$J$291,Data!$E$5:$E$291,$A15,Data!$F$5:$F$291,"S7") -> 0 | T15: =SUMIFS(Data!$H$5:$H$291,Data!$E$5:$E$291,$A15,Data!$F$5:$F$291,"S1") -> 0 | U15: =SUMIFS(Data!$H$5:$H$291,Data!$E$5:$E$291,$A15,Data!$F$5:$F$291,"S2") -> 280 | V15: =SUMIFS(Data!$H$5:$H$291,Data!$E$5:$E$291,$A15,Data!$F$5:$F$291,"S3") -> 490 | W15: =SUMIFS(Data!$H$5:$H$291,Data!$E$5:$E$291,$A15,Data!$F$5:$F$291,"S4") -> 695 | X15: =SUMIFS(Data!$H$5:$H$291,Data!$E$5:$E$291,$A15,Data!$F$5:$F$291,"S5") -> 0 | Y15: =SUMIFS(Data!$H$5:$H$291,Data!$E$5:$E$291,$A15,Data!$F$5:$F$291,"S6") -> 0 | Z15: =SUMIFS(Data!$H$5:$H$291,Data!$E$5:$E$291,$A15,Data!$F$5:$F$291,"S7") -> 0 | AA15: =M15+N15+O15 -> 176756.48 | AB15: =P15+Q15 -> 159322.27 | AC15: =R15+S15 -> 0 | AD15: =M15+N15+O15+P15+Q15 -> 336078.75 | AE15: =M15+N15+O15+P15+Q15+R15+S15 -> 336078.75
A16: S25 | B16: Radiation Dose Assessment /Normal) Operations Dose Assessment | C16: IDOM | D16: Other | E16: =IF(C16="IDOM",1,IF(C16="Shared",1-Assumptions!$C$14,0)) -> 1 | F16: =IF(C16="Plan Safe",1,IF(C16="Shared",Assumptions!$C$14,0)) -> 0 | G16: =IF(C16="INVAP",1,0) -> 0 | H16: 1 | I16: 1 | J16: 1 | K16: 1 | L16: 1 | M16: =SUMIFS(Data!$J$5:$J$291,Data!$E$5:$E$291,$A16,Data!$F$5:$F$291,"S1") -> 0 | N16: =SUMIFS(Data!$J$5:$J$291,Data!$E$5:$E$291,$A16,Data!$F$5:$F$291,"S2") -> 0 | O16: =SUMIFS(Data!$J$5:$J$291,Data!$E$5:$E$291,$A16,Data!$F$5:$F$291,"S3") -> 0 | P16: =SUMIFS(Data!$J$5:$J$291,Data!$E$5:$E$291,$A16,Data!$F$5:$F$291,"S4") -> 152615.4 | Q16: =SUMIFS(Data!$J$5:$J$291,Data!$E$5:$E$291,$A16,Data!$F$5:$F$291,"S5") -> 0 | R16: =SUMIFS(Data!$J$5:$J$291,Data!$E$5:$E$291,$A16,Data!$F$5:$F$291,"S6") -> 0 | S16: =SUMIFS(Data!$J$5:$J$291,Data!$E$5:$E$291,$A16,Data!$F$5:$F$291,"S7") -> 0 | T16: =SUMIFS(Data!$H$5:$H$291,Data!$E$5:$E$291,$A16,Data!$F$5:$F$291,"S1") -> 0 | U16: =SUMIFS(Data!$H$5:$H$291,Data!$E$5:$E$291,$A16,Data!$F$5:$F$291,"S2") -> 0 | V16: =SUMIFS(Data!$H$5:$H$291,Data!$E$5:$E$291,$A16,Data!$F$5:$F$291,"S3") -> 0 | W16: =SUMIFS(Data!$H$5:$H$291,Data!$E$5:$E$291,$A16,Data!$F$5:$F$291,"S4") -> 665 | X16: =SUMIFS(Data!$H$5:$H$291,Data!$E$5:$E$291,$A16,Data!$F$5:$F$291,"S5") -> 0 | Y16: =SUMIFS(Data!$H$5:$H$291,Data!$E$5:$E$291,$A16,Data!$F$5:$F$291,"S6") -> 0 | Z16: =SUMIFS(Data!$H$5:$H$291,Data!$E$5:$E$291,$A16,Data!$F$5:$F$291,"S7") -> 0 | AA16: =M16+N16+O16 -> 0 | AB16: =P16+Q16 -> 152615.4 | AC16: =R16+S16 -> 0 | AD16: =M16+N16+O16+P16+Q16 -> 152615.4 | AE16: =M16+N16+O16+P16+Q16+R16+S16 -> 152615.4
... A24: S38 | B24: Radiological Stack Monitoring Protocol | C24: Shared | D24: Other | E24: =IF(C24="IDOM",1,IF(C24="Shared",1-Assumptions!$C$14,0)) -> 0.9 | F24: =IF(C24="Plan Safe",1,IF(C24="Shared",Assumptions!$C$14,0)) -> 0.1 | G24: =IF(C24="INVAP",1,0) -> 0 | H24: 1 | I24: 1 | J24: 1 | K24: 1 | L24: 1 | M24: =SUMIFS(Data!$J$5:$J$291,Data!$E$5:$E$291,$A24,Data!$F$5:$F$291,"S1") -> 0 | N24: =SUMIFS(Data!$J$5:$J$291,Data!$E$5:$E$291,$A24,Data!$F$5:$F$291,"S2") -> 0 | O24: =SUMIFS(Data!$J$5:$J$291,Data!$E$5:$E$291,$A24,Data!$F$5:$F$291,"S3") -> 0 | P24: =SUMIFS(Data!$J$5:$J$291,Data!$E$5:$E$291,$A24,Data!$F$5:$F$291,"S4") -> 0 | Q24: =SUMIFS(Data!$J$5:$J$291,Data!$E$5:$E$291,$A24,Data!$F$5:$F$291,"S5") -> 103524.75 | R24: =SUMIFS(Data!$J$5:$J$291,Data!$E$5:$E$291,$A24,Data!$F$5:$F$291,"S6") -> 77678.475 | S24: =SUMIFS(Data!$J$5:$J$291,Data!$E$5:$E$291,$A24,Data!$F$5:$F$291,"S7") -> 51314.025 | T24: =SUMIFS(Data!$H$5:$H$291,Data!$E$5:$E$291,$A24,Data!$F$5:$F$291,"S1") -> 0 | U24: =SUMIFS(Data!$H$5:$H$291,Data!$E$5:$E$291,$A24,Data!$F$5:$F$291,"S2") -> 0 | V24: =SUMIFS(Data!$H$5:$H$291,Data!$E$5:$E$291,$A24,Data!$F$5:$F$291,"S3") -> 0 | W24: =SUMIFS(Data!$H$5:$H$291,Data!$E$5:$E$291,$A24,Data!$F$5:$F$291,"S4") -> 0 | X24: =SUMIFS(Data!$H$5:$H$291,Data!$E$5:$E$291,$A24,Data!$F$5:$F$291,"S5") -> 450 | Y24: =SUMIFS(Data!$H$5:$H$291,Data!$E$5:$E$291,$A24,Data!$F$5:$F$291,"S6") -> 340 | Z24: =SUMIFS(Data!$H$5:$H$291,Data!$E$5:$E$291,$A24,Data!$F$5:$F$291,"S7") -> 225 | AA24: =M24+N24+O24 -> 0 | AB24: =P24+Q24 -> 103524.75 | AC24: =R24+S24 -> 128992.5 | AD24: =M24+N24+O24+P24+Q24 -> 103524.75 | AE24: =M24+N24+O24+P24+Q24+R24+S24 -> 232517.25
A25: Pre | B25: Conceptual Design Verification | C25: INVAP | D25: INVAP | E25: =IF(C25="IDOM",1,IF(C25="Shared",1-Assumptions!$C$14,0)) -> 0 | F25: =IF(C25="Plan Safe",1,IF(C25="Shared",Assumptions!$C$14,0)) -> 0 | G25: =IF(C25="INVAP",1,0) -> 1 | H25: =IF(Assumptions!$C$9="Yes",1,0) -> 1 | I25: =IF(Assumptions!$C$9="Yes",1,0) -> 1 | J25: =IF(Assumptions!$C$9="Yes",1,0) -> 1 | K25: =IF(Assumptions!$C$9="Yes",1,0) -> 1 | L25: =IF(Assumptions!$C$9="Yes",1,0) -> 1 | M25: =SUMIFS(Data!$J$5:$J$291,Data!$E$5:$E$291,$A25,Data!$F$5:$F$291,"S1") -> 78836.1 | N25: =SUMIFS(Data!$J$5:$J$291,Data!$E$5:$E$291,$A25,Data!$F$5:$F$291,"S2") -> 0 | O25: =SUMIFS(Data!$J$5:$J$291,Data!$E$5:$E$291,$A25,Data!$F$5:$F$291,"S3") -> 0 | P25: =SUMIFS(Data!$J$5:$J$291,Data!$E$5:$E$291,$A25,Data!$F$5:$F$291,"S4") -> 0 | Q25: =SUMIFS(Data!$J$5:$J$291,Data!$E$5:$E$291,$A25,Data!$F$5:$F$291,"S5") -> 0 | R25: =SUMIFS(Data!$J$5:$J$291,Data!$E$5:$E$291,$A25,Data!$F$5:$F$291,"S6") -> 0 | S25: =SUMIFS(Data!$J$5:$J$291,Data!$E$5:$E$291,$A25,Data!$F$5:$F$291,"S7") -> 0 | T25: =SUMIFS(Data!$H$5:$H$291,Data!$E$5:$E$291,$A25,Data!$F$5:$F$291,"S1") -> 345 | U25: =SUMIFS(Data!$H$5:$H$291,Data!$E$5:$E$291,$A25,Data!$F$5:$F$291,"S2") -> 0 | V25: =SUMIFS(Data!$H$5:$H$291,Data!$E$5:$E$291,$A25,Data!$F$5:$F$291,"S3") -> 0 | W25: =SUMIFS(Data!$H$5:$H$291,Data!$E$5:$E$291,$A25,Data!$F$5:$F$291,"S4") -> 0 | X25: =SUMIFS(Data!$H$5:$H$291,Data!$E$5:$E$291,$A25,Data!$F$5:$F$291,"S5") -> 0 | Y25: =SUMIFS(Data!$H$5:$H$291,Data!$E$5:$E$291,$A25,Data!$F$5:$F$291,"S6") -> 0 | Z25: =SUMIFS(Data!$H$5:$H$291,Data!$E$5:$E$291,$A25,Data!$F$5:$F$291,"S7") -> 0 | AA25: =M25+N25+O25 -> 78836.1 | AB25: =P25+Q25 -> 0 | AC25: =R25+S25 -> 0 | AD25: =M25+N25+O25+P25+Q25 -> 78836.1 | AE25: =M25+N25+O25+P25+Q25+R25+S25 -> 78836.1
A26: S2 | B26: Human Factors Assurance Plan / Human Factors Integration Plan (HFIP) | C26: Plan Safe | D26: Plan Safe task | E26: =IF(C26="IDOM",1,IF(C26="Shared",1-Assumptions!$C$14,0)) -> 0 | F26: =IF(C26="Plan Safe",1,IF(C26="Shared",Assumptions!$C$14,0)) -> 1 | G26: =IF(C26="INVAP",1,0) -> 0 | H26: 1 | I26: 0 | J26: 0 | K26: =Assumptions!$C$15 -> 0.5 | L26: 1 | M26: =SUMIFS(Data!$J$5:$J$291,Data!$E$5:$E$291,$A26,Data!$F$5:$F$291,"S1") -> 62875.575 | N26: =SUMIFS(Data!$J$5:$J$291,Data!$E$5:$E$291,$A26,Data!$F$5:$F$291,"S2") -> 88244.1 | O26: =SUMIFS(Data!$J$5:$J$291,Data!$E$5:$E$291,$A26,Data!$F$5:$F$291,"S3") -> 0 | P26: =SUMIFS(Data!$J$5:$J$291,Data!$E$5:$E$291,$A26,Data!$F$5:$F$291,"S4") -> 0 | Q26: =SUMIFS(Data!$J$5:$J$291,Data!$E$5:$E$291,$A26,Data!$F$5:$F$291,"S5") -> 0 | R26: =SUMIFS(Data!$J$5:$J$291,Data!$E$5:$E$291,$A26,Data!$F$5:$F$291,"S6") -> 0 | S26: =SUMIFS(Data!$J$5:$J$291,Data!$E$5:$E$291,$A26,Data!$F$5:$F$291,"S7") -> 0 | T26: =SUMIFS(Data!$H$5:$H$291,Data!$E$5:$E$291,$A26,Data!$F$5:$F$291,"S1") -> 270 | U26: =SUMIFS(Data!$H$5:$H$291,Data!$E$5:$E$291,$A26,Data!$F$5:$F$291,"S2") -> 380 | V26: =SUMIFS(Data!$H$5:$H$291,Data!$E$5:$E$291,$A26,Data!$F$5:$F$291,"S3") -> 0 | W26: =SUMIFS(Data!$H$5:$H$291,Data!$E$5:$E$291,$A26,Data!$F$5:$F$291,"S4") -> 0 | X26: =SUMIFS(Data!$H$5:$H$291,Data!$E$5:$E$291,$A26,Data!$F$5:$F$291,"S5") -> 0 | Y26: =SUMIFS(Data!$H$5:$H$291,Data!$E$5:$E$291,$A26,Data!$F$5:$F$291,"S6") -> 0 | Z26: =SUMIFS(Data!$H$5:$H$291,Data!$E$5:$E$291,$A26,Data!$F$5:$F$291,"S7") -> 0 | AA26: =M26+N26+O26 -> 151119.67 | AB26: =P26+Q26 -> 0 | AC26: =R26+S26 -> 0 | AD26: =M26+N26+O26+P26+Q26 -> 151119.67 | AE26: =M26+N26+O26+P26+Q26+R26+S26 -> 151119.67
A27: S3 | B27: Human Factors Hazards Identification and Control Plan (HFHICP) | C27: Plan Safe | D27: Plan Safe task | E27: =IF(C27="IDOM",1,IF(C27="Shared",1-Assumptions!$C$14,0)) -> 0 | F27: =IF(C27="Plan Safe",1,IF(C27="Shared",Assumptions!$C$14,0)) -> 1 | G27: =IF(C27="INVAP",1,0) -> 0 | H27: 1 | I27: 0 | J27: 0 | K27: =Assumptions!$C$15 -> 0.5 | L27: 1 | M27: =SUMIFS(Data!$J$5:$J$291,Data!$E$5:$E$291,$A27,Data!$F$5:$F$291,"S1") -> 45191.475 | N27: =SUMIFS(Data!$J$5:$J$291,Data!$E$5:$E$291,$A27,Data!$F$5:$F$291,"S2") -> 70622.475 | O27: =SUMIFS(Data!$J$5:$J$291,Data!$E$5:$E$291,$A27,Data!$F$5:$F$291,"S3") -> 124531.05 | P27: =SUMIFS(Data!$J$5:$J$291,Data!$E$5:$E$291,$A27,Data!$F$5:$F$291,"S4") -> 145416.08 | Q27: =SUMIFS(Data!$J$5:$J$291,Data!$E$5:$E$291,$A27,Data!$F$5:$F$291,"S5") -> 63195.3 | R27: =SUMIFS(Data!$J$5:$J$291,Data!$E$5:$E$291,$A27,Data!$F$5:$F$291,"S6") -> 65411.325 | S27: =SUMIFS(Data!$J$5:$J$291,Data!$E$5:$E$291,$A27,Data!$F$5:$F$291,"S7") -> 0 | T27: =SUMIFS(Data!$H$5:$H$291,Data!$E$5:$E$291,$A27,Data!$F$5:$F$291,"S1") -> 195 | U27: =SUMIFS(Data!$H$5:$H$291,Data!$E$5:$E$291,$A27,Data!$F$5:$F$291,"S2") -> 305 | V27: =SUMIFS(Data!$H$5:$H$291,Data!$E$5:$E$291,$A27,Data!$F$5:$F$291,"S3") -> 540 | W27: =SUMIFS(Data!$H$5:$H$291,Data!$E$5:$E$291,$A27,Data!$F$5:$F$291,"S4") -> 630 | X27: =SUMIFS(Data!$H$5:$H$291,Data!$E$5:$E$291,$A27,Data!$F$5:$F$291,"S5") -> 275 | Y27: =SUMIFS(Data!$H$5:$H$291,Data!$E$5:$E$291,$A27,Data!$F$5:$F$291,"S6") -> 285 | Z27: =SUMIFS(Data!$H$5:$H$291,Data!$E$5:$E$291,$A27,Data!$F$5:$F$291,"S7") -> 0 | AA27: =M27+N27+O27 -> 240345 | AB27: =P27+Q27 -> 208611.38 | AC27: =R27+S27 -> 65411.325 | AD27: =M27+N27+O27+P27+Q27 -> 448956.38 | AE27: =M27+N27+O27+P27+Q27+R27+S27 -> 514367.7
A28: S8 | B28: Human Factor Task Assessments | C28: Plan Safe | D28: Plan Safe task | E28: =IF(C28="IDOM",1,IF(C28="Shared",1-Assumptions!$C$14,0)) -> 0 | F28: =IF(C28="Plan Safe",1,IF(C28="Shared",Assumptions!$C$14,0)) -> 1 | G28: =IF(C28="INVAP",1,0) -> 0 | H28: 1 | I28: 0 | J28: 0 | K28: =Assumptions!$C$15 -> 0.5 | L28: 1 | M28: =SUMIFS(Data!$J$5:$J$291,Data!$E$5:$E$291,$A28,Data!$F$5:$F$291,"S1") -> 0 | N28: =SUMIFS(Data!$J$5:$J$291,Data!$E$5:$E$291,$A28,Data!$F$5:$F$291,"S2") -> 0 | O28: =SUMIFS(Data!$J$5:$J$291,Data!$E$5:$E$291,$A28,Data!$F$5:$F$291,"S3") -> 0 | P28: =SUMIFS(Data!$J$5:$J$291,Data!$E$5:$E$291,$A28,Data!$F$5:$F$291,"S4") -> 135672.18 | Q28: =SUMIFS(Data!$J$5:$J$291,Data!$E$5:$E$291,$A28,Data!$F$5:$F$291,"S5") -> 0 | R28: =SUMIFS(Data!$J$5:$J$291,Data!$E$5:$E$291,$A28,Data!$F$5:$F$291,"S6") -> 0 | S28: =SUMIFS(Data!$J$5:$J$291,Data!$E$5:$E$291,$A28,Data!$F$5:$F$291,"S7") -> 0 | T28: =SUMIFS(Data!$H$5:$H$291,Data!$E$5:$E$291,$A28,Data!$F$5:$F$291,"S1") -> 0 | U28: =SUMIFS(Data!$H$5:$H$291,Data!$E$5:$E$291,$A28,Data!$F$5:$F$291,"S2") -> 0 | V28: =SUMIFS(Data!$H$5:$H$291,Data!$E$5:$E$291,$A28,Data!$F$5:$F$291,"S3") -> 0 | W28: =SUMIFS(Data!$H$5:$H$291,Data!$E$5:$E$291,$A28,Data!$F$5:$F$291,"S4") -> 597 | X28: =SUMIFS(Data!$H$5:$H$291,Data!$E$5:$E$291,$A28,Data!$F$5:$F$291,"S5") -> 0 | Y28: =SUMIFS(Data!$H$5:$H$291,Data!$E$5:$E$291,$A28,Data!$F$5:$F$291,"S6") -> 0 | Z28: =SUMIFS(Data!$H$5:$H$291,Data!$E$5:$E$291,$A28,Data!$F$5:$F$291,"S7") -> 0 | AA28: =M28+N28+O28 -> 0 | AB28: =P28+Q28 -> 135672.18 | AC28: =R28+S28 -> 0 | AD28: =M28+N28+O28+P28+Q28 -> 135672.18 | AE28: =M28+N28+O28+P28+Q28+R28+S28 -> 135672.18
A29: S30 | B29: Human Factors Substantiation/Assurance Report | C29: Plan Safe | D29: Plan Safe task | E29: =IF(C29="IDOM",1,IF(C29="Shared",1-Assumptions!$C$14,0)) -> 0 | F29: =IF(C29="Plan Safe",1,IF(C29="Shared",Assumptions!$C$14,0)) -> 1 | G29: =IF(C29="INVAP",1,0) -> 0 | H29: 1 | I29: 0 | J29: 0 | K29: =Assumptions!$C$15 -> 0.5 | L29: 1 | M29: =SUMIFS(Data!$J$5:$J$291,Data!$E$5:$E$291,$A29,Data!$F$5:$F$291,"S1") -> 0 | N29: =SUMIFS(Data!$J$5:$J$291,Data!$E$5:$E$291,$A29,Data!$F$5:$F$291,"S2") -> 0 | O29: =SUMIFS(Data!$J$5:$J$291,Data!$E$5:$E$291,$A29,Data!$F$5:$F$291,"S3") -> 65275.35 | P29: =SUMIFS(Data!$J$5:$J$291,Data!$E$5:$E$291,$A29,Data!$F$5:$F$291,"S4") -> 152016.38 | Q29: =SUMIFS(Data!$J$5:$J$291,Data!$E$5:$E$291,$A29,Data!$F$5:$F$291,"S5") -> 65337.825 | R29: =SUMIFS(Data!$J$5:$J$291,Data!$E$5:$E$291,$A29,Data!$F$5:$F$291,"S6") -> 81478.425 | S29: =SUMIFS(Data!$J$5:$J$291,Data!$E$5:$E$291,$A29,Data!$F$5:$F$291,"S7") -> 56448 | T29: =SUMIFS(Data!$H$5:$H$291,Data!$E$5:$E$291,$A29,Data!$F$5:$F$291,"S1") -> 0 | U29: =SUMIFS(Data!$H$5:$H$291,Data!$E$5:$E$291,$A29,Data!$F$5:$F$291,"S2") -> 0 | V29: =SUMIFS(Data!$H$5:$H$291,Data!$E$5:$E$291,$A29,Data!$F$5:$F$291,"S3") -> 285 | W29: =SUMIFS(Data!$H$5:$H$291,Data!$E$5:$E$291,$A29,Data!$F$5:$F$291,"S4") -> 660 | X29: =SUMIFS(Data!$H$5:$H$291,Data!$E$5:$E$291,$A29,Data!$F$5:$F$291,"S5") -> 285 | Y29: =SUMIFS(Data!$H$5:$H$291,Data!$E$5:$E$291,$A29,Data!$F$5:$F$291,"S6") -> 355 | Z29: =SUMIFS(Data!$H$5:$H$291,Data!$E$5:$E$291,$A29,Data!$F$5:$F$291,"S7") -> 245 | AA29: =M29+N29+O29 -> 65275.35 | AB29: =P29+Q29 -> 217354.2 | AC29: =R29+S29 -> 137926.42 | AD29: =M29+N29+O29+P29+Q29 -> 282629.55 | AE29: =M29+N29+O29+P29+Q29+R29+S29 -> 420555.97
A33: Original offer (reference, no adjustments) | M33: S1 | N33: S2 | O33: S3 | P33: S4 | Q33: S5 | R33: S6 | S33: S7 | T33: Total
B34: IDOM – deliverables | M34: =SUMPRODUCT(M$5:M$29,E$5:E$29) -> 133361.71 | N34: =SUMPRODUCT(N$5:N$29,E$5:E$29) -> 536515.09 | O34: =SUMPRODUCT(O$5:O$29,E$5:E$29) -> 1212914.3 | P34: =SUMPRODUCT(P$5:P$29,E$5:E$29) -> 2599061.4 | Q34: =SUMPRODUCT(Q$5:Q$29,E$5:E$29) -> 380134.65 | R34: =SUMPRODUCT(R$5:R$29,E$5:E$29) -> 584012.26 | S34: =SUMPRODUCT(S$5:S$29,E$5:E$29) -> 412218.5 | T34: =SUM(M34:S34) -> 5858217.9
B35: Plan Safe – deliverables | M35: =SUMPRODUCT(M$5:M$29,F$5:F$29) -> 122885.02 | N35: =SUMPRODUCT(N$5:N$29,F$5:F$29) -> 196324.01 | O35: =SUMPRODUCT(O$5:O$29,F$5:F$29) -> 256409.53 | P35: =SUMPRODUCT(P$5:P$29,F$5:F$29) -> 584821.12 | Q35: =SUMPRODUCT(Q$5:Q$29,F$5:F$29) -> 160476.23 | R35: =SUMPRODUCT(R$5:R$29,F$5:F$29) -> 191067.29 | S35: =SUMPRODUCT(S$5:S$29,F$5:F$29) -> 81686.798 | T35: =SUM(M35:S35) -> 1593670
B36: INVAP – deliverables | M36: =SUMPRODUCT(M$5:M$29,G$5:G$29) -> 78836.1 | N36: =SUMPRODUCT(N$5:N$29,G$5:G$29) -> 0 | O36: =SUMPRODUCT(O$5:O$29,G$5:G$29) -> 0 | P36: =SUMPRODUCT(P$5:P$29,G$5:G$29) -> 0 | Q36: =SUMPRODUCT(Q$5:Q$29,G$5:G$29) -> 0 | R36: =SUMPRODUCT(R$5:R$29,G$5:G$29) -> 0 | S36: =SUMPRODUCT(S$5:S$29,G$5:G$29) -> 0 | T36: =SUM(M36:S36) -> 78836.1
B37: IDOM – deliverable S1 option | M37: 0 | N37: 0 | O37: 0 | P37: 0 | Q37: 0 | R37: 0 | S37: 0 | T37: =SUM(M37:S37) -> 0
B38: Plan Safe – deliverable S1 option | M38: 0 | N38: 0 | O38: 0 | P38: 0 | Q38: 0 | R38: 0 | S38: 0 | T38: =SUM(M38:S38) -> 0
B39: IDOM – Stage 2 rework release | M39: 0 | N39: 0 | O39: 0 | P39: 0 | Q39: 0 | R39: 0 | S39: 0 | T39: =SUM(M39:S39) -> 0
B40: IDOM – commercial discount | M40: 0 | N40: 0 | O40: 0 | P40: 0 | Q40: 0 | R40: 0 | S40: 0 | T40: =SUM(M40:S40) -> 0
B41: IDOM – net | M41: =M34+M37+M39+M40 -> 133361.71 | N41: =N34+N37+N39+N40 -> 536515.09 | O41: =O34+O37+O39+O40 -> 1212914.3 | P41: =P34+P37+P39+P40 -> 2599061.4 | Q41: =Q34+Q37+Q39+Q40 -> 380134.65 | R41: =R34+R37+R39+R40 -> 584012.26 | S41: =S34+S37+S39+S40 -> 412218.5 | T41: =SUM(M41:S41) -> 5858217.9
B42: Plan Safe – net | M42: =M35+M38 -> 122885.02 | N42: =N35+N38 -> 196324.01 | O42: =O35+O38 -> 256409.53 | P42: =P35+P38 -> 584821.12 | Q42: =Q35+Q38 -> 160476.23 | R42: =R35+R38 -> 191067.29 | S42: =S35+S38 -> 81686.798 | T42: =SUM(M42:S42) -> 1593670
B43: INVAP – net | M43: =M36 -> 78836.1 | N43: =N36 -> 0 | O43: =O36 -> 0 | P43: =P36 -> 0 | Q43: =Q36 -> 0 | R43: =R36 -> 0 | S43: =S36 -> 0 | T43: =SUM(M43:S43) -> 78836.1
B44: Total price | M44: =M41+M42+M43 -> 335082.83 | N44: =N41+N42+N43 -> 732839.1 | O44: =O41+O42+O43 -> 1469323.8 | P44: =P41+P42+P43 -> 3183882.6 | Q44: =Q41+Q42+Q43 -> 540610.88 | R44: =R41+R42+R43 -> 775079.55 | S44: =S41+S42+S43 -> 493905.3 | T44: =SUM(M44:S44) -> 7530724
B45: Hours – deliverables | M45: =SUM(T$5:T$29) -> 1435 | N45: =SUM(U$5:U$29) -> 3170 | O45: =SUM(V$5:V$29) -> 6420 | P45: =SUM(W$5:W$29) -> 13842 | Q45: =SUM(X$5:X$29) -> 2355 | R45: =SUM(Y$5:Y$29) -> 3360 | S45: =SUM(Z$5:Z$29) -> 2140 | T45: =SUM(M45:S45) -> 32722
B46: Hours – deliverable S1 option | M46: 0 | N46: 0 | O46: 0 | P46: 0 | Q46: 0 | R46: 0 | S46: 0 | T46: =SUM(M46:S46) -> 0
B47: Hours – total | M47: =M45+M46 -> 1435 | N47: =N45+N46 -> 3170 | O47: =O45+O46 -> 6420 | P47: =P45+P46 -> 13842 | Q47: =Q45+Q46 -> 2355 | R47: =R45+R46 -> 3360 | S47: =S45+S46 -> 2140 | T47: =SUM(M47:S47) -> 32722
A50: Scenario 1 — Base offer | M50: S1 | N50: S2 | O50: S3 | P50: S4 | Q50: S5 | R50: S6 | S50: S7 | T50: Total
B51: IDOM – deliverables | M51: =SUMPRODUCT(M$5:M$29,H$5:H$29,E$5:E$29) -> 133361.71 | N51: =SUMPRODUCT(N$5:N$29,H$5:H$29,E$5:E$29) -> 536515.09 | O51: =SUMPRODUCT(O$5:O$29,H$5:H$29,E$5:E$29) -> 1212914.3 | P51: =SUMPRODUCT(P$5:P$29,H$5:H$29,E$5:E$29) -> 2599061.4 | Q51: =SUMPRODUCT(Q$5:Q$29,H$5:H$29,E$5:E$29) -> 380134.65 | R51: =SUMPRODUCT(R$5:R$29,H$5:H$29,E$5:E$29) -> 584012.26 | S51: =SUMPRODUCT(S$5:S$29,H$5:H$29,E$5:E$29) -> 412218.5 | T51: =SUM(M51:S51) -> 5858217.9
B52: Plan Safe – deliverables | M52: =SUMPRODUCT(M$5:M$29,H$5:H$29,F$5:F$29) -> 122885.02 | N52: =SUMPRODUCT(N$5:N$29,H$5:H$29,F$5:F$29) -> 196324.01 | O52: =SUMPRODUCT(O$5:O$29,H$5:H$29,F$5:F$29) -> 256409.53 | P52: =SUMPRODUCT(P$5:P$29,H$5:H$29,F$5:F$29) -> 584821.12 | Q52: =SUMPRODUCT(Q$5:Q$29,H$5:H$29,F$5:F$29) -> 160476.23 | R52: =SUMPRODUCT(R$5:R$29,H$5:H$29,F$5:F$29) -> 191067.29 | S52: =SUMPRODUCT(S$5:S$29,H$5:H$29,F$5:F$29) -> 81686.798 | T52: =SUM(M52:S52) -> 1593670
B53: INVAP – deliverables | M53: =SUMPRODUCT(M$5:M$29,H$5:H$29,G$5:G$29) -> 78836.1 | N53: =SUMPRODUCT(N$5:N$29,H$5:H$29,G$5:G$29) -> 0 | O53: =SUMPRODUCT(O$5:O$29,H$5:H$29,G$5:G$29) -> 0 | P53: =SUMPRODUCT(P$5:P$29,H$5:H$29,G$5:G$29) -> 0 | Q53: =SUMPRODUCT(Q$5:Q$29,H$5:H$29,G$5:G$29) -> 0 | R53: =SUMPRODUCT(R$5:R$29,H$5:H$29,G$5:G$29) -> 0 | S53: =SUMPRODUCT(S$5:S$29,H$5:H$29,G$5:G$29) -> 0 | T53: =SUM(M53:S53) -> 78836.1
B54: IDOM – deliverable S1 option | M54: =IF(Assumptions!$C$10="Yes",(IF(M$3="S1",Assumptions!$C$12*$H$6,0)-M$6*$H$6)*$E$6,0) -> 0 | N54: =IF(Assumptions!$C$10="Yes",(IF(N$3="S1",Assumptions!$C$12*$H$6,0)-N$6*$H$6)*$E$6,0) -> 0 | O54: =IF(Assumptions!$C$10="Yes",(IF(O$3="S1",Assumptions!$C$12*$H$6,0)-O$6*$H$6)*$E$6,0) -> 0 | P54: =IF(Assumptions!$C$10="Yes",(IF(P$3="S1",Assumptions!$C$12*$H$6,0)-P$6*$H$6)*$E$6,0) -> 0 | Q54: =IF(Assumptions!$C$10="Yes",(IF(Q$3="S1",Assumptions!$C$12*$H$6,0)-Q$6*$H$6)*$E$6,0) -> 0 | R54: =IF(Assumptions!$C$10="Yes",(IF(R$3="S1",Assumptions!$C$12*$H$6,0)-R$6*$H$6)*$E$6,0) -> 0 | S54: =IF(Assumptions!$C$10="Yes",(IF(S$3="S1",Assumptions!$C$12*$H$6,0)-S$6*$H$6)*$E$6,0) -> 0 | T54: =SUM(M54:S54) -> 0
B55: Plan Safe – deliverable S1 option | M55: =IF(Assumptions!$C$10="Yes",(IF(M$3="S1",Assumptions!$C$12*$H$6,0)-M$6*$H$6)*$F$6,0) -> 0 | N55: =IF(Assumptions!$C$10="Yes",(IF(N$3="S1",Assumptions!$C$12*$H$6,0)-N$6*$H$6)*$F$6,0) -> 0 | O55: =IF(Assumptions!$C$10="Yes",(IF(O$3="S1",Assumptions!$C$12*$H$6,0)-O$6*$H$6)*$F$6,0) -> 0 | P55: =IF(Assumptions!$C$10="Yes",(IF(P$3="S1",Assumptions!$C$12*$H$6,0)-P$6*$H$6)*$F$6,0) -> 0 | Q55: =IF(Assumptions!$C$10="Yes",(IF(Q$3="S1",Assumptions!$C$12*$H$6,0)-Q$6*$H$6)*$F$6,0) -> 0 | R55: =IF(Assumptions!$C$10="Yes",(IF(R$3="S1",Assumptions!$C$12*$H$6,0)-R$6*$H$6)*$F$6,0) -> 0 | S55: =IF(Assumptions!$C$10="Yes",(IF(S$3="S1",Assumptions!$C$12*$H$6,0)-S$6*$H$6)*$F$6,0) -> 0 | T55: =SUM(M55:S55) -> 0
B56: IDOM – Stage 2 rework release | M56: =IF(M$3="S2",(M51+M54)*(Assumptions!$C$6-Assumptions!$C$5)/(1+Assumptions!$C$5),0) -> 0 | N56: =IF(N$3="S2",(N51+N54)*(Assumptions!$C$6-Assumptions!$C$5)/(1+Assumptions!$C$5),0) -> -139096.5 | O56: =IF(O$3="S2",(O51+O54)*(Assumptions!$C$6-Assumptions!$C$5)/(1+Assumptions!$C$5),0) -> 0 | P56: =IF(P$3="S2",(P51+P54)*(Assumptions!$C$6-Assumptions!$C$5)/(1+Assumptions!$C$5),0) -> 0 | Q56: =IF(Q$3="S2",(Q51+Q54)*(Assumptions!$C$6-Assumptions!$C$5)/(1+Assumptions!$C$5),0) -> 0 | R56: =IF(R$3="S2",(R51+R54)*(Assumptions!$C$6-Assumptions!$C$5)/(1+Assumptions!$C$5),0) -> 0 | S56: =IF(S$3="S2",(S51+S54)*(Assumptions!$C$6-Assumptions!$C$5)/(1+Assumptions!$C$5),0) -> 0 | T56: =SUM(M56:S56) -> -139096.5
B57: IDOM – commercial discount | M57: =-Assumptions!$C$7*(M51+M54+M56) -> -5334.4683 | N57: =-Assumptions!$C$7*(N51+N54+N56) -> -15896.743 | O57: =-Assumptions!$C$7*(O51+O54+O56) -> -48516.571 | P57: =-Assumptions!$C$7*(P51+P54+P56) -> -103962.46 | Q57: =-Assumptions!$C$7*(Q51+Q54+Q56) -> -15205.386 | R57: =-Assumptions!$C$7*(R51+R54+R56) -> -23360.49 | S57: =-Assumptions!$C$7*(S51+S54+S56) -> -16488.74 | T57: =SUM(M57:S57) -> -228764.86
B58: IDOM – net | M58: =M51+M54+M56+M57 -> 128027.24 | N58: =N51+N54+N56+N57 -> 381521.84 | O58: =O51+O54+O56+O57 -> 1164397.7 | P58: =P51+P54+P56+P57 -> 2495099 | Q58: =Q51+Q54+Q56+Q57 -> 364929.26 | R58: =R51+R54+R56+R57 -> 560651.77 | S58: =S51+S54+S56+S57 -> 395729.76 | T58: =SUM(M58:S58) -> 5490356.5
B59: Plan Safe – net | M59: =M52+M55 -> 122885.02 | N59: =N52+N55 -> 196324.01 | O59: =O52+O55 -> 256409.53 | P59: =P52+P55 -> 584821.12 | Q59: =Q52+Q55 -> 160476.23 | R59: =R52+R55 -> 191067.29 | S59: =S52+S55 -> 81686.798 | T59: =SUM(M59:S59) -> 1593670
B60: INVAP – net | M60: =M53 -> 78836.1 | N60: =N53 -> 0 | O60: =O53 -> 0 | P60: =P53 -> 0 | Q60: =Q53 -> 0 | R60: =R53 -> 0 | S60: =S53 -> 0 | T60: =SUM(M60:S60) -> 78836.1
B61: Total price | M61: =M58+M59+M60 -> 329748.36 | N61: =N58+N59+N60 -> 577845.85 | O61: =O58+O59+O60 -> 1420807.2 | P61: =P58+P59+P60 -> 3079920.1 | Q61: =Q58+Q59+Q60 -> 525405.49 | R61: =R58+R59+R60 -> 751719.06 | S61: =S58+S59+S60 -> 477416.56 | T61: =SUM(M61:S61) -> 7162862.6
B62: Hours – deliverables | M62: =SUMPRODUCT(T$5:T$29*(H$5:H$29>0)) -> 1435 | N62: =SUMPRODUCT(U$5:U$29*(H$5:H$29>0)) -> 3170 | O62: =SUMPRODUCT(V$5:V$29*(H$5:H$29>0)) -> 6420 | P62: =SUMPRODUCT(W$5:W$29*(H$5:H$29>0)) -> 13842 | Q62: =SUMPRODUCT(X$5:X$29*(H$5:H$29>0)) -> 2355 | R62: =SUMPRODUCT(Y$5:Y$29*(H$5:H$29>0)) -> 3360 | S62: =SUMPRODUCT(Z$5:Z$29*(H$5:H$29>0)) -> 2140 | T62: =SUM(M62:S62) -> 32722
B63: Hours – deliverable S1 option | M63: =IF(Assumptions!$C$10="Yes",IF(M$3="S1",Assumptions!$C$11*($H$6>0),0)-T$6*($H$6>0),0) -> 0 | N63: =IF(Assumptions!$C$10="Yes",IF(N$3="S1",Assumptions!$C$11*($H$6>0),0)-U$6*($H$6>0),0) -> 0 | O63: =IF(Assumptions!$C$10="Yes",IF(O$3="S1",Assumptions!$C$11*($H$6>0),0)-V$6*($H$6>0),0) -> 0 | P63: =IF(Assumptions!$C$10="Yes",IF(P$3="S1",Assumptions!$C$11*($H$6>0),0)-W$6*($H$6>0),0) -> 0 | Q63: =IF(Assumptions!$C$10="Yes",IF(Q$3="S1",Assumptions!$C$11*($H$6>0),0)-X$6*($H$6>0),0) -> 0 | R63: =IF(Assumptions!$C$10="Yes",IF(R$3="S1",Assumptions!$C$11*($H$6>0),0)-Y$6*($H$6>0),0) -> 0 | S63: =IF(Assumptions!$C$10="Yes",IF(S$3="S1",Assumptions!$C$11*($H$6>0),0)-Z$6*($H$6>0),0) -> 0 | T63: =SUM(M63:S63) -> 0
B64: Hours – total | M64: =M62+M63 -> 1435 | N64: =N62+N63 -> 3170 | O64: =O62+O63 -> 6420 | P64: =P62+P63 -> 13842 | Q64: =Q62+Q63 -> 2355 | R64: =R62+R63 -> 3360 | S64: =S62+S63 -> 2140 | T64: =SUM(M64:S64) -> 32722
A67: Scenario 2 — Without Plan Safe HF tasks | M67: S1 | N67: S2 | O67: S3 | P67: S4 | Q67: S5 | R67: S6 | S67: S7 | T67: Total
B68: IDOM – deliverables | M68: =SUMPRODUCT(M$5:M$29,I$5:I$29,E$5:E$29) -> 133361.71 | N68: =SUMPRODUCT(N$5:N$29,I$5:I$29,E$5:E$29) -> 536515.09 | O68: =SUMPRODUCT(O$5:O$29,I$5:I$29,E$5:E$29) -> 1212914.3 | P68: =SUMPRODUCT(P$5:P$29,I$5:I$29,E$5:E$29) -> 2599061.4 | Q68: =SUMPRODUCT(Q$5:Q$29,I$5:I$29,E$5:E$29) -> 380134.65 | R68: =SUMPRODUCT(R$5:R$29,I$5:I$29,E$5:E$29) -> 584012.26 | S68: =SUMPRODUCT(S$5:S$29,I$5:I$29,E$5:E$29) -> 412218.5 | T68: =SUM(M68:S68) -> 5858217.9
B69: Plan Safe – deliverables | M69: =SUMPRODUCT(M$5:M$29,I$5:I$29,F$5:F$29) -> 14817.968 | N69: =SUMPRODUCT(N$5:N$29,I$5:I$29,F$5:F$29) -> 37457.438 | O69: =SUMPRODUCT(O$5:O$29,I$5:I$29,F$5:F$29) -> 66603.128 | P69: =SUMPRODUCT(P$5:P$29,I$5:I$29,F$5:F$29) -> 151716.49 | Q69: =SUMPRODUCT(Q$5:Q$29,I$5:I$29,F$5:F$29) -> 31943.1 | R69: =SUMPRODUCT(R$5:R$29,I$5:I$29,F$5:F$29) -> 44177.543 | S69: =SUMPRODUCT(S$5:S$29,I$5:I$29,F$5:F$29) -> 25238.798 | T69: =SUM(M69:S69) -> 371954.47
B70: INVAP – deliverables | M70: =SUMPRODUCT(M$5:M$29,I$5:I$29,G$5:G$29) -> 78836.1 | N70: =SUMPRODUCT(N$5:N$29,I$5:I$29,G$5:G$29) -> 0 | O70: =SUMPRODUCT(O$5:O$29,I$5:I$29,G$5:G$29) -> 0 | P70: =SUMPRODUCT(P$5:P$29,I$5:I$29,G$5:G$29) -> 0 | Q70: =SUMPRODUCT(Q$5:Q$29,I$5:I$29,G$5:G$29) -> 0 | R70: =SUMPRODUCT(R$5:R$29,I$5:I$29,G$5:G$29) -> 0 | S70: =SUMPRODUCT(S$5:S$29,I$5:I$29,G$5:G$29) -> 0 | T70: =SUM(M70:S70) -> 78836.1
B71: IDOM – deliverable S1 option | M71: =IF(Assumptions!$C$10="Yes",(IF(M$3="S1",Assumptions!$C$12*$I$6,0)-M$6*$I$6)*$E$6,0) -> 0 | N71: =IF(Assumptions!$C$10="Yes",(IF(N$3="S1",Assumptions!$C$12*$I$6,0)-N$6*$I$6)*$E$6,0) -> 0 | O71: =IF(Assumptions!$C$10="Yes",(IF(O$3="S1",Assumptions!$C$12*$I$6,0)-O$6*$I$6)*$E$6,0) -> 0 | P71: =IF(Assumptions!$C$10="Yes",(IF(P$3="S1",Assumptions!$C$12*$I$6,0)-P$6*$I$6)*$E$6,0) -> 0 | Q71: =IF(Assumptions!$C$10="Yes",(IF(Q$3="S1",Assumptions!$C$12*$I$6,0)-Q$6*$I$6)*$E$6,0) -> 0 | R71: =IF(Assumptions!$C$10="Yes",(IF(R$3="S1",Assumptions!$C$12*$I$6,0)-R$6*$I$6)*$E$6,0) -> 0 | S71: =IF(Assumptions!$C$10="Yes",(IF(S$3="S1",Assumptions!$C$12*$I$6,0)-S$6*$I$6)*$E$6,0) -> 0 | T71: =SUM(M71:S71) -> 0
B72: Plan Safe – deliverable S1 option | M72: =IF(Assumptions!$C$10="Yes",(IF(M$3="S1",Assumptions!$C$12*$I$6,0)-M$6*$I$6)*$F$6,0) -> 0 | N72: =IF(Assumptions!$C$10="Yes",(IF(N$3="S1",Assumptions!$C$12*$I$6,0)-N$6*$I$6)*$F$6,0) -> 0 | O72: =IF(Assumptions!$C$10="Yes",(IF(O$3="S1",Assumptions!$C$12*$I$6,0)-O$6*$I$6)*$F$6,0) -> 0 | P72: =IF(Assumptions!$C$10="Yes",(IF(P$3="S1",Assumptions!$C$12*$I$6,0)-P$6*$I$6)*$F$6,0) -> 0 | Q72: =IF(Assumptions!$C$10="Yes",(IF(Q$3="S1",Assumptions!$C$12*$I$6,0)-Q$6*$I$6)*$F$6,0) -> 0 | R72: =IF(Assumptions!$C$10="Yes",(IF(R$3="S1",Assumptions!$C$12*$I$6,0)-R$6*$I$6)*$F$6,0) -> 0 | S72: =IF(Assumptions!$C$10="Yes",(IF(S$3="S1",Assumptions!$C$12*$I$6,0)-S$6*$I$6)*$F$6,0) -> 0 | T72: =SUM(M72:S72) -> 0
B73: IDOM – Stage 2 rework release | M73: =IF(M$3="S2",(M68+M71)*(Assumptions!$C$6-Assumptions!$C$5)/(1+Assumptions!$C$5),0) -> 0 | N73: =IF(N$3="S2",(N68+N71)*(Assumptions!$C$6-Assumptions!$C$5)/(1+Assumptions!$C$5),0) -> -139096.5 | O73: =IF(O$3="S2",(O68+O71)*(Assumptions!$C$6-Assumptions!$C$5)/(1+Assumptions!$C$5),0) -> 0 | P73: =IF(P$3="S2",(P68+P71)*(Assumptions!$C$6-Assumptions!$C$5)/(1+Assumptions!$C$5),0) -> 0 | Q73: =IF(Q$3="S2",(Q68+Q71)*(Assumptions!$C$6-Assumptions!$C$5)/(1+Assumptions!$C$5),0) -> 0 | R73: =IF(R$3="S2",(R68+R71)*(Assumptions!$C$6-Assumptions!$C$5)/(1+Assumptions!$C$5),0) -> 0 | S73: =IF(S$3="S2",(S68+S71)*(Assumptions!$C$6-Assumptions!$C$5)/(1+Assumptions!$C$5),0) -> 0 | T73: =SUM(M73:S73) -> -139096.5
B74: IDOM – commercial discount | M74: =-Assumptions!$C$7*(M68+M71+M73) -> -5334.4683 | N74: =-Assumptions!$C$7*(N68+N71+N73) -> -15896.743 | O74: =-Assumptions!$C$7*(O68+O71+O73) -> -48516.571 | P74: =-Assumptions!$C$7*(P68+P71+P73) -> -103962.46 | Q74: =-Assumptions!$C$7*(Q68+Q71+Q73) -> -15205.386 | R74: =-Assumptions!$C$7*(R68+R71+R73) -> -23360.49 | S74: =-Assumptions!$C$7*(S68+S71+S73) -> -16488.74 | T74: =SUM(M74:S74) -> -228764.86
B75: IDOM – net | M75: =M68+M71+M73+M74 -> 128027.24 | N75: =N68+N71+N73+N74 -> 381521.84 | O75: =O68+O71+O73+O74 -> 1164397.7 | P75: =P68+P71+P73+P74 -> 2495099 | Q75: =Q68+Q71+Q73+Q74 -> 364929.26 | R75: =R68+R71+R73+R74 -> 560651.77 | S75: =S68+S71+S73+S74 -> 395729.76 | T75: =SUM(M75:S75) -> 5490356.5
B76: Plan Safe – net | M76: =M69+M72 -> 14817.968 | N76: =N69+N72 -> 37457.438 | O76: =O69+O72 -> 66603.128 | P76: =P69+P72 -> 151716.49 | Q76: =Q69+Q72 -> 31943.1 | R76: =R69+R72 -> 44177.543 | S76: =S69+S72 -> 25238.798 | T76: =SUM(M76:S76) -> 371954.47
B77: INVAP – net | M77: =M70 -> 78836.1 | N77: =N70 -> 0 | O77: =O70 -> 0 | P77: =P70 -> 0 | Q77: =Q70 -> 0 | R77: =R70 -> 0 | S77: =S70 -> 0 | T77: =SUM(M77:S77) -> 78836.1
B78: Total price | M78: =M75+M76+M77 -> 221681.31 | N78: =N75+N76+N77 -> 418979.28 | O78: =O75+O76+O77 -> 1231000.8 | P78: =P75+P76+P77 -> 2646815.5 | Q78: =Q75+Q76+Q77 -> 396872.36 | R78: =R75+R76+R77 -> 604829.31 | S78: =S75+S76+S77 -> 420968.56 | T78: =SUM(M78:S78) -> 5941147.1
B79: Hours – deliverables | M79: =SUMPRODUCT(T$5:T$29*(I$5:I$29>0)) -> 970 | N79: =SUMPRODUCT(U$5:U$29*(I$5:I$29>0)) -> 2485 | O79: =SUMPRODUCT(V$5:V$29*(I$5:I$29>0)) -> 5595 | P79: =SUMPRODUCT(W$5:W$29*(I$5:I$29>0)) -> 11955 | Q79: =SUMPRODUCT(X$5:X$29*(I$5:I$29>0)) -> 1795 | R79: =SUMPRODUCT(Y$5:Y$29*(I$5:I$29>0)) -> 2720 | S79: =SUMPRODUCT(Z$5:Z$29*(I$5:I$29>0)) -> 1895 | T79: =SUM(M79:S79) -> 27415
B80: Hours – deliverable S1 option | M80: =IF(Assumptions!$C$10="Yes",IF(M$3="S1",Assumptions!$C$11*($I$6>0),0)-T$6*($I$6>0),0) -> 0 | N80: =IF(Assumptions!$C$10="Yes",IF(N$3="S1",Assumptions!$C$11*($I$6>0),0)-U$6*($I$6>0),0) -> 0 | O80: =IF(Assumptions!$C$10="Yes",IF(O$3="S1",Assumptions!$C$11*($I$6>0),0)-V$6*($I$6>0),0) -> 0 | P80: =IF(Assumptions!$C$10="Yes",IF(P$3="S1",Assumptions!$C$11*($I$6>0),0)-W$6*($I$6>0),0) -> 0 | Q80: =IF(Assumptions!$C$10="Yes",IF(Q$3="S1",Assumptions!$C$11*($I$6>0),0)-X$6*($I$6>0),0) -> 0 | R80: =IF(Assumptions!$C$10="Yes",IF(R$3="S1",Assumptions!$C$11*($I$6>0),0)-Y$6*($I$6>0),0) -> 0 | S80: =IF(Assumptions!$C$10="Yes",IF(S$3="S1",Assumptions!$C$11*($I$6>0),0)-Z$6*($I$6>0),0) -> 0 | T80: =SUM(M80:S80) -> 0
B81: Hours – total | M81: =M79+M80 -> 970 | N81: =N79+N80 -> 2485 | O81: =O79+O80 -> 5595 | P81: =P79+P80 -> 11955 | Q81: =Q79+Q80 -> 1795 | R81: =R79+R80 -> 2720 | S81: =S79+S80 -> 1895 | T81: =SUM(M81:S81) -> 27415
A84: Scenario 3 — Without Plan Safe HF tasks and SSC | M84: S1 | N84: S2 | O84: S3 | P84: S4 | Q84: S5 | R84: S6 | S84: S7 | T84: Total
B85: IDOM – deliverables | M85: =SUMPRODUCT(M$5:M$29,J$5:J$29,E$5:E$29) -> 133361.71 | N85: =SUMPRODUCT(N$5:N$29,J$5:J$29,E$5:E$29) -> 436779.26 | O85: =SUMPRODUCT(O$5:O$29,J$5:J$29,E$5:E$29) -> 942471.02 | P85: =SUMPRODUCT(P$5:P$29,J$5:J$29,E$5:E$29) -> 2006652.5 | Q85: =SUMPRODUCT(Q$5:Q$29,J$5:J$29,E$5:E$29) -> 148043.7 | R85: =SUMPRODUCT(R$5:R$29,J$5:J$29,E$5:E$29) -> 334653.22 | S85: =SUMPRODUCT(S$5:S$29,J$5:J$29,E$5:E$29) -> 281937.18 | T85: =SUM(M85:S85) -> 4283898.6
B86: Plan Safe – deliverables | M86: =SUMPRODUCT(M$5:M$29,J$5:J$29,F$5:F$29) -> 14817.968 | N86: =SUMPRODUCT(N$5:N$29,J$5:J$29,F$5:F$29) -> 37457.438 | O86: =SUMPRODUCT(O$5:O$29,J$5:J$29,F$5:F$29) -> 58558.552 | P86: =SUMPRODUCT(P$5:P$29,J$5:J$29,F$5:F$29) -> 119276.17 | Q86: =SUMPRODUCT(Q$5:Q$29,J$5:J$29,F$5:F$29) -> 16449.3 | R86: =SUMPRODUCT(R$5:R$29,J$5:J$29,F$5:F$29) -> 28161.158 | S86: =SUMPRODUCT(S$5:S$29,J$5:J$29,F$5:F$29) -> 19229.07 | T86: =SUM(M86:S86) -> 293949.65
B87: INVAP – deliverables | M87: =SUMPRODUCT(M$5:M$29,J$5:J$29,G$5:G$29) -> 78836.1 | N87: =SUMPRODUCT(N$5:N$29,J$5:J$29,G$5:G$29) -> 0 | O87: =SUMPRODUCT(O$5:O$29,J$5:J$29,G$5:G$29) -> 0 | P87: =SUMPRODUCT(P$5:P$29,J$5:J$29,G$5:G$29) -> 0 | Q87: =SUMPRODUCT(Q$5:Q$29,J$5:J$29,G$5:G$29) -> 0 | R87: =SUMPRODUCT(R$5:R$29,J$5:J$29,G$5:G$29) -> 0 | S87: =SUMPRODUCT(S$5:S$29,J$5:J$29,G$5:G$29) -> 0 | T87: =SUM(M87:S87) -> 78836.1
B88: IDOM – deliverable S1 option | M88: =IF(Assumptions!$C$10="Yes",(IF(M$3="S1",Assumptions!$C$12*$J$6,0)-M$6*$J$6)*$E$6,0) -> 0 | N88: =IF(Assumptions!$C$10="Yes",(IF(N$3="S1",Assumptions!$C$12*$J$6,0)-N$6*$J$6)*$E$6,0) -> 0 | O88: =IF(Assumptions!$C$10="Yes",(IF(O$3="S1",Assumptions!$C$12*$J$6,0)-O$6*$J$6)*$E$6,0) -> 0 | P88: =IF(Assumptions!$C$10="Yes",(IF(P$3="S1",Assumptions!$C$12*$J$6,0)-P$6*$J$6)*$E$6,0) -> 0 | Q88: =IF(Assumptions!$C$10="Yes",(IF(Q$3="S1",Assumptions!$C$12*$J$6,0)-Q$6*$J$6)*$E$6,0) -> 0 | R88: =IF(Assumptions!$C$10="Yes",(IF(R$3="S1",Assumptions!$C$12*$J$6,0)-R$6*$J$6)*$E$6,0) -> 0 | S88: =IF(Assumptions!$C$10="Yes",(IF(S$3="S1",Assumptions!$C$12*$J$6,0)-S$6*$J$6)*$E$6,0) -> 0 | T88: =SUM(M88:S88) -> 0
B89: Plan Safe – deliverable S1 option | M89: =IF(Assumptions!$C$10="Yes",(IF(M$3="S1",Assumptions!$C$12*$J$6,0)-M$6*$J$6)*$F$6,0) -> 0 | N89: =IF(Assumptions!$C$10="Yes",(IF(N$3="S1",Assumptions!$C$12*$J$6,0)-N$6*$J$6)*$F$6,0) -> 0 | O89: =IF(Assumptions!$C$10="Yes",(IF(O$3="S1",Assumptions!$C$12*$J$6,0)-O$6*$J$6)*$F$6,0) -> 0 | P89: =IF(Assumptions!$C$10="Yes",(IF(P$3="S1",Assumptions!$C$12*$J$6,0)-P$6*$J$6)*$F$6,0) -> 0 | Q89: =IF(Assumptions!$C$10="Yes",(IF(Q$3="S1",Assumptions!$C$12*$J$6,0)-Q$6*$J$6)*$F$6,0) -> 0 | R89: =IF(Assumptions!$C$10="Yes",(IF(R$3="S1",Assumptions!$C$12*$J$6,0)-R$6*$J$6)*$F$6,0) -> 0 | S89: =IF(Assumptions!$C$10="Yes",(IF(S$3="S1",Assumptions!$C$12*$J$6,0)-S$6*$J$6)*$F$6,0) -> 0 | T89: =SUM(M89:S89) -> 0
B90: IDOM – Stage 2 rework release | M90: =IF(M$3="S2",(M85+M88)*(Assumptions!$C$6-Assumptions!$C$5)/(1+Assumptions!$C$5),0) -> 0 | N90: =IF(N$3="S2",(N85+N88)*(Assumptions!$C$6-Assumptions!$C$5)/(1+Assumptions!$C$5),0) -> -113239.07 | O90: =IF(O$3="S2",(O85+O88)*(Assumptions!$C$6-Assumptions!$C$5)/(1+Assumptions!$C$5),0) -> 0 | P90: =IF(P$3="S2",(P85+P88)*(Assumptions!$C$6-Assumptions!$C$5)/(1+Assumptions!$C$5),0) -> 0 | Q90: =IF(Q$3="S2",(Q85+Q88)*(Assumptions!$C$6-Assumptions!$C$5)/(1+Assumptions!$C$5),0) -> 0 | R90: =IF(R$3="S2",(R85+R88)*(Assumptions!$C$6-Assumptions!$C$5)/(1+Assumptions!$C$5),0) -> 0 | S90: =IF(S$3="S2",(S85+S88)*(Assumptions!$C$6-Assumptions!$C$5)/(1+Assumptions!$C$5),0) -> 0 | T90: =SUM(M90:S90) -> -113239.07
B91: IDOM – commercial discount | M91: =-Assumptions!$C$7*(M85+M88+M90) -> -5334.4683 | N91: =-Assumptions!$C$7*(N85+N88+N90) -> -12941.608 | O91: =-Assumptions!$C$7*(O85+O88+O90) -> -37698.841 | P91: =-Assumptions!$C$7*(P85+P88+P90) -> -80266.101 | Q91: =-Assumptions!$C$7*(Q85+Q88+Q90) -> -5921.748 | R91: =-Assumptions!$C$7*(R85+R88+R90) -> -13386.129 | S91: =-Assumptions!$C$7*(S85+S88+S90) -> -11277.487 | T91: =SUM(M91:S91) -> -166826.38
B92: IDOM – net | M92: =M85+M88+M90+M91 -> 128027.24 | N92: =N85+N88+N90+N91 -> 310598.59 | O92: =O85+O88+O90+O91 -> 904772.18 | P92: =P85+P88+P90+P91 -> 1926386.4 | Q92: =Q85+Q88+Q90+Q91 -> 142121.95 | R92: =R85+R88+R90+R91 -> 321267.09 | S92: =S85+S88+S90+S91 -> 270659.69 | T92: =SUM(M92:S92) -> 4003833.2
B93: Plan Safe – net | M93: =M86+M89 -> 14817.968 | N93: =N86+N89 -> 37457.438 | O93: =O86+O89 -> 58558.552 | P93: =P86+P89 -> 119276.17 | Q93: =Q86+Q89 -> 16449.3 | R93: =R86+R89 -> 28161.158 | S93: =S86+S89 -> 19229.07 | T93: =SUM(M93:S93) -> 293949.65
B94: INVAP – net | M94: =M87 -> 78836.1 | N94: =N87 -> 0 | O94: =O87 -> 0 | P94: =P87 -> 0 | Q94: =Q87 -> 0 | R94: =R87 -> 0 | S94: =S87 -> 0 | T94: =SUM(M94:S94) -> 78836.1
B95: Total price | M95: =M92+M93+M94 -> 221681.31 | N95: =N92+N93+N94 -> 348056.02 | O95: =O92+O93+O94 -> 963330.73 | P95: =P92+P93+P94 -> 2045662.6 | Q95: =Q92+Q93+Q94 -> 158571.25 | R95: =R92+R93+R94 -> 349428.25 | S95: =S92+S93+S94 -> 289888.76 | T95: =SUM(M95:S95) -> 4376618.9
B96: Hours – deliverables | M96: =SUMPRODUCT(T$5:T$29*(J$5:J$29>0)) -> 970 | N96: =SUMPRODUCT(U$5:U$29*(J$5:J$29>0)) -> 2050 | O96: =SUMPRODUCT(V$5:V$29*(J$5:J$29>0)) -> 4380 | P96: =SUMPRODUCT(W$5:W$29*(J$5:J$29>0)) -> 9235 | Q96: =SUMPRODUCT(X$5:X$29*(J$5:J$29>0)) -> 715 | R96: =SUMPRODUCT(Y$5:Y$29*(J$5:J$29>0)) -> 1565 | S96: =SUMPRODUCT(Z$5:Z$29*(J$5:J$29>0)) -> 1305 | T96: =SUM(M96:S96) -> 20220
B97: Hours – deliverable S1 option | M97: =IF(Assumptions!$C$10="Yes",IF(M$3="S1",Assumptions!$C$11*($J$6>0),0)-T$6*($J$6>0),0) -> 0 | N97: =IF(Assumptions!$C$10="Yes",IF(N$3="S1",Assumptions!$C$11*($J$6>0),0)-U$6*($J$6>0),0) -> 0 | O97: =IF(Assumptions!$C$10="Yes",IF(O$3="S1",Assumptions!$C$11*($J$6>0),0)-V$6*($J$6>0),0) -> 0 | P97: =IF(Assumptions!$C$10="Yes",IF(P$3="S1",Assumptions!$C$11*($J$6>0),0)-W$6*($J$6>0),0) -> 0 | Q97: =IF(Assumptions!$C$10="Yes",IF(Q$3="S1",Assumptions!$C$11*($J$6>0),0)-X$6*($J$6>0),0) -> 0 | R97: =IF(Assumptions!$C$10="Yes",IF(R$3="S1",Assumptions!$C$11*($J$6>0),0)-Y$6*($J$6>0),0) -> 0 | S97: =IF(Assumptions!$C$10="Yes",IF(S$3="S1",Assumptions!$C$11*($J$6>0),0)-Z$6*($J$6>0),0) -> 0 | T97: =SUM(M97:S97) -> 0
B98: Hours – total | M98: =M96+M97 -> 970 | N98: =N96+N97 -> 2050 | O98: =O96+O97 -> 4380 | P98: =P96+P97 -> 9235 | Q98: =Q96+Q97 -> 715 | R98: =R96+R97 -> 1565 | S98: =S96+S97 -> 1305 | T98: =SUM(M98:S98) -> 20220
A101: Scenario 4 — Without SSC, Plan Safe HF tasks at reduced price | M101: S1 | N101: S2 | O101: S3 | P101: S4 | Q101: S5 | R101: S6 | S101: S7 | T101: Total
B102: IDOM – deliverables | M102: =SUMPRODUCT(M$5:M$29,K$5:K$29,E$5:E$29) -> 133361.71 | N102: =SUMPRODUCT(N$5:N$29,K$5:K$29,E$5:E$29) -> 436779.26 | O102: =SUMPRODUCT(O$5:O$29,K$5:K$29,E$5:E$29) -> 942471.02 | P102: =SUMPRODUCT(P$5:P$29,K$5:K$29,E$5:E$29) -> 2006652.5 | Q102: =SUMPRODUCT(Q$5:Q$29,K$5:K$29,E$5:E$29) -> 148043.7 | R102: =SUMPRODUCT(R$5:R$29,K$5:K$29,E$5:E$29) -> 334653.22 | S102: =SUMPRODUCT(S$5:S$29,K$5:K$29,E$5:E$29) -> 281937.18 | T102: =SUM(M102:S102) -> 4283898.6
B103: Plan Safe – deliverables | M103: =SUMPRODUCT(M$5:M$29,K$5:K$29,F$5:F$29) -> 68851.492 | N103: =SUMPRODUCT(N$5:N$29,K$5:K$29,F$5:F$29) -> 116890.73 | O103: =SUMPRODUCT(O$5:O$29,K$5:K$29,F$5:F$29) -> 153461.75 | P103: =SUMPRODUCT(P$5:P$29,K$5:K$29,F$5:F$29) -> 335828.48 | Q103: =SUMPRODUCT(Q$5:Q$29,K$5:K$29,F$5:F$29) -> 80715.863 | R103: =SUMPRODUCT(R$5:R$29,K$5:K$29,F$5:F$29) -> 101606.03 | S103: =SUMPRODUCT(S$5:S$29,K$5:K$29,F$5:F$29) -> 47453.07 | T103: =SUM(M103:S103) -> 904807.42
B104: INVAP – deliverables | M104: =SUMPRODUCT(M$5:M$29,K$5:K$29,G$5:G$29) -> 78836.1 | N104: =SUMPRODUCT(N$5:N$29,K$5:K$29,G$5:G$29) -> 0 | O104: =SUMPRODUCT(O$5:O$29,K$5:K$29,G$5:G$29) -> 0 | P104: =SUMPRODUCT(P$5:P$29,K$5:K$29,G$5:G$29) -> 0 | Q104: =SUMPRODUCT(Q$5:Q$29,K$5:K$29,G$5:G$29) -> 0 | R104: =SUMPRODUCT(R$5:R$29,K$5:K$29,G$5:G$29) -> 0 | S104: =SUMPRODUCT(S$5:S$29,K$5:K$29,G$5:G$29) -> 0 | T104: =SUM(M104:S104) -> 78836.1
B105: IDOM – deliverable S1 option | M105: =IF(Assumptions!$C$10="Yes",(IF(M$3="S1",Assumptions!$C$12*$K$6,0)-M$6*$K$6)*$E$6,0) -> 0 | N105: =IF(Assumptions!$C$10="Yes",(IF(N$3="S1",Assumptions!$C$12*$K$6,0)-N$6*$K$6)*$E$6,0) -> 0 | O105: =IF(Assumptions!$C$10="Yes",(IF(O$3="S1",Assumptions!$C$12*$K$6,0)-O$6*$K$6)*$E$6,0) -> 0 | P105: =IF(Assumptions!$C$10="Yes",(IF(P$3="S1",Assumptions!$C$12*$K$6,0)-P$6*$K$6)*$E$6,0) -> 0 | Q105: =IF(Assumptions!$C$10="Yes",(IF(Q$3="S1",Assumptions!$C$12*$K$6,0)-Q$6*$K$6)*$E$6,0) -> 0 | R105: =IF(Assumptions!$C$10="Yes",(IF(R$3="S1",Assumptions!$C$12*$K$6,0)-R$6*$K$6)*$E$6,0) -> 0 | S105: =IF(Assumptions!$C$10="Yes",(IF(S$3="S1",Assumptions!$C$12*$K$6,0)-S$6*$K$6)*$E$6,0) -> 0 | T105: =SUM(M105:S105) -> 0
B106: Plan Safe – deliverable S1 option | M106: =IF(Assumptions!$C$10="Yes",(IF(M$3="S1",Assumptions!$C$12*$K$6,0)-M$6*$K$6)*$F$6,0) -> 0 | N106: =IF(Assumptions!$C$10="Yes",(IF(N$3="S1",Assumptions!$C$12*$K$6,0)-N$6*$K$6)*$F$6,0) -> 0 | O106: =IF(Assumptions!$C$10="Yes",(IF(O$3="S1",Assumptions!$C$12*$K$6,0)-O$6*$K$6)*$F$6,0) -> 0 | P106: =IF(Assumptions!$C$10="Yes",(IF(P$3="S1",Assumptions!$C$12*$K$6,0)-P$6*$K$6)*$F$6,0) -> 0 | Q106: =IF(Assumptions!$C$10="Yes",(IF(Q$3="S1",Assumptions!$C$12*$K$6,0)-Q$6*$K$6)*$F$6,0) -> 0 | R106: =IF(Assumptions!$C$10="Yes",(IF(R$3="S1",Assumptions!$C$12*$K$6,0)-R$6*$K$6)*$F$6,0) -> 0 | S106: =IF(Assumptions!$C$10="Yes",(IF(S$3="S1",Assumptions!$C$12*$K$6,0)-S$6*$K$6)*$F$6,0) -> 0 | T106: =SUM(M106:S106) -> 0
B107: IDOM – Stage 2 rework release | M107: =IF(M$3="S2",(M102+M105)*(Assumptions!$C$6-Assumptions!$C$5)/(1+Assumptions!$C$5),0) -> 0 | N107: =IF(N$3="S2",(N102+N105)*(Assumptions!$C$6-Assumptions!$C$5)/(1+Assumptions!$C$5),0) -> -113239.07 | O107: =IF(O$3="S2",(O102+O105)*(Assumptions!$C$6-Assumptions!$C$5)/(1+Assumptions!$C$5),0) -> 0 | P107: =IF(P$3="S2",(P102+P105)*(Assumptions!$C$6-Assumptions!$C$5)/(1+Assumptions!$C$5),0) -> 0 | Q107: =IF(Q$3="S2",(Q102+Q105)*(Assumptions!$C$6-Assumptions!$C$5)/(1+Assumptions!$C$5),0) -> 0 | R107: =IF(R$3="S2",(R102+R105)*(Assumptions!$C$6-Assumptions!$C$5)/(1+Assumptions!$C$5),0) -> 0 | S107: =IF(S$3="S2",(S102+S105)*(Assumptions!$C$6-Assumptions!$C$5)/(1+Assumptions!$C$5),0) -> 0 | T107: =SUM(M107:S107) -> -113239.07
B108: IDOM – commercial discount | M108: =-Assumptions!$C$7*(M102+M105+M107) -> -5334.4683 | N108: =-Assumptions!$C$7*(N102+N105+N107) -> -12941.608 | O108: =-Assumptions!$C$7*(O102+O105+O107) -> -37698.841 | P108: =-Assumptions!$C$7*(P102+P105+P107) -> -80266.101 | Q108: =-Assumptions!$C$7*(Q102+Q105+Q107) -> -5921.748 | R108: =-Assumptions!$C$7*(R102+R105+R107) -> -13386.129 | S108: =-Assumptions!$C$7*(S102+S105+S107) -> -11277.487 | T108: =SUM(M108:S108) -> -166826.38
B109: IDOM – net | M109: =M102+M105+M107+M108 -> 128027.24 | N109: =N102+N105+N107+N108 -> 310598.59 | O109: =O102+O105+O107+O108 -> 904772.18 | P109: =P102+P105+P107+P108 -> 1926386.4 | Q109: =Q102+Q105+Q107+Q108 -> 142121.95 | R109: =R102+R105+R107+R108 -> 321267.09 | S109: =S102+S105+S107+S108 -> 270659.69 | T109: =SUM(M109:S109) -> 4003833.2
B110: Plan Safe – net | M110: =M103+M106 -> 68851.492 | N110: =N103+N106 -> 116890.73 | O110: =O103+O106 -> 153461.75 | P110: =P103+P106 -> 335828.48 | Q110: =Q103+Q106 -> 80715.863 | R110: =R103+R106 -> 101606.03 | S110: =S103+S106 -> 47453.07 | T110: =SUM(M110:S110) -> 904807.42
B111: INVAP – net | M111: =M104 -> 78836.1 | N111: =N104 -> 0 | O111: =O104 -> 0 | P111: =P104 -> 0 | Q111: =Q104 -> 0 | R111: =R104 -> 0 | S111: =S104 -> 0 | T111: =SUM(M111:S111) -> 78836.1
B112: Total price | M112: =M109+M110+M111 -> 275714.83 | N112: =N109+N110+N111 -> 427489.31 | O112: =O109+O110+O111 -> 1058233.9 | P112: =P109+P110+P111 -> 2262214.9 | Q112: =Q109+Q110+Q111 -> 222837.81 | R112: =R109+R110+R111 -> 422873.12 | S112: =S109+S110+S111 -> 318112.76 | T112: =SUM(M112:S112) -> 4987476.7
B113: Hours – deliverables | M113: =SUMPRODUCT(T$5:T$29*(K$5:K$29>0)) -> 1435 | N113: =SUMPRODUCT(U$5:U$29*(K$5:K$29>0)) -> 2735 | O113: =SUMPRODUCT(V$5:V$29*(K$5:K$29>0)) -> 5205 | P113: =SUMPRODUCT(W$5:W$29*(K$5:K$29>0)) -> 11122 | Q113: =SUMPRODUCT(X$5:X$29*(K$5:K$29>0)) -> 1275 | R113: =SUMPRODUCT(Y$5:Y$29*(K$5:K$29>0)) -> 2205 | S113: =SUMPRODUCT(Z$5:Z$29*(K$5:K$29>0)) -> 1550 | T113: =SUM(M113:S113) -> 25527
B114: Hours – deliverable S1 option | M114: =IF(Assumptions!$C$10="Yes",IF(M$3="S1",Assumptions!$C$11*($K$6>0),0)-T$6*($K$6>0),0) -> 0 | N114: =IF(Assumptions!$C$10="Yes",IF(N$3="S1",Assumptions!$C$11*($K$6>0),0)-U$6*($K$6>0),0) -> 0 | O114: =IF(Assumptions!$C$10="Yes",IF(O$3="S1",Assumptions!$C$11*($K$6>0),0)-V$6*($K$6>0),0) -> 0 | P114: =IF(Assumptions!$C$10="Yes",IF(P$3="S1",Assumptions!$C$11*($K$6>0),0)-W$6*($K$6>0),0) -> 0 | Q114: =IF(Assumptions!$C$10="Yes",IF(Q$3="S1",Assumptions!$C$11*($K$6>0),0)-X$6*($K$6>0),0) -> 0 | R114: =IF(Assumptions!$C$10="Yes",IF(R$3="S1",Assumptions!$C$11*($K$6>0),0)-Y$6*($K$6>0),0) -> 0 | S114: =IF(Assumptions!$C$10="Yes",IF(S$3="S1",Assumptions!$C$11*($K$6>0),0)-Z$6*($K$6>0),0) -> 0 | T114: =SUM(M114:S114) -> 0
B115: Hours – total | M115: =M113+M114 -> 1435 | N115: =N113+N114 -> 2735 | O115: =O113+O114 -> 5205 | P115: =P113+P114 -> 11122 | Q115: =Q113+Q114 -> 1275 | R115: =R113+R114 -> 2205 | S115: =S113+S114 -> 1550 | T115: =SUM(M115:S115) -> 25527
A118: Scenario 5 — Plan Safe as offered, without SSC | M118: S1 | N118: S2 | O118: S3 | P118: S4 | Q118: S5 | R118: S6 | S118: S7 | T118: Total
B119: IDOM – deliverables | M119: =SUMPRODUCT(M$5:M$29,L$5:L$29,E$5:E$29) -> 133361.71 | N119: =SUMPRODUCT(N$5:N$29,L$5:L$29,E$5:E$29) -> 436779.26 | O119: =SUMPRODUCT(O$5:O$29,L$5:L$29,E$5:E$29) -> 942471.02 | P119: =SUMPRODUCT(P$5:P$29,L$5:L$29,E$5:E$29) -> 2006652.5 | Q119: =SUMPRODUCT(Q$5:Q$29,L$5:L$29,E$5:E$29) -> 148043.7 | R119: =SUMPRODUCT(R$5:R$29,L$5:L$29,E$5:E$29) -> 334653.22 | S119: =SUMPRODUCT(S$5:S$29,L$5:L$29,E$5:E$29) -> 281937.18 | T119: =SUM(M119:S119) -> 4283898.6
B120: Plan Safe – deliverables | M120: =SUMPRODUCT(M$5:M$29,L$5:L$29,F$5:F$29) -> 122885.02 | N120: =SUMPRODUCT(N$5:N$29,L$5:L$29,F$5:F$29) -> 196324.01 | O120: =SUMPRODUCT(O$5:O$29,L$5:L$29,F$5:F$29) -> 248364.95 | P120: =SUMPRODUCT(P$5:P$29,L$5:L$29,F$5:F$29) -> 552380.8 | Q120: =SUMPRODUCT(Q$5:Q$29,L$5:L$29,F$5:F$29) -> 144982.42 | R120: =SUMPRODUCT(R$5:R$29,L$5:L$29,F$5:F$29) -> 175050.91 | S120: =SUMPRODUCT(S$5:S$29,L$5:L$29,F$5:F$29) -> 75677.07 | T120: =SUM(M120:S120) -> 1515665.2
B121: INVAP – deliverables | M121: =SUMPRODUCT(M$5:M$29,L$5:L$29,G$5:G$29) -> 78836.1 | N121: =SUMPRODUCT(N$5:N$29,L$5:L$29,G$5:G$29) -> 0 | O121: =SUMPRODUCT(O$5:O$29,L$5:L$29,G$5:G$29) -> 0 | P121: =SUMPRODUCT(P$5:P$29,L$5:L$29,G$5:G$29) -> 0 | Q121: =SUMPRODUCT(Q$5:Q$29,L$5:L$29,G$5:G$29) -> 0 | R121: =SUMPRODUCT(R$5:R$29,L$5:L$29,G$5:G$29) -> 0 | S121: =SUMPRODUCT(S$5:S$29,L$5:L$29,G$5:G$29) -> 0 | T121: =SUM(M121:S121) -> 78836.1
...

Sheet Data
A1: Source data: offer hours by deliverable, stage and profile, at the offer sell rates
A2: Source: IDOM bottom-up cost model of the offer (NMMP tool, «Oferta mayo»). Rates in A$/h, discounted, including the 1.05 factor.
A4: Profile | B4: Description | C4: Rate A$/h | E4: Deliverable | F4: Stage | G4: Profile | H4: Hours | I4: Rate A$/h | J4: Amount A$
A5: P7 | B5: Associate Director 2 | C5: 256.515 | E5: E94 | F5: S2 | G5: P7 | H5: 20 | I5: =INDEX($C$5:$C$26,MATCH(G5,$A$5:$A$26,0)) -> 256.515 | J5: =H5*I5 -> 5130.3
A6: P6 | B6: Principal Professional | C6: 236.67 | E6: E94 | F6: S2 | G6: P6 | H6: 40 | I6: =INDEX($C$5:$C$26,MATCH(G6,$A$5:$A$26,0)) -> 236.67 | J6: =H6*I6 -> 9466.8
A7: P5 | B7: Senior Professional 1 | C7: 224.175 | E7: E94 | F7: S2 | G7: P5 | H7: 40 | I7: =INDEX($C$5:$C$26,MATCH(G7,$A$5:$A$26,0)) -> 224.175 | J7: =H7*I7 -> 8967
A8: P4 | B8: Senior Professional 2 | C8: 206.535 | E8: E94 | F8: S2 | G8: TO3 | H8: 55 | I8: =INDEX($C$5:$C$26,MATCH(G8,$A$5:$A$26,0)) -> 145.53 | J8: =H8*I8 -> 8004.15
A9: TO4 | B9: Senior Technical Officer | C9: 182.28 | E9: E94 | F9: S2 | G9: TO2 | H9: 30 | I9: =INDEX($C$5:$C$26,MATCH(G9,$A$5:$A$26,0)) -> 121.275 | J9: =H9*I9 -> 3638.25
A10: TO3 | B10: Technical Officer 1 | C10: 145.53 | E10: E94 | F10: S3 | G10: P7 | H10: 30 | I10: =INDEX($C$5:$C$26,MATCH(G10,$A$5:$A$26,0)) -> 256.515 | J10: =H10*I10 -> 7695.45
A11: TO2 | B11: Technical Officer 2 | C11: 121.275 | E11: E94 | F11: S3 | G11: P6 | H11: 55 | I11: =INDEX($C$5:$C$26,MATCH(G11,$A$5:$A$26,0)) -> 236.67 | J11: =H11*I11 -> 13016.85
A12: PM3 | B12: Project Director / Project Manager | C12: 360.15 | E12: E94 | F12: S3 | G12: P5 | H12: 75 | I12: =INDEX($C$5:$C$26,MATCH(G12,$A$5:$A$26,0)) -> 224.175 | J12: =H12*I12 -> 16813.125
A13: PM2 | B13: Senior Executive | C13: 349.125 | E13: E94 | F13: S3 | G13: TO3 | H13: 105 | I13: =INDEX($C$5:$C$26,MATCH(G13,$A$5:$A$26,0)) -> 145.53 | J13: =H13*I13 -> 15280.65
A14: PM1 | B14: Discipline Lead / Design Manager | C14: 323.4 | E14: E94 | F14: S3 | G14: TO2 | H14: 50 | I14: =INDEX($C$5:$C$26,MATCH(G14,$A$5:$A$26,0)) -> 121.275 | J14: =H14*I14 -> 6063.75
A15: P10 | B15: Industry / International Specialist | C15: 360.15 | E15: E94 | F15: S4 | G15: P7 | H15: 35 | I15: =INDEX($C$5:$C$26,MATCH(G15,$A$5:$A$26,0)) -> 256.515 | J15: =H15*I15 -> 8978.025
A16: P9 | B16: Technical Director | C16: 293.265 | E16: E94 | F16: S4 | G16: P6 | H16: 80 | I16: =INDEX($C$5:$C$26,MATCH(G16,$A$5:$A$26,0)) -> 236.67 | J16: =H16*I16 -> 18933.6
... A26: A1 | B26: Admin Assistant | C26: 66.885 | E26: S1 | F26: S2 | G26: P5 | H26: 295 | I26: =INDEX($C$5:$C$26,MATCH(G26,$A$5:$A$26,0)) -> 224.175 | J26: =H26*I26 -> 66131.625
E27: S1 | F27: S2 | G27: P4 | H27: 130 | I27: =INDEX($C$5:$C$26,MATCH(G27,$A$5:$A$26,0)) -> 206.535 | J27: =H27*I27 -> 26849.55
E28: S9 | F28: S3 | G28: P7 | H28: 275 | I28: =INDEX($C$5:$C$26,MATCH(G28,$A$5:$A$26,0)) -> 256.515 | J28: =H28*I28 -> 70541.625
E29: S9 | F29: S3 | G29: P6 | H29: 505 | I29: =INDEX($C$5:$C$26,MATCH(G29,$A$5:$A$26,0)) -> 236.67 | J29: =H29*I29 -> 119518.35
E30: S9 | F30: S3 | G30: P5 | H30: 475 | I30: =INDEX($C$5:$C$26,MATCH(G30,$A$5:$A$26,0)) -> 224.175 | J30: =H30*I30 -> 106483.12
E31: S9 | F31: S3 | G31: P4 | H31: 130 | I31: =INDEX($C$5:$C$26,MATCH(G31,$A$5:$A$26,0)) -> 206.535 | J31: =H31*I31 -> 26849.55
E32: S9 | F32: S4 | G32: P7 | H32: 210 | I32: =INDEX($C$5:$C$26,MATCH(G32,$A$5:$A$26,0)) -> 256.515 | J32: =H32*I32 -> 53868.15
E33: S9 | F33: S4 | G33: P6 | H33: 370 | I33: =INDEX($C$5:$C$26,MATCH(G33,$A$5:$A$26,0)) -> 236.67 | J33: =H33*I33 -> 87567.9
E34: S9 | F34: S4 | G34: P5 | H34: 360 | I34: =INDEX($C$5:$C$26,MATCH(G34,$A$5:$A$26,0)) -> 224.175 | J34: =H34*I34 -> 80703
E35: S9 | F35: S4 | G35: P4 | H35: 75 | I35: =INDEX($C$5:$C$26,MATCH(G35,$A$5:$A$26,0)) -> 206.535 | J35: =H35*I35 -> 15490.125
E36: S9 | F36: S6 | G36: P7 | H36: 130 | I36: =INDEX($C$5:$C$26,MATCH(G36,$A$5:$A$26,0)) -> 256.515 | J36: =H36*I36 -> 33346.95
E37: S9 | F37: S6 | G37: P6 | H37: 120 | I37: =INDEX($C$5:$C$26,MATCH(G37,$A$5:$A$26,0)) -> 236.67 | J37: =H37*I37 -> 28400.4
E38: S9 | F38: S6 | G38: P5 | H38: 105 | I38: =INDEX($C$5:$C$26,MATCH(G38,$A$5:$A$26,0)) -> 224.175 | J38: =H38*I38 -> 23538.375
... E291: S30 | F291: S7 | G291: P4 | H291: 40 | I291: =INDEX($C$5:$C$26,MATCH(G291,$A$5:$A$26,0)) -> 206.535 | J291: =H291*I291 -> 8261.4
